Workbook

Sheet Resumen
A1: CONTROL OPERATIVO ORVANN | E1: Otras referencias (Conocidas pero de nicho) | H1: Lunes | I1: Martes | J1: Miercoles | K1: Jueves | L1: Viernes | M1: Sábado | N1: Domingo
A2: Última actualización | B2: 46131 | E2: Pulp Fiction (1994)
E3: Pedro navaja | G3: 10:30 - 11:00 | H3: Kathe | I3: Kathe | J3: Kathe | K3: Kathe | L3: Kathe | M3: Andrés | O3: Kathe
A4: RESUMEN FINANCIERO | E4: Léon: The Professional | G4: 11:00 - 11.30 | H4: Kathe | I4: Kathe | J4: Kathe | K4: Kathe | L4: Kathe | M4: Andrés | O4: JP
A5: Inventario a costo: | B5: =Inventario!J2 -> 7194000 | E5: Ciudad de Dios | G5: 11.30 - 12:00 | H5: Kathe | I5: Kathe | J5: Kathe | K5: Kathe | L5: Kathe | M5: Andrés | O5: Trabajador
A6: Inventario a precio venta: | B6: =Inventario!K2 -> 14780000 | E6: Charles Bukowski (Literatura Cruda) | G6: 12:00 - 12:30 | H6: Kathe | I6: Kathe | J6: Kathe | K6: Kathe | L6: Kathe | M6: Andrés
A7: Ventas del mes: | B7: =SUMIF(Ventas!A:A,">="&DATE(YEAR(TODAY()),MONTH(TODAY()),1),Ventas!E:E) -> 3120000 | E7: Héctor Lavoe. Estilo "Vinyl Cover" | G7: 12:30 - 1:00 | H7: Kathe | I7: Kathe | J7: Kathe | K7: Kathe | L7: Kathe | M7: Andrés
A8: Gastos del mes: | B8: =SUMIF(Gastos!A:A,">="&DATE(YEAR(TODAY()),MONTH(TODAY()),1),Gastos!C:C) -> 5073445 | E8: Gabo y Cien Años de Soledad | G8: 1:00 - 1:30 | H8: Kathe | I8: Kathe | J8: Kathe | K8: Kathe | L8: Kathe | M8: Andrés
A9: Cuentas por pagar: | B9: =SUMIF('Pedidos Proveedores'!G:G,"Pendiente",'Pedidos Proveedores'!F:F) -> 0 | E9: Blade Runner (1982). | G9: 1:30 - 2:00 | H9: Kathe | I9: Kathe | J9: Kathe | K9: Kathe | L9: Andrés | M9: Andrés
A10: Utilidad bruta mes: | B10: =B7-SUMIF(Ventas!A:A,">="&DATE(YEAR(TODAY()),MONTH(TODAY()),1),Ventas!D:D)-B8 -> -3347445 | E10: Mercedes Sosa y LA FANIA. Volver a los 17 | G10: 2:00 - 2:30 | H10: Andrés | I10: Andrés | J10: Andrés | K10: Andrés | L10: Andrés | M10: Andrés
A11: Ventas Totales: | B11: =SUM(Ventas!E2:E1002) -> 11278000 | E11: Taxi Driver | G11: 2:30 - 3:00 | H11: JP | I11: JP | J11: JP | K11: Andrés | L11: Andrés | M11: Andrés
A12: Gastos Totales: | B12: =SUM(Gastos!C2:C1010) -> 39686865 | E12: Fight Club | G12: 3:00 - 3:30 | H12: JP | I12: JP | J12: JP | K12: Andrés | L12: Andrés | M12: Andrés
A13: Utilidad Bruta Total: | B13: =B11-B12 -> -28408865 | E13: Scarface | G13: 3:30 - 4:00 | H13: JP | I13: JP | J13: JP | K13: JP | L13: Andrés | M13: Andrés
E14: Vendedora de Rosas | G14: 4:00 - 4:30 | H14: JP | I14: JP | J14: JP | K14: JP | L14: Andrés | M14: Andrés
A15: ALERTAS | E15: Notorius BIG | G15: 4:30 - 5:00 | H15: JP | I15: JP | J15: JP | K15: JP | L15: Andrés | M15: Andrés
A16: Productos con stock bajo (<3): | B16: =COUNTIF(Inventario!K:K,"<3")-1 -> 87 | E16: Celia Cruz | G16: 5:00 - 5:30 | H16: JP | I16: JP | J16: JP | K16: JP | L16: Andrés | M16: Andrés
A17: Pedidos pendientes de pago: | B17: =COUNTIF('Pedidos Proveedores'!G:G,"Pendiente") -> 0 | E17: Mike Tyson | G17: 5:30 - 6:00 | H17: JP | I17: JP | J17: JP | K17: JP | L17: Andrés | M17: Andrés
E18: Principe de Bel Air | G18: 6:00 - 6:30 | H18: JP | I18: JP | J18: JP | K18: JP | L18: Andrés | M18: Andrés
E19: Jackass | G19: 6:30 - 7:00 | H19: JP | I19: JP | J19: JP | K19: JP | L19: Andrés | M19: Andrés
A20: INDICADORES CLAVE DE DESEMPEÑO | E20: Friends | G20: 7:00 - 7:30
A21: Costo promedio por prenda vendida: | B21: =IFERROR(SUMIF(Ventas!A:A,">="&DATE(YEAR(TODAY()),MONTH(TODAY()),1),Ventas!D:D)/COUNTIF(Ventas!A:A,">="&DATE(YEAR(TODAY()),MONTH(TODAY()),1)),0) -> 41000 | E21: MTV | G21: 7:30 - 8:00
A22: Ticket promedio: | B22: =IFERROR(SUMIF(Ventas!A:A,">="&DATE(YEAR(TODAY()),MONTH(TODAY()),1),Ventas!E:E)/COUNTIF(Ventas!A:A,">="&DATE(YEAR(TODAY()),MONTH(TODAY()),1)),0) -> 91764.706 | E22: Play Station 1 | G22: 8:00 - 8:30
A23: Prendas vendidas (mes): | B23: =COUNTIF(Ventas!A:A,">="&DATE(YEAR(TODAY()),MONTH(TODAY()),1)) -> 34 | E23: BackStreet Boys | G23: 8:30 - 9:00
A24: Margen bruto %: | B24: =IFERROR((SUMIF(Ventas!A:A,">="&DATE(YEAR(TODAY()),MONTH(TODAY()),1),Ventas!E:E)-SUMIF(Ventas!A:A,">="&DATE(YEAR(TODAY()),MONTH(TODAY()),1),Ventas!D:D))/SUMIF(Ventas!A:A,">="&DATE(YEAR(TODAY()),MONTH(TODAY()),1),Ventas!E:E),0) -> 0.55320513 | E24: Punk
A25: Rotación inventario: | B25: =IFERROR(COUNTIF(Ventas!A:A,">="&DATE(YEAR(TODAY()),MONTH(TODAY()),1))/Inventario!I2,0) -> 0.22222222 | C25: Mide cuántas veces se vende y se reemplaza el inventario en un período de un mes. | E25: Eminem
A26: Días de inventario: | B26: =IFERROR(Inventario!I2/(COUNTIF(Ventas!A:A,">="&DATE(YEAR(TODAY()),MONTH(TODAY()),1))/30),0) -> 135 | C26: Mide cuántos días tomaría vender el inventario actual. | E26: Tupac y BIG | G26: Kathe | H26: =COUNTIF($H$2:$N$23,G26)*0.5 -> 17
E27: Cerati y Rock Español (Soda, cadillacs,caifanes) | G27: JP | H27: =COUNTIF($H$2:$N$23,G27)*0.5 -> 17
E28: Mi pobre angelito | G28: Andrés | H28: =COUNTIF($H$2:$N$23,G28)*0.5 -> 17
A29: PUNTO DE EQUILIBRIO | E29: Manos de tijera | G29: TOTAL | H29: =SUM(H26:H28) -> 51
A30: Costos fijos mensuales: | B30: ='Costos Fijos'!B12 -> 1964900 | E30: Titanic | G30: C/U | H30: =H29/3 -> 17
A31: Margen promedio por prenda: | B31: =B24 -> 0.55320513 | E31: Sexto sentido
A32: Precio promedio venta: | B32: =B22 -> 91764.706 | E32: Marc Anthony
A33: Prendas/mes para equilibrio: | B33: =IFERROR(ROUNDUP(B30/(B32*B31),0),0) -> 39 | E33: Grupo niche
A34: Prendas/día para equilibrio: | B34: =ROUNDUP(B33/26,0) -> 2 | E34: Gran combo de las estrellas
E35: Rocky
E36: Canserbero (Raperos canon)
E37: Thalia
E38: Vicente Fernandez
E39: El principito
E40: La mascara y Show de truman (Jim Carrey)
E41: El silencio de los inocentes
E42: LA BRUJA DE BLAIR
E43: El rey Leon (Disney clásico)
E44: Tarzan
E45: Los Simpsons (Sátiras)
E46: Kenan y Kel
... E116: Neon Genesis Evangelion

Sheet Inventario
A1: INVENTARIO | I1: Total Stock: | J1: Valor Costo: | K1: Valor Venta:
I2: =SUM(K5:K1019) -> 153 | J2: =SUMPRODUCT(G5:G1019,K5:K1019) -> 7194000 | K2: =SUMPRODUCT(H5:H1019,K5:K1019) -> 14780000
J3: =SUM(J5:J313) -> 262 | K3: =SUM(K5:K313) -> 153 | L3: =SUM(L5:L313) -> 109
A4: SKU | B4: Producto | C4: Prenda | D4: Talla | E4: Color | F4: Diseño | G4: Costo | H4: Precio Venta | I4: Margen % | J4: Entradas | K4: Stock Actual | L4: Ventas | M4: Notas
A5: CAM-OVS-NEG-S | B5: Camisa Oversize Peruana S Negro | C5: Camisa Oversize Peruana | D5: S | E5: Negro | G5: 37000 | H5: 75000 | I5: =IF(H5>0,(H5-G5)/H5,0) -> 0.50666667 | J5: 2 | K5: =J5-COUNTIF(Ventas!$B$2:$B$1002,A5) -> 1 | L5: =J5-K5 -> 1
A6: CAM-OVS-NEG-M | B6: Camisa Oversize Peruana M Negro | C6: Camisa Oversize Peruana | D6: M | G6: 37000 | H6: 75000 | I6: =IF(H6>0,(H6-G6)/H6,0) -> 0.50666667 | J6: 6 | K6: =J6-COUNTIF(Ventas!$B$2:$B$1002,A6) -> 5 | L6: =J6-K6 -> 1
A7: CAM-OVS-NEG-L | B7: Camisa Oversize Peruana L Negro | C7: Camisa Oversize Peruana | D7: L | G7: 37000 | H7: 75000 | I7: =IF(H7>0,(H7-G7)/H7,0) -> 0.50666667 | J7: 6 | K7: =J7-COUNTIF(Ventas!$B$2:$B$1002,A7) -> 2 | L7: =J7-K7 -> 4
A8: CAM-OVS-NEG-XL | B8: Camisa Oversize Peruana XL Negro | C8: Camisa Oversize Peruana | D8: XL | G8: 37000 | H8: 75000 | I8: =IF(H8>0,(H8-G8)/H8,0) -> 0.50666667 | J8: 6 | K8: =J8-COUNTIF(Ventas!$B$2:$B$1002,A8) -> 4 | L8: =J8-K8 -> 2
A9: CAM-OVS-BLA-S | B9: Camisa Oversize Peruana S Blanco | C9: Camisa Oversize Peruana | G9: 37000 | H9: 75000 | I9: =IF(H9>0,(H9-G9)/H9,0) -> 0.50666667 | J9: 2 | K9: =J9-COUNTIF(Ventas!$B$2:$B$1002,A9) -> 1 | L9: =J9-K9 -> 1
A10: CAM-OVS-BLA-M | B10: Camisa Oversize Peruana M Blanco | C10: Camisa Oversize Peruana | G10: 37000 | H10: 75000 | I10: =IF(H10>0,(H10-G10)/H10,0) -> 0.50666667 | J10: 6 | K10: =J10-COUNTIF(Ventas!$B$2:$B$1002,A10) -> -2 | L10: =J10-K10 -> 8
A11: CAM-OVS-BLA-L | B11: Camisa Oversize Peruana L Blanco | C11: Camisa Oversize Peruana | G11: 37000 | H11: 75000 | I11: =IF(H11>0,(H11-G11)/H11,0) -> 0.50666667 | J11: 6 | K11: =J11-COUNTIF(Ventas!$B$2:$B$1002,A11) -> -1 | L11: =J11-K11 -> 7
A12: CAM-OVS-BLA-XL | B12: Camisa Oversize Peruana XL Blanco | C12: Camisa Oversize Peruana | G12: 37000 | H12: 75000 | I12: =IF(H12>0,(H12-G12)/H12,0) -> 0.50666667 | J12: 6 | K12: =J12-COUNTIF(Ventas!$B$2:$B$1002,A12) -> 3 | L12: =J12-K12 -> 3
A13: CAM-OVS-PER-S | B13: Camisa Oversize Peruana S Perla | C13: Camisa Oversize Peruana | G13: 37000 | H13: 75000 | I13: =IF(H13>0,(H13-G13)/H13,0) -> 0.50666667 | J13: 2 | K13: =J13-COUNTIF(Ventas!$B$2:$B$1002,A13) -> 2 | L13: =J13-K13 -> 0
A14: CAM-OVS-PER-M | B14: Camisa Oversize Peruana M Perla | C14: Camisa Oversize Peruana | G14: 37000 | H14: 75000 | I14: =IF(H14>0,(H14-G14)/H14,0) -> 0.50666667 | J14: 6 | K14: =J14-COUNTIF(Ventas!$B$2:$B$1002,A14) -> 3 | L14: =J14-K14 -> 3
A15: CAM-OVS-PER-L | B15: Camisa Oversize Peruana L Perla | C15: Camisa Oversize Peruana | G15: 37000 | H15: 75000 | I15: =IF(H15>0,(H15-G15)/H15,0) -> 0.50666667 | J15: 6 | K15: =J15-COUNTIF(Ventas!$B$2:$B$1002,A15) -> 4 | L15: =J15-K15 -> 2
A16: CAM-OVS-PER-XL | B16: Camisa Oversize Peruana XL Perla | C16: Camisa Oversize Peruana | G16: 37000 | H16: 75000 | I16: =IF(H16>0,(H16-G16)/H16,0) -> 0.50666667 | J16: 6 | K16: =J16-COUNTIF(Ventas!$B$2:$B$1002,A16) -> 3 | L16: =J16-K16 -> 3
A17: CAM-OVS-BEIG-S | B17: Camisa Oversize Peruana S Beige | C17: Camisa Oversize Peruana | G17: 37000 | H17: 75000 | I17: =IF(H17>0,(H17-G17)/H17,0) -> 0.50666667 | J17: 0 | K17: =J17-COUNTIF(Ventas!$B$2:$B$1002,A17) -> 0 | L17: =J17-K17 -> 0
A18: CAM-OVS-BEIG-M | B18: Camisa Oversize Peruana M Beige | C18: Camisa Oversize Peruana | G18: 37000 | H18: 75000 | I18: =IF(H18>0,(H18-G18)/H18,0) -> 0.50666667 | J18: 0 | K18: =J18-COUNTIF(Ventas!$B$2:$B$1002,A18) -> 0 | L18: =J18-K18 -> 0
A19: CAM-OVS-BEIG-L | B19: Camisa Oversize Peruana L Beige | C19: Camisa Oversize Peruana | G19: 37000 | H19: 75000 | I19: =IF(H19>0,(H19-G19)/H19,0) -> 0.50666667 | J19: 0 | K19: =J19-COUNTIF(Ventas!$B$2:$B$1002,A19) -> 0 | L19: =J19-K19 -> 0
A20: CAM-OVS-BEIG-XL | B20: Camisa Oversize Peruana XL Beige | C20: Camisa Oversize Peruana | G20: 37000 | H20: 75000 | I20: =IF(H20>0,(H20-G20)/H20,0) -> 0.50666667 | J20: 0 | K20: =J20-COUNTIF(Ventas!$B$2:$B$1002,A20) -> 0 | L20: =J20-K20 -> 0
... A44: HOOD-ACID-L | B44: Hoodie L Acid Wash Gris | C44: Hoodie Acid Wash | G44: 120000 | H44: 190000 | I44: =IF(H44>0,(H44-G44)/H44,0) -> 0.36842105 | J44: 12 | K44: =J44-COUNTIF(Ventas!$B$2:$B$1002,A44) -> 0 | L44: =J44-K44 -> 12
A45: CHOM-NEG-S | B45: Chompa Capucha S Negro | C45: Chompa Capucha | G45: ='Pedidos Proveedores'!$E$3 -> 90000 | H45: 180000 | I45: =IF(H45>0,(H45-G45)/H45,0) -> 0.5 | J45: 0 | K45: =J45-COUNTIF(Ventas!$B$2:$B$1002,A45) -> 0 | L45: =J45-K45 -> 0
A46: CHOM-NEG-M | B46: Chompa Capucha M Negro | C46: Chompa Capucha | G46: ='Pedidos Proveedores'!$E$3 -> 90000 | H46: 180000 | I46: =IF(H46>0,(H46-G46)/H46,0) -> 0.5 | J46: 3 | K46: =J46-COUNTIF(Ventas!$B$2:$B$1002,A46) -> 3 | L46: =J46-K46 -> 0
A47: CHOM-NEG-L | B47: Chompa Capucha L Negro | C47: Chompa Capucha | G47: ='Pedidos Proveedores'!$E$3 -> 90000 | H47: 180000 | I47: =IF(H47>0,(H47-G47)/H47,0) -> 0.5 | J47: 3 | K47: =J47-COUNTIF(Ventas!$B$2:$B$1002,A47) -> 1 | L47: =J47-K47 -> 2
A48: CHOM-PER-S | B48: Chompa Capucha S Perla | C48: Chompa Capucha | G48: ='Pedidos Proveedores'!$E$3 -> 90000 | H48: 180000 | I48: =IF(H48>0,(H48-G48)/H48,0) -> 0.5 | J48: 0 | K48: =J48-COUNTIF(Ventas!$B$2:$B$1002,A48) -> 0 | L48: =J48-K48 -> 0
A49: CHOM-PER-M | B49: Chompa Capucha M Perla | C49: Chompa Capucha | G49: ='Pedidos Proveedores'!$E$3 -> 90000 | H49: 180000 | I49: =IF(H49>0,(H49-G49)/H49,0) -> 0.5 | J49: 0 | K49: =J49-COUNTIF(Ventas!$B$2:$B$1002,A49) -> 0 | L49: =J49-K49 -> 0
A50: CHOM-PER-L | B50: Chompa Capucha L Perla | C50: Chompa Capucha | G50: ='Pedidos Proveedores'!$E$3 -> 90000 | H50: 180000 | I50: =IF(H50>0,(H50-G50)/H50,0) -> 0.5 | J50: 3 | K50: =J50-COUNTIF(Ventas!$B$2:$B$1002,A50) -> 3 | L50: =J50-K50 -> 0
A51: CHOM-VERD-S | B51: Chompa Capucha S Verde Botella | C51: Chompa Capucha | G51: ='Pedidos Proveedores'!$E$3 -> 90000 | H51: 180000 | I51: =IF(H51>0,(H51-G51)/H51,0) -> 0.5 | J51: 0 | K51: =J51-COUNTIF(Ventas!$B$2:$B$1002,A51) -> 0 | L51: =J51-K51 -> 0
A52: CHOM-VERD-M | B52: Chompa Capucha M Verde Botella | C52: Chompa Capucha | G52: ='Pedidos Proveedores'!$E$3 -> 90000 | H52: 180000 | I52: =IF(H52>0,(H52-G52)/H52,0) -> 0.5 | J52: 0 | K52: =J52-COUNTIF(Ventas!$B$2:$B$1002,A52) -> 0 | L52: =J52-K52 -> 0
A53: CHOM-VERD-L | B53: Chompa Capucha L Verde Botella | C53: Chompa Capucha | G53: ='Pedidos Proveedores'!$E$3 -> 90000 | H53: 180000 | I53: =IF(H53>0,(H53-G53)/H53,0) -> 0.5 | J53: 0 | K53: =J53-COUNTIF(Ventas!$B$2:$B$1002,A53) -> 0 | L53: =J53-K53 -> 0
A54: CHOM-PLOM-S | B54: Chompa Capucha S Plomo Plata | C54: Chompa Capucha | G54: ='Pedidos Proveedores'!$E$3 -> 90000 | H54: 180000 | I54: =IF(H54>0,(H54-G54)/H54,0) -> 0.5 | J54: 0 | K54: =J54-COUNTIF(Ventas!$B$2:$B$1002,A54) -> 0 | L54: =J54-K54 -> 0
A55: CHOM-PLOM-M | B55: Chompa Capucha M Plomo Plata | C55: Chompa Capucha | G55: ='Pedidos Proveedores'!$E$3 -> 90000 | H55: 180000 | I55: =IF(H55>0,(H55-G55)/H55,0) -> 0.5 | J55: 0 | K55: =J55-COUNTIF(Ventas!$B$2:$B$1002,A55) -> 0 | L55: =J55-K55 -> 0
A56: CHOM-PLOM-L | B56: Chompa Capucha L Plomo Plata | C56: Chompa Capucha | G56: ='Pedidos Proveedores'!$E$3 -> 90000 | H56: 180000 | I56: =IF(H56>0,(H56-G56)/H56,0) -> 0.5 | J56: 0 | K56: =J56-COUNTIF(Ventas!$B$2:$B$1002,A56) -> 0 | L56: =J56-K56 -> 0
A57: BUZ-OVS-NEG-M | B57: Buzo Cuello Redondo Oversized M Negro | C57: Buzo Cuello Redondo Oversized | G57: 55000 | H57: 120000 | I57: =IF(H57>0,(H57-G57)/H57,0) -> 0.54166667 | J57: 2 | K57: =J57-COUNTIF(Ventas!$B$2:$B$1002,A57) -> 1 | L57: =J57-K57 -> 1
A58: BUZ-OVS-NEG-L | B58: Buzo Cuello Redondo Oversized L Negro | C58: Buzo Cuello Redondo Oversized | G58: 55000 | H58: 120000 | I58: =IF(H58>0,(H58-G58)/H58,0) -> 0.54166667 | J58: 4 | K58: =J58-COUNTIF(Ventas!$B$2:$B$1002,A58) -> 2 | L58: =J58-K58 -> 2
A59: BUZ-OVS-NEG-XL | B59: Buzo Cuello Redondo Oversized XL Negro | C59: Buzo Cuello Redondo Oversized | G59: 55000 | H59: 120000 | I59: =IF(H59>0,(H59-G59)/H59,0) -> 0.54166667 | J59: 4 | K59: =J59-COUNTIF(Ventas!$B$2:$B$1002,A59) -> 2 | L59: =J59-K59 -> 2
A60: BUZ-OVS-BEIG-M | B60: Buzo Cuello Redondo Oversized M Beige | C60: Buzo Cuello Redondo Oversized | G60: 55000 | H60: 120000 | I60: =IF(H60>0,(H60-G60)/H60,0) -> 0.54166667 | J60: 2 | K60: =J60-COUNTIF(Ventas!$B$2:$B$1002,A60) -> 2 | L60: =J60-K60 -> 0
A61: BUZ-OVS-BEIG-L | B61: Buzo Cuello Redondo Oversized L Beige | C61: Buzo Cuello Redondo Oversized | G61: 55000 | H61: 120000 | I61: =IF(H61>0,(H61-G61)/H61,0) -> 0.54166667 | J61: 2 | K61: =J61-COUNTIF(Ventas!$B$2:$B$1002,A61) -> 1 | L61: =J61-K61 -> 1
A62: BUZ-OVS-BEIG-XL | B62: Buzo Cuello Redondo Oversized XL Beige | C62: Buzo Cuello Redondo Oversized | G62: 55000 | H62: 120000 | I62: =IF(H62>0,(H62-G62)/H62,0) -> 0.54166667 | J62: 2 | K62: =J62-COUNTIF(Ventas!$B$2:$B$1002,A62) -> 2 | L62: =J62-K62 -> 0
A63: BUZ-OVS-NEG-2XL | B63: Buzo Cuello Redondo Oversized 2XL Negro | C63: Buzo Cuello Redondo Oversized | G63: 55000 | H63: 120000 | I63: =IF(H63>0,(H63-G63)/H63,0) -> 0.54166667 | J63: 2 | K63: =J63-COUNTIF(Ventas!$B$2:$B$1002,A63) -> 2 | L63: =J63-K63 -> 0
A64: BUZ-OVS-BEIG-2XL | B64: Buzo Cuello Redondo Oversized 2XL Beige | C64: Buzo Cuello Redondo Oversized | G64: 55000 | H64: 120000 | I64: =IF(H64>0,(H64-G64)/H64,0) -> 0.54166667 | J64: 2 | K64: =J64-COUNTIF(Ventas!$B$2:$B$1002,A64) -> 2 | L64: =J64-K64 -> 0
A65: BUZ-OVS-CAF-L | B65: Buzo Cuello Redondo Oversized L Café | C65: Buzo Cuello Redondo Oversized | G65: 55000 | H65: 120000 | I65: =IF(H65>0,(H65-G65)/H65,0) -> 0.54166667 | J65: 2 | K65: =J65-COUNTIF(Ventas!$B$2:$B$1002,A65) -> 2 | L65: =J65-K65 -> 0
A66: BUZ-OVS-CAF-XL | B66: Buzo Cuello Redondo Oversized XL Café | C66: Buzo Cuello Redondo Oversized | G66: 55000 | H66: 120000 | I66: =IF(H66>0,(H66-G66)/H66,0) -> 0.54166667 | J66: 2 | K66: =J66-COUNTIF(Ventas!$B$2:$B$1002,A66) -> 2 | L66: =J66-K66 -> 0
A67: JOG-NEG-M | B67: Jogger Largo M Negro | C67: Jogger | G67: 55000 | H67: 100000 | I67: =IF(H67>0,(H67-G67)/H67,0) -> 0.45 | J67: 4 | K67: =J67-COUNTIF(Ventas!$B$2:$B$1002,A67) -> 4 | L67: =J67-K67 -> 0
A68: JOG-NEG-L | B68: Jogger Largo L Negro | C68: Jogger | G68: 55000 | H68: 100000 | I68: =IF(H68>0,(H68-G68)/H68,0) -> 0.45 | J68: 4 | K68: =J68-COUNTIF(Ventas!$B$2:$B$1002,A68) -> 4 | L68: =J68-K68 -> 0
... A75: JOG-CAF-XL | B75: Jogger Largo XL Café | C75: Jogger | G75: 55000 | H75: 100000 | I75: =IF(H75>0,(H75-G75)/H75,0) -> 0.45 | J75: 2 | K75: =J75-COUNTIF(Ventas!$B$2:$B$1002,A75) -> 2 | L75: =J75-K75 -> 0
A76: CHA-NEG-M | B76: Chaqueta Cortavientos M Negro | C76: Chaqueta Cortavientos | G76: ='Pedidos Proveedores'!$E$8 -> 40000 | H76: 110000 | I76: =IF(H76>0,(H76-G76)/H76,0) -> 0.63636364 | J76: 4 | K76: =J76-COUNTIF(Ventas!$B$2:$B$1002,A76) -> 2 | L76: =J76-K76 -> 2
A77: CHA-NEG-L | B77: Chaqueta Cortavientos L Negro | C77: Chaqueta Cortavientos | G77: ='Pedidos Proveedores'!$E$8 -> 40000 | H77: 110000 | I77: =IF(H77>0,(H77-G77)/H77,0) -> 0.63636364 | J77: 4 | K77: =J77-COUNTIF(Ventas!$B$2:$B$1002,A77) -> 4 | L77: =J77-K77 -> 0
A78: CHA-NEG-XL | B78: Chaqueta Cortavientos XL Negro | C78: Chaqueta Cortavientos | G78: ='Pedidos Proveedores'!$E$8 -> 40000 | H78: 110000 | I78: =IF(H78>0,(H78-G78)/H78,0) -> 0.63636364 | J78: 4 | K78: =J78-COUNTIF(Ventas!$B$2:$B$1002,A78) -> 1 | L78: =J78-K78 -> 3
A79: CHA-GRICLA-M | B79: Chaqueta Cortavientos M Gris Claro | C79: Chaqueta Cortavientos | G79: ='Pedidos Proveedores'!$E$8 -> 40000 | H79: 110000 | I79: =IF(H79>0,(H79-G79)/H79,0) -> 0.63636364 | J79: 2 | K79: =J79-COUNTIF(Ventas!$B$2:$B$1002,A79) -> 2 | L79: =J79-K79 -> 0
A80: CHA-GRICLA-L | B80: Chaqueta Cortavientos L Gris Claro | C80: Chaqueta Cortavientos | G80: ='Pedidos Proveedores'!$E$8 -> 40000 | H80: 110000 | I80: =IF(H80>0,(H80-G80)/H80,0) -> 0.63636364 | J80: 2 | K80: =J80-COUNTIF(Ventas!$B$2:$B$1002,A80) -> 1 | L80: =J80-K80 -> 1
A81: CHA-GRICLA-XL | B81: Chaqueta Cortavientos XL Gris Claro | C81: Chaqueta Cortavientos | G81: ='Pedidos Proveedores'!$E$8 -> 40000 | H81: 110000 | I81: =IF(H81>0,(H81-G81)/H81,0) -> 0.63636364 | J81: 2 | K81: =J81-COUNTIF(Ventas!$B$2:$B$1002,A81) -> 2 | L81: =J81-K81 -> 0
A82: CHA-VERNEG-M | B82: Chaqueta Cortavientos M Verde Botella/Negro | C82: Chaqueta Cortavientos | G82: ='Pedidos Proveedores'!$E$8 -> 40000 | H82: 110000 | I82: =IF(H82>0,(H82-G82)/H82,0) -> 0.63636364 | J82: 2 | K82: =J82-COUNTIF(Ventas!$B$2:$B$1002,A82) -> 0 | L82: =J82-K82 -> 2
A83: CHA-GRIOSC-M | B83: Chaqueta Cortavientos M Gris Oscuro | C83: Chaqueta Cortavientos | G83: ='Pedidos Proveedores'!$E$8 -> 40000 | H83: 110000 | I83: =IF(H83>0,(H83-G83)/H83,0) -> 0.63636364 | J83: 2 | K83: =J83-COUNTIF(Ventas!$B$2:$B$1002,A83) -> 2 | L83: =J83-K83 -> 0
A84: CHA-GRIOSC-L | B84: Chaqueta Cortavientos L Gris Oscuro | C84: Chaqueta Cortavientos | G84: ='Pedidos Proveedores'!$E$8 -> 40000 | H84: 110000 | I84: =IF(H84>0,(H84-G84)/H84,0) -> 0.63636364 | J84: 2 | K84: =J84-COUNTIF(Ventas!$B$2:$B$1002,A84) -> 1 | L84: =J84-K84 -> 1
A85: CHA-GRIOSC-XL | B85: Chaqueta Cortavientos XL Gris Oscuro | C85: Chaqueta Cortavientos | G85: ='Pedidos Proveedores'!$E$8 -> 40000 | H85: 110000 | I85: =IF(H85>0,(H85-G85)/H85,0) -> 0.63636364 | J85: 2 | K85: =J85-COUNTIF(Ventas!$B$2:$B$1002,A85) -> 1 | L85: =J85-K85 -> 1
A86: CHA-MOSTNEG-L | B86: Chaqueta Cortavientos L Mostaza/Negro | C86: Chaqueta Cortavientos | G86: ='Pedidos Proveedores'!$E$8 -> 40000 | H86: 110000 | I86: =IF(H86>0,(H86-G86)/H86,0) -> 0.63636364 | J86: 2 | K86: =J86-COUNTIF(Ventas!$B$2:$B$1002,A86) -> 0 | L86: =J86-K86 -> 2
A87: CHA-MOSTNEG-XL | B87: Chaqueta Cortavientos XL Mostaza/Negro | C87: Chaqueta Cortavientos | G87: ='Pedidos Proveedores'!$E$8 -> 40000 | H87: 110000 | I87: =IF(H87>0,(H87-G87)/H87,0) -> 0.63636364 | J87: 2 | K87: =J87-COUNTIF(Ventas!$B$2:$B$1002,A87) -> 2 | L87: =J87-K87 -> 0
... A90: CHA-GRINEG-XL | B90: Chaqueta Cortavientos XL Gris Claro/Negro | C90: Chaqueta Cortavientos | G90: ='Pedidos Proveedores'!$E$8 -> 40000 | H90: 110000 | I90: =IF(H90>0,(H90-G90)/H90,0) -> 0.63636364 | J90: 2 | K90: =J90-COUNTIF(Ventas!$B$2:$B$1002,A90) -> 2 | L90: =J90-K90 -> 0
A91: SUD-NEG-M | B91: Sudadera Bota Recta M Negro | C91: Sudadera Bota Recta | G91: 55000 | H91: 100000 | I91: =IF(H91>0,(H91-G91)/H91,0) -> 0.45 | J91: 2 | K91: =J91-COUNTIF(Ventas!$B$2:$B$1002,A91) -> 2 | L91: =J91-K91 -> 0
A92: SUD-NEG-L | B92: Sudadera Bota Recta L Negro | C92: Sudadera Bota Recta | G92: 55000 | H92: 100000 | I92: =IF(H92>0,(H92-G92)/H92,0) -> 0.45 | J92: 2 | K92: =J92-COUNTIF(Ventas!$B$2:$B$1002,A92) -> -1 | L92: =J92-K92 -> 3
A93: SUD-NEG-XL | B93: Sudadera Bota Recta XL Negro | C93: Sudadera Bota Recta | G93: 55000 | H93: 100000 | I93: =IF(H93>0,(H93-G93)/H93,0) -> 0.45 | J93: 2 | K93: =J93-COUNTIF(Ventas!$B$2:$B$1002,A93) -> 1 | L93: =J93-K93 -> 1
A94: SUD-BEIG-S | B94: Sudadera Bota Recta S Beige | C94: Sudadera Bota Recta | G94: 55000 | H94: 100000 | I94: =IF(H94>0,(H94-G94)/H94,0) -> 0.45 | J94: 1 | K94: =J94-COUNTIF(Ventas!$B$2:$B$1002,A94) -> 0 | L94: =J94-K94 -> 1
A95: SUD-BEIG-M | B95: Sudadera Bota Recta M Beige | C95: Sudadera Bota Recta | G95: 55000 | H95: 100000 | I95: =IF(H95>0,(H95-G95)/H95,0) -> 0.45 | J95: 1 | K95: =J95-COUNTIF(Ventas!$B$2:$B$1002,A95) -> 1 | L95: =J95-K95 -> 0
A96: SUD-BEIG-XL | B96: Sudadera Bota Recta XL Beige | C96: Sudadera Bota Recta | G96: 55000 | H96: 100000 | I96: =IF(H96>0,(H96-G96)/H96,0) -> 0.45 | J96: 2 | K96: =J96-COUNTIF(Ventas!$B$2:$B$1002,A96) -> 2 | L96: =J96-K96 -> 0
A97: SUD-CAF-M | B97: Sudadera Bota Recta M Café | C97: Sudadera Bota Recta | G97: 55000 | H97: 100000 | I97: =IF(H97>0,(H97-G97)/H97,0) -> 0.45 | J97: 1 | K97: =J97-COUNTIF(Ventas!$B$2:$B$1002,A97) -> 1 | L97: =J97-K97 -> 0
A98: SUD-CAF-L | B98: Sudadera Bota Recta L Café | C98: Sudadera Bota Recta | G98: 55000 | H98: 100000 | I98: =IF(H98>0,(H98-G98)/H98,0) -> 0.45 | J98: 2 | K98: =J98-COUNTIF(Ventas!$B$2:$B$1002,A98) -> 2 | L98: =J98-K98 -> 0
A99: PANT-NEG-M | B99: Pantaloneta M Negro | C99: Pantaloneta | G99: 45000 | H99: 90000 | I99: =IF(H99>0,(H99-G99)/H99,0) -> 0.5 | J99: 1 | K99: =J99-COUNTIF(Ventas!$B$2:$B$1002,A99) -> 0 | L99: =J99-K99 -> 1
A100: PANT-NEG-L | B100: Pantaloneta L Negro | C100: Pantaloneta | G100: 45000 | H100: 90000 | I100: =IF(H100>0,(H100-G100)/H100,0) -> 0.5 | J100: 1 | K100: =J100-COUNTIF(Ventas!$B$2:$B$1002,A100) -> 0 | L100: =J100-K100 -> 1
A101: PANT-NEG-XL | B101: Pantaloneta XL Negro | C101: Pantaloneta | G101: 45000 | H101: 90000 | I101: =IF(H101>0,(H101-G101)/H101,0) -> 0.5 | J101: 1 | K101: =J101-COUNTIF(Ventas!$B$2:$B$1002,A101) -> 1 | L101: =J101-K101 -> 0
A102: PANT-BEIG-M | B102: Pantaloneta M Beige | C102: Pantaloneta | G102: 45000 | H102: 90000 | I102: =IF(H102>0,(H102-G102)/H102,0) -> 0.5 | J102: 1 | K102: =J102-COUNTIF(Ventas!$B$2:$B$1002,A102) -> 0 | L102: =J102-K102 -> 1
... A109: CAM-REP-1.1 | B109: Camisa Réplica 1.1 | C109: Camisa Réplica 1.1 | G109: 54000 | H109: 75000 | I109: =IF(H109>0,(H109-G109)/H109,0) -> 0.28 | J109: 22 | K109: =J109-COUNTIF(Ventas!$B$2:$B$1002,A109) -> 1 | L109: =J109-K109 -> 21

Sheet Ventas
A1: Fecha | B1: SKU | C1: Producto | D1: Costo | E1: Precio Venta | F1: Método Pago | G1: Cliente | H1: Notas | L1: VENTAS | O1: Consignaciones (Entradas a cuenta adicionales a venta)
A2: 46067 | B2: =Inventario!A82 -> CHA-VERNEG-M | C2: =IFERROR(VLOOKUP(B2,Inventario!A:G,2,FALSE()),"") -> Chaqueta Cortavientos M Verde Botella/Negro | D2: =IFERROR(VLOOKUP(B2,Inventario!A:G,7,FALSE()),"") -> 40000 | E2: 120000 | F2: Transferencia | G2: Edison | H2: OK | K2: Efectivo | L2: =SUMIF($F$2:$F$1002,K2,$E$2:$E$1002) -> 4766000 | O2: 1000000
A3: 46067 | B3: =Inventario!A44 -> HOOD-ACID-L | C3: =IFERROR(VLOOKUP(B3,Inventario!A:G,2,FALSE()),"") -> Hoodie L Acid Wash Gris | D3: =IFERROR(VLOOKUP(B3,Inventario!A:G,7,FALSE()),"") -> 120000 | E3: =IFERROR(VLOOKUP(B3,Inventario!A:H,8,FALSE()),"") -> 190000 | F3: Efectivo | G3: Claudia Ramírez | K3: Transferencia | L3: =SUMIF($F$2:$F$1002,K3,$E$2:$E$1002) -> 5841000 | O3: 580000
A4: 46072 | B4: CHA-GRICLA-L | C4: =IFERROR(VLOOKUP(B4,Inventario!A:G,2,FALSE()),"") -> Chaqueta Cortavientos L Gris Claro | D4: =IFERROR(VLOOKUP(B4,Inventario!A:G,7,FALSE()),"") -> 40000 | E4: =IFERROR(VLOOKUP(B4,Inventario!A:H,8,FALSE()),"") -> 110000 | F4: Transferencia | G4: Sebastian Calderon | H4: OK | K4: Datáfono | L4: =SUMIF($F$2:$F$1002,K4,$E$2:$E$1002) -> 671000 | O4: 250000
A5: 46073 | B5: CAM-BOX-NEG-L | C5: =IFERROR(VLOOKUP(B5,Inventario!A:G,2,FALSE()),"") -> Camisa Boxy fit L Negro | D5: =IFERROR(VLOOKUP(B5,Inventario!A:G,7,FALSE()),"") -> 37000 | E5: =IFERROR(VLOOKUP(B5,Inventario!A:H,8,FALSE()),"") -> 75000 | F5: Efectivo | K5: Crédito | L5: =SUMIF($F$2:$F$1002,K5,$E$2:$E$1002) -> 0 | O5: 200000
A6: 46073 | B6: CAM-BOX-BLA-L | C6: =IFERROR(VLOOKUP(B6,Inventario!A:G,2,FALSE()),"") -> Camisa Boxy fit L Blanco | D6: =IFERROR(VLOOKUP(B6,Inventario!A:G,7,FALSE()),"") -> 37000 | E6: =IFERROR(VLOOKUP(B6,Inventario!A:H,8,FALSE()),"") -> 75000 | F6: Efectivo | K6: Plan separe | L6: 10000 | M6: Cliente X (10.000) - Felipe Hernandez (100.000) (M Kobe y Sudadera negra L) | O6: 100000
A7: 46077 | B7: CAM-REP-1.1 | C7: =IFERROR(VLOOKUP(B7,Inventario!A:G,2,FALSE()),"") -> Camisa Réplica 1.1 | D7: =IFERROR(VLOOKUP(B7,Inventario!A:G,7,FALSE()),"") -> 54000 | E7: 70000 | F7: Efectivo | G7: Santiago Javi | O7: =-202500*2 -> -405000
A8: 46077 | B8: CAM-REP-1.1 | C8: =IFERROR(VLOOKUP(B8,Inventario!A:G,2,FALSE()),"") -> Camisa Réplica 1.1 | D8: =IFERROR(VLOOKUP(B8,Inventario!A:G,7,FALSE()),"") -> 54000 | E8: 70000 | F8: Efectivo | G8: Santiago Javi | K8: RESUMEN VENTAS | O8: 100000 | P8: 46100
A9: 46079 | B9: CAM-REP-1.1 | C9: =IFERROR(VLOOKUP(B9,Inventario!A:G,2,FALSE()),"") -> Camisa Réplica 1.1 | D9: =IFERROR(VLOOKUP(B9,Inventario!A:G,7,FALSE()),"") -> 54000 | E9: 70000 | F9: Efectivo | K9: Total ventas: | L9: =COUNTA(B2:B502) -> 109 | O9: 500000 | P9: 46101
A10: 46080 | B10: CAM-OVS-BLA-L | C10: =IFERROR(VLOOKUP(B10,Inventario!A:G,2,FALSE()),"") -> Camisa Oversize Peruana L Blanco | D10: =IFERROR(VLOOKUP(B10,Inventario!A:G,7,FALSE()),"") -> 37000 | E10: =IFERROR(VLOOKUP(B10,Inventario!A:H,8,FALSE()),"") -> 75000 | F10: Efectivo | K10: Ingresos: | L10: =SUM(E2:E502) -> 11278000 | O10: 300000 | P10: 46107
A11: 46094 | B11: HOOD-ACID-L | C11: =IFERROR(VLOOKUP(B11,Inventario!A:G,2,FALSE()),"") -> Hoodie L Acid Wash Gris | D11: =IFERROR(VLOOKUP(B11,Inventario!A:G,7,FALSE()),"") -> 120000 | E11: =IFERROR(VLOOKUP(B11,Inventario!A:H,8,FALSE()),"") -> 190000 | F11: Transferencia | G11: Daniela Blandón | H11: OK | K11: Costo mercancía: | L11: =SUM(D2:D502) -> 5809000 | O11: 110000 | P11: 46118
A12: 46081 | B12: SUD-NEG-L | C12: =IFERROR(VLOOKUP(B12,Inventario!A:G,2,FALSE()),"") -> Sudadera Bota Recta L Negro | D12: =IFERROR(VLOOKUP(B12,Inventario!A:G,7,FALSE()),"") -> 55000 | E12: 100000 | F12: Efectivo | G12: Daniela Blandón | K12: Margen bruto: | L12: =L10-L11 -> 5469000 | O12: 10000 | P12: 46128
A13: 46083 | B13: CAM-OVS-NEG-M | C13: =IFERROR(VLOOKUP(B13,Inventario!A:G,2,FALSE()),"") -> Camisa Oversize Peruana M Negro | D13: =IFERROR(VLOOKUP(B13,Inventario!A:G,7,FALSE()),"") -> 37000 | E13: =IFERROR(VLOOKUP(B13,Inventario!A:H,8,FALSE()),"") -> 75000 | F13: Efectivo | G13: Don Darío | O13: 500000 | P13: 46130
A14: 46083 | B14: CAM-OVS-BLA-M | C14: =IFERROR(VLOOKUP(B14,Inventario!A:G,2,FALSE()),"") -> Camisa Oversize Peruana M Blanco | D14: =IFERROR(VLOOKUP(B14,Inventario!A:G,7,FALSE()),"") -> 37000 | E14: =IFERROR(VLOOKUP(B14,Inventario!A:H,8,FALSE()),"") -> 75000 | F14: Efectivo | G14: Don Darío | O14: 300000 | P14: 46140
A15: 46083 | B15: CAM-OVS-PER-M | C15: =IFERROR(VLOOKUP(B15,Inventario!A:G,2,FALSE()),"") -> Camisa Oversize Peruana M Perla | D15: =IFERROR(VLOOKUP(B15,Inventario!A:G,7,FALSE()),"") -> 37000 | E15: 80000 | F15: Efectivo | G15: Don Darío | K15: Cierre 17-3-2026 | L15: Debería | M15: Hay (6-4-2026) | N15: Hay (7-4-2026)
A16: 46084 | B16: CHA-NEG-M | C16: =IFERROR(VLOOKUP(B16,Inventario!A:G,2,FALSE()),"") -> Chaqueta Cortavientos M Negro | D16: =IFERROR(VLOOKUP(B16,Inventario!A:G,7,FALSE()),"") -> 40000 | E16: 80000 | F16: Efectivo | K16: Cuenta Ahorros | L16: =L3+O18+L4 -> 10057000 | M16: =2734000+588000-26250 -> 3295750
A17: 46085 | B17: CAM-REP-1.1 | C17: =IFERROR(VLOOKUP(B17,Inventario!A:G,2,FALSE()),"") -> Camisa Réplica 1.1 | D17: =IFERROR(VLOOKUP(B17,Inventario!A:G,7,FALSE()),"") -> 54000 | E17: =IFERROR(VLOOKUP(B17,Inventario!A:H,8,FALSE()),"") -> 75000 | F17: Transferencia | H17: OK | K17: Credito | L17: =L5 -> 0 | M17: =L17 -> 0
A18: 46085 | B18: CHA-NEG-XL | C18: =IFERROR(VLOOKUP(B18,Inventario!A:G,2,FALSE()),"") -> Chaqueta Cortavientos XL Negro | D18: =IFERROR(VLOOKUP(B18,Inventario!A:G,7,FALSE()),"") -> 40000 | E18: 100000 | F18: Transferencia | H18: OK | K18: Efectivo | L18: =L10-L16-L17-L19 -> -7499295 | M18: 229000 | O18: =SUM(O2:O17) -> 3545000
A19: 46085 | B19: CAM-OVS-BLA-L | C19: =IFERROR(VLOOKUP(B19,Inventario!A:G,2,FALSE()),"") -> Camisa Oversize Peruana L Blanco | D19: =IFERROR(VLOOKUP(B19,Inventario!A:G,7,FALSE()),"") -> 37000 | E19: =IFERROR(VLOOKUP(B19,Inventario!A:H,8,FALSE()),"") -> 75000 | F19: Efectivo | K19: Gastos | L19: =Gastos!M2 -> 8720295 | M19: =L19 -> 8720295
A20: 46085 | B20: CAM-OVS-BLA-L | C20: =IFERROR(VLOOKUP(B20,Inventario!A:G,2,FALSE()),"") -> Camisa Oversize Peruana L Blanco | D20: =IFERROR(VLOOKUP(B20,Inventario!A:G,7,FALSE()),"") -> 37000 | E20: =IFERROR(VLOOKUP(B20,Inventario!A:H,8,FALSE()),"") -> 75000 | F20: Transferencia | H20: OK | K20: =K6 -> Plan separe | L20: =L6 -> 10000 | M20: =L20 -> 10000
A21: 46085 | B21: HOOD-ACID-L | C21: =IFERROR(VLOOKUP(B21,Inventario!A:G,2,FALSE()),"") -> Hoodie L Acid Wash Gris | D21: =IFERROR(VLOOKUP(B21,Inventario!A:G,7,FALSE()),"") -> 120000 | E21: 180000 | F21: Transferencia | H21: OK | K21: Total | L21: =L19+L18+L17+L16+L20 -> 11288000 | M21: =M19+M18+M17+M16+M20 -> 12255045
A22: 46086 | B22: CAM-BOX-NEG-M | C22: =IFERROR(VLOOKUP(B22,Inventario!A:G,2,FALSE()),"") -> Camisa Boxy fit M Negro | D22: =IFERROR(VLOOKUP(B22,Inventario!A:G,7,FALSE()),"") -> 37000 | E22: 68000 | F22: Efectivo | G22: Juan Fernando | K22: Total sin separe | L22: =L16+L17+L18+L19 -> 11278000 | M22: =M16+M17+M18+M19 -> 12245045
A23: 46086 | B23: CAM-BOX-BLA-M | C23: =IFERROR(VLOOKUP(B23,Inventario!A:G,2,FALSE()),"") -> Camisa Boxy fit M Blanco | D23: =IFERROR(VLOOKUP(B23,Inventario!A:G,7,FALSE()),"") -> 37000 | E23: 68000 | F23: Efectivo | G23: Juan Fernando
A24: 46086 | B24: PANT-NEG-L | C24: =IFERROR(VLOOKUP(B24,Inventario!A:G,2,FALSE()),"") -> Pantaloneta L Negro | D24: =IFERROR(VLOOKUP(B24,Inventario!A:G,7,FALSE()),"") -> 45000 | E24: =IFERROR(VLOOKUP(B24,Inventario!A:H,8,FALSE()),"") -> 90000 | F24: Efectivo | G24: Juan Fernando | L24: DIFERENCIA | M24: =M22-L22 -> 967045
A25: 46088 | B25: CHA-GRIOSC-XL | C25: =IFERROR(VLOOKUP(B25,Inventario!A:G,2,FALSE()),"") -> Chaqueta Cortavientos XL Gris Oscuro | D25: =IFERROR(VLOOKUP(B25,Inventario!A:G,7,FALSE()),"") -> 40000 | E25: =IFERROR(VLOOKUP(B25,Inventario!A:H,8,FALSE()),"") -> 110000 | F25: Efectivo
A26: 46088 | B26: CAM-OVS-BLA-M | C26: =IFERROR(VLOOKUP(B26,Inventario!A:G,2,FALSE()),"") -> Camisa Oversize Peruana M Blanco | D26: =IFERROR(VLOOKUP(B26,Inventario!A:G,7,FALSE()),"") -> 37000 | E26: =IFERROR(VLOOKUP(B26,Inventario!A:H,8,FALSE()),"") -> 75000 | F26: Transferencia | H26: OK | K26: ROBO TARJETA
A27: 46088 | B27: CAM-REP-YOUT | C27: =IFERROR(VLOOKUP(B27,Inventario!A:G,2,FALSE()),"") -> Camisa Réplica Y/Out | D27: =IFERROR(VLOOKUP(B27,Inventario!A:G,7,FALSE()),"") -> 60000 | E27: =IFERROR(VLOOKUP(B27,Inventario!A:H,8,FALSE()),"") -> 75000 | F27: Transferencia | H27: OK
A28: 46090 | B28: CHA-NEG-XL | C28: =IFERROR(VLOOKUP(B28,Inventario!A:G,2,FALSE()),"") -> Chaqueta Cortavientos XL Negro | D28: =IFERROR(VLOOKUP(B28,Inventario!A:G,7,FALSE()),"") -> 40000 | E28: =IFERROR(VLOOKUP(B28,Inventario!A:H,8,FALSE()),"") -> 110000 | F28: Efectivo
A29: 46090 | B29: SUD-NEG-XL | C29: =IFERROR(VLOOKUP(B29,Inventario!A:G,2,FALSE()),"") -> Sudadera Bota Recta XL Negro | D29: =IFERROR(VLOOKUP(B29,Inventario!A:G,7,FALSE()),"") -> 55000 | E29: =IFERROR(VLOOKUP(B29,Inventario!A:H,8,FALSE()),"") -> 100000 | F29: Efectivo
A30: 46091 | B30: BUZ-OVS-NEG-XL | C30: =IFERROR(VLOOKUP(B30,Inventario!A:G,2,FALSE()),"") -> Buzo Cuello Redondo Oversized XL Negro | D30: =IFERROR(VLOOKUP(B30,Inventario!A:G,7,FALSE()),"") -> 55000 | E30: =IFERROR(VLOOKUP(B30,Inventario!A:H,8,FALSE()),"") -> 120000 | F30: Efectivo | G30: Colo
A31: 46091 | B31: CAM-OVS-PER-L | C31: =IFERROR(VLOOKUP(B31,Inventario!A:G,2,FALSE()),"") -> Camisa Oversize Peruana L Perla | D31: =IFERROR(VLOOKUP(B31,Inventario!A:G,7,FALSE()),"") -> 37000 | E31: 110000 | F31: Transferencia | H31: OK
A32: 46091 | B32: HOOD-ACID-L | C32: =IFERROR(VLOOKUP(B32,Inventario!A:G,2,FALSE()),"") -> Hoodie L Acid Wash Gris | D32: =IFERROR(VLOOKUP(B32,Inventario!A:G,7,FALSE()),"") -> 120000 | E32: =IFERROR(VLOOKUP(B32,Inventario!A:H,8,FALSE()),"") -> 190000 | F32: Transferencia | H32: OK
A33: 46091 | B33: SUD-NEG-L | C33: =IFERROR(VLOOKUP(B33,Inventario!A:G,2,FALSE()),"") -> Sudadera Bota Recta L Negro | D33: =IFERROR(VLOOKUP(B33,Inventario!A:G,7,FALSE()),"") -> 55000 | E33: 120000 | F33: Transferencia | H33: OK
A34: 46091 | B34: PANT-NEG-M | C34: =IFERROR(VLOOKUP(B34,Inventario!A:G,2,FALSE()),"") -> Pantaloneta M Negro | D34: =IFERROR(VLOOKUP(B34,Inventario!A:G,7,FALSE()),"") -> 45000 | E34: 85000 | F34: Transferencia | H34: OK
A35: 46091 | B35: CAM-OVS-BLA-M | C35: =IFERROR(VLOOKUP(B35,Inventario!A:G,2,FALSE()),"") -> Camisa Oversize Peruana M Blanco | D35: =IFERROR(VLOOKUP(B35,Inventario!A:G,7,FALSE()),"") -> 37000 | E35: 50000 | F35: Efectivo | G35: Carlos Ramirez
A36: 46092 | B36: CAM-REP-1.1 | C36: =IFERROR(VLOOKUP(B36,Inventario!A:G,2,FALSE()),"") -> Camisa Réplica 1.1 | D36: =IFERROR(VLOOKUP(B36,Inventario!A:G,7,FALSE()),"") -> 54000 | E36: =IFERROR(VLOOKUP(B36,Inventario!A:H,8,FALSE()),"") -> 75000 | F36: Efectivo
A37: 46092 | B37: CAM-OVS-NEG-XL | C37: =IFERROR(VLOOKUP(B37,Inventario!A:G,2,FALSE()),"") -> Camisa Oversize Peruana XL Negro | D37: =IFERROR(VLOOKUP(B37,Inventario!A:G,7,FALSE()),"") -> 37000 | E37: =IFERROR(VLOOKUP(B37,Inventario!A:H,8,FALSE()),"") -> 75000 | F37: Efectivo | G37: Dueño "Qué Bendición"
A38: 46092 | B38: CHA-VERNEG-M | C38: =IFERROR(VLOOKUP(B38,Inventario!A:G,2,FALSE()),"") -> Chaqueta Cortavientos M Verde Botella/Negro | D38: =IFERROR(VLOOKUP(B38,Inventario!A:G,7,FALSE()),"") -> 40000 | E38: 100000 | F38: Efectivo
A39: 46093 | B39: CAM-OVS-NEG-L | C39: =IFERROR(VLOOKUP(B39,Inventario!A:G,2,FALSE()),"") -> Camisa Oversize Peruana L Negro | D39: =IFERROR(VLOOKUP(B39,Inventario!A:G,7,FALSE()),"") -> 37000 | E39: 110000 | F39: Transferencia | G39: Jonathan Mazarello | H39: OK
A40: 46093 | B40: CAM-OVS-BLA-M | C40: =IFERROR(VLOOKUP(B40,Inventario!A:G,2,FALSE()),"") -> Camisa Oversize Peruana M Blanco | D40: =IFERROR(VLOOKUP(B40,Inventario!A:G,7,FALSE()),"") -> 37000 | E40: 110000 | F40: Transferencia | G40: Amparo Ramírez | H40: OK
A41: 46094 | B41: CAM-OVS-PER-L | C41: =IFERROR(VLOOKUP(B41,Inventario!A:G,2,FALSE()),"") -> Camisa Oversize Peruana L Perla | D41: =IFERROR(VLOOKUP(B41,Inventario!A:G,7,FALSE()),"") -> 37000 | E41: 120000 | F41: Efectivo | G41: Cliente Bogotá
A42: 46094 | B42: HOOD-ACID-L | C42: =IFERROR(VLOOKUP(B42,Inventario!A:G,2,FALSE()),"") -> Hoodie L Acid Wash Gris | D42: =IFERROR(VLOOKUP(B42,Inventario!A:G,7,FALSE()),"") -> 120000 | E42: =IFERROR(VLOOKUP(B42,Inventario!A:H,8,FALSE()),"") -> 190000 | F42: Transferencia | H42: OK
A43: 46098 | B43: CHOM-NEG-L | C43: =IFERROR(VLOOKUP(B43,Inventario!A:G,2,FALSE()),"") -> Chompa Capucha L Negro | D43: =IFERROR(VLOOKUP(B43,Inventario!A:G,7,FALSE()),"") -> 90000 | E43: 200000 | F43: Transferencia | G43: Sebastian Garces
A44: 46094 | B44: CAM-REP-1.1 | C44: =IFERROR(VLOOKUP(B44,Inventario!A:G,2,FALSE()),"") -> Camisa Réplica 1.1 | D44: =IFERROR(VLOOKUP(B44,Inventario!A:G,7,FALSE()),"") -> 54000 | E44: =IFERROR(VLOOKUP(B44,Inventario!A:H,8,FALSE()),"") -> 75000 | F44: Efectivo
A45: 46095 | B45: CAM-OVS-NEG-XL | C45: =IFERROR(VLOOKUP(B45,Inventario!A:G,2,FALSE()),"") -> Camisa Oversize Peruana XL Negro | D45: =IFERROR(VLOOKUP(B45,Inventario!A:G,7,FALSE()),"") -> 37000 | E45: =IFERROR(VLOOKUP(B45,Inventario!A:H,8,FALSE()),"") -> 75000 | F45: Transferencia | G45: Luis Ceren | H45: OK
A46: 46095 | B46: CAM-REP-1.1 | C46: =IFERROR(VLOOKUP(B46,Inventario!A:G,2,FALSE()),"") -> Camisa Réplica 1.1 | D46: =IFERROR(VLOOKUP(B46,Inventario!A:G,7,FALSE()),"") -> 54000 | E46: =IFERROR(VLOOKUP(B46,Inventario!A:H,8,FALSE()),"") -> 75000 | F46: Transferencia | H46: OK
A47: 46095 | B47: CAM-REP-1.1 | C47: =IFERROR(VLOOKUP(B47,Inventario!A:G,2,FALSE()),"") -> Camisa Réplica 1.1 | D47: =IFERROR(VLOOKUP(B47,Inventario!A:G,7,FALSE()),"") -> 54000 | E47: =IFERROR(VLOOKUP(B47,Inventario!A:H,8,FALSE()),"") -> 75000 | F47: Transferencia | H47: OK
A48: 46097 | B48: CAM-REP-YOUT | C48: =IFERROR(VLOOKUP(B48,Inventario!A:G,2,FALSE()),"") -> Camisa Réplica Y/Out | D48: =IFERROR(VLOOKUP(B48,Inventario!A:G,7,FALSE()),"") -> 60000 | E48: =IFERROR(VLOOKUP(B48,Inventario!A:H,8,FALSE()),"") -> 75000 | F48: Efectivo
A49: 46099 | B49: CAM-REP-1.1 | C49: =IFERROR(VLOOKUP(B49,Inventario!A:G,2,FALSE()),"") -> Camisa Réplica 1.1 | D49: =IFERROR(VLOOKUP(B49,Inventario!A:G,7,FALSE()),"") -> 54000 | E49: =IFERROR(VLOOKUP(B49,Inventario!A:H,8,FALSE()),"") -> 75000 | F49: Transferencia | H49: OK
A50: 46100 | B50: CAM-REP-1.1 | C50: =IFERROR(VLOOKUP(B50,Inventario!A:G,2,FALSE()),"") -> Camisa Réplica 1.1 | D50: =IFERROR(VLOOKUP(B50,Inventario!A:G,7,FALSE()),"") -> 54000 | E50: =IFERROR(VLOOKUP(B50,Inventario!A:H,8,FALSE()),"") -> 75000 | F50: Transferencia | H50: OK
A51: 46100 | B51: CAM-REP-1.1 | C51: =IFERROR(VLOOKUP(B51,Inventario!A:G,2,FALSE()),"") -> Camisa Réplica 1.1 | D51: =IFERROR(VLOOKUP(B51,Inventario!A:G,7,FALSE()),"") -> 54000 | E51: =IFERROR(VLOOKUP(B51,Inventario!A:H,8,FALSE()),"") -> 75000 | F51: Efectivo
A52: 46100 | B52: CAM-OVS-BLA-L | C52: =IFERROR(VLOOKUP(B52,Inventario!A:G,2,FALSE()),"") -> Camisa Oversize Peruana L Blanco | D52: =IFERROR(VLOOKUP(B52,Inventario!A:G,7,FALSE()),"") -> 37000 | E52: =IFERROR(VLOOKUP(B52,Inventario!A:H,8,FALSE()),"") -> 75000 | F52: Transferencia | H52: OK
A53: 46100 | B53: CAM-REP-1.1 | C53: =IFERROR(VLOOKUP(B53,Inventario!A:G,2,FALSE()),"") -> Camisa Réplica 1.1 | D53: =IFERROR(VLOOKUP(B53,Inventario!A:G,7,FALSE()),"") -> 54000 | E53: =IFERROR(VLOOKUP(B53,Inventario!A:H,8,FALSE()),"") -> 75000 | F53: Efectivo
A54: 46100 | B54: CAM-OVS-BLA-XL | C54: =IFERROR(VLOOKUP(B54,Inventario!A:G,2,FALSE()),"") -> Camisa Oversize Peruana XL Blanco | D54: =IFERROR(VLOOKUP(B54,Inventario!A:G,7,FALSE()),"") -> 37000 | E54: 37000 | F54: Efectivo | G54: Colo
A55: 46101 | B55: HOOD-ACID-L | C55: =IFERROR(VLOOKUP(B55,Inventario!A:G,2,FALSE()),"") -> Hoodie L Acid Wash Gris | D55: =IFERROR(VLOOKUP(B55,Inventario!A:G,7,FALSE()),"") -> 120000 | E55: =IFERROR(VLOOKUP(B55,Inventario!A:H,8,FALSE()),"") -> 190000 | F55: Efectivo
A56: 46101 | B56: CHA-GRINEG-M | C56: =IFERROR(VLOOKUP(B56,Inventario!A:G,2,FALSE()),"") -> Chaqueta Cortavientos M Gris Claro/Negro | D56: =IFERROR(VLOOKUP(B56,Inventario!A:G,7,FALSE()),"") -> 40000 | E56: =IFERROR(VLOOKUP(B56,Inventario!A:H,8,FALSE()),"") -> 110000 | F56: Efectivo
A57: 46101 | B57: CAM-BOX-BLA-M | C57: =IFERROR(VLOOKUP(B57,Inventario!A:G,2,FALSE()),"") -> Camisa Boxy fit M Blanco | D57: =IFERROR(VLOOKUP(B57,Inventario!A:G,7,FALSE()),"") -> 37000 | E57: =IFERROR(VLOOKUP(B57,Inventario!A:H,8,FALSE()),"") -> 75000 | F57: Efectivo
A58: 46101 | B58: CAM-REP-1.1 | C58: =IFERROR(VLOOKUP(B58,Inventario!A:G,2,FALSE()),"") -> Camisa Réplica 1.1 | D58: =IFERROR(VLOOKUP(B58,Inventario!A:G,7,FALSE()),"") -> 54000 | E58: =IFERROR(VLOOKUP(B58,Inventario!A:H,8,FALSE()),"") -> 75000 | F58: Transferencia | G58: Lina Saldarriaga | H58: OK
A59: 46102 | B59: HOOD-ACID-L | C59: =IFERROR(VLOOKUP(B59,Inventario!A:G,2,FALSE()),"") -> Hoodie L Acid Wash Gris | D59: =IFERROR(VLOOKUP(B59,Inventario!A:G,7,FALSE()),"") -> 120000 | E59: =IFERROR(VLOOKUP(B59,Inventario!A:H,8,FALSE()),"") -> 190000 | F59: Transferencia | H59: OK
A60: 46102 | B60: CAM-OVS-NEG-L | C60: =IFERROR(VLOOKUP(B60,Inventario!A:G,2,FALSE()),"") -> Camisa Oversize Peruana L Negro | D60: =IFERROR(VLOOKUP(B60,Inventario!A:G,7,FALSE()),"") -> 37000 | E60: 120000 | F60: Transferencia | H60: OK
A61: 46102 | B61: CAM-OVS-BLA-L | C61: =IFERROR(VLOOKUP(B61,Inventario!A:G,2,FALSE()),"") -> Camisa Oversize Peruana L Blanco | D61: =IFERROR(VLOOKUP(B61,Inventario!A:G,7,FALSE()),"") -> 37000 | E61: 120000 | F61: Efectivo
A62: 46102 | B62: CAM-REP-1.1 | C62: =IFERROR(VLOOKUP(B62,Inventario!A:G,2,FALSE()),"") -> Camisa Réplica 1.1 | D62: =IFERROR(VLOOKUP(B62,Inventario!A:G,7,FALSE()),"") -> 54000 | E62: =IFERROR(VLOOKUP(B62,Inventario!A:H,8,FALSE()),"") -> 75000 | F62: Efectivo
A63: 46102 | B63: CHOM-NEG-L | C63: =IFERROR(VLOOKUP(B63,Inventario!A:G,2,FALSE()),"") -> Chompa Capucha L Negro | D63: =IFERROR(VLOOKUP(B63,Inventario!A:G,7,FALSE()),"") -> 90000 | E63: =IFERROR(VLOOKUP(B63,Inventario!A:H,8,FALSE()),"") -> 180000 | F63: Transferencia | H63: OK
A64: 46102 | B64: HOOD-ACID-L | C64: =IFERROR(VLOOKUP(B64,Inventario!A:G,2,FALSE()),"") -> Hoodie L Acid Wash Gris | D64: =IFERROR(VLOOKUP(B64,Inventario!A:G,7,FALSE()),"") -> 120000 | E64: 171000 | F64: Transferencia | G64: Jorge Junior | H64: OK
A65: 46102 | B65: CHA-NEG-M | C65: =IFERROR(VLOOKUP(B65,Inventario!A:G,2,FALSE()),"") -> Chaqueta Cortavientos M Negro | D65: =IFERROR(VLOOKUP(B65,Inventario!A:G,7,FALSE()),"") -> 40000 | E65: 90000 | F65: Transferencia | G65: Jorge Junior | H65: OK
A66: 46102 | B66: SUD-NEG-L | C66: =IFERROR(VLOOKUP(B66,Inventario!A:G,2,FALSE()),"") -> Sudadera Bota Recta L Negro | D66: =IFERROR(VLOOKUP(B66,Inventario!A:G,7,FALSE()),"") -> 55000 | E66: =IFERROR(VLOOKUP(B66,Inventario!A:H,8,FALSE()),"") -> 100000 | F66: Efectivo
A67: 46102 | B67: CAM-BOX-NEG-M | C67: =IFERROR(VLOOKUP(B67,Inventario!A:G,2,FALSE()),"") -> Camisa Boxy fit M Negro | D67: =IFERROR(VLOOKUP(B67,Inventario!A:G,7,FALSE()),"") -> 37000 | E67: 120000 | F67: Datáfono | G67: Manuela Moncada
A68: 46102 | B68: CAM-OVS-BLA-L | C68: =IFERROR(VLOOKUP(B68,Inventario!A:G,2,FALSE()),"") -> Camisa Oversize Peruana L Blanco | D68: =IFERROR(VLOOKUP(B68,Inventario!A:G,7,FALSE()),"") -> 37000 | E68: 120000 | F68: Datáfono | G68: Federico Ángel
A69: 46102 | B69: CAM-OVS-NEG-L | C69: =IFERROR(VLOOKUP(B69,Inventario!A:G,2,FALSE()),"") -> Camisa Oversize Peruana L Negro | D69: =IFERROR(VLOOKUP(B69,Inventario!A:G,7,FALSE()),"") -> 37000 | E69: 120000 | F69: Datáfono | G69: Federico Ángel
A70: 46102 | B70: BUZ-OVS-NEG-M | C70: =IFERROR(VLOOKUP(B70,Inventario!A:G,2,FALSE()),"") -> Buzo Cuello Redondo Oversized M Negro | D70: =IFERROR(VLOOKUP(B70,Inventario!A:G,7,FALSE()),"") -> 55000 | E70: 98000 | F70: Datáfono | G70: Federico Ángel
A71: 46102 | B71: CAM-OVS-BLA-XL | C71: =IFERROR(VLOOKUP(B71,Inventario!A:G,2,FALSE()),"") -> Camisa Oversize Peruana XL Blanco | D71: =IFERROR(VLOOKUP(B71,Inventario!A:G,7,FALSE()),"") -> 37000 | E71: 103000 | F71: Datáfono | G71: Santiago Arteaga
A72: 46102 | B72: HOOD-ACID-L | C72: =IFERROR(VLOOKUP(B72,Inventario!A:G,2,FALSE()),"") -> Hoodie L Acid Wash Gris | D72: =IFERROR(VLOOKUP(B72,Inventario!A:G,7,FALSE()),"") -> 120000 | E72: 171000 | F72: Transferencia | G72: Natalia Cardona | H72: OK
A73: 46102 | B73: HOOD-ACID-L | C73: =IFERROR(VLOOKUP(B73,Inventario!A:G,2,FALSE()),"") -> Hoodie L Acid Wash Gris | D73: =IFERROR(VLOOKUP(B73,Inventario!A:G,7,FALSE()),"") -> 120000 | E73: 171000 | F73: Transferencia | G73: Anuar | H73: OK
A74: 46102 | B74: HOOD-ACID-L | C74: =IFERROR(VLOOKUP(B74,Inventario!A:G,2,FALSE()),"") -> Hoodie L Acid Wash Gris | D74: =IFERROR(VLOOKUP(B74,Inventario!A:G,7,FALSE()),"") -> 120000 | E74: 171000 | F74: Transferencia | G74: Carolina Ramírez | H74: OK
A75: 46106 | B75: HOOD-ACID-L | C75: =IFERROR(VLOOKUP(B75,Inventario!A:G,2,FALSE()),"") -> Hoodie L Acid Wash Gris | D75: =IFERROR(VLOOKUP(B75,Inventario!A:G,7,FALSE()),"") -> 120000 | E75: 180000 | F75: Efectivo | G75: Grillo
A76: 46109 | B76: PANT-BEIG-M | C76: =IFERROR(VLOOKUP(B76,Inventario!A:G,2,FALSE()),"") -> Pantaloneta M Beige | D76: =IFERROR(VLOOKUP(B76,Inventario!A:G,7,FALSE()),"") -> 45000 | E76: 100000 | F76: Transferencia | G76: Jorge Gay Caicedo | H76: OK
A77: 46111 | B77: CHA-NEG-XL | C77: =IFERROR(VLOOKUP(B77,Inventario!A:G,2,FALSE()),"") -> Chaqueta Cortavientos XL Negro | D77: =IFERROR(VLOOKUP(B77,Inventario!A:G,7,FALSE()),"") -> 40000 | E77: =IFERROR(VLOOKUP(B77,Inventario!A:H,8,FALSE()),"") -> 110000 | F77: Transferencia | H77: OK
A78: 46111 | B78: SUD-BEIG-S | C78: =IFERROR(VLOOKUP(B78,Inventario!A:G,2,FALSE()),"") -> Sudadera Bota Recta S Beige | D78: =IFERROR(VLOOKUP(B78,Inventario!A:G,7,FALSE()),"") -> 55000 | E78: =IFERROR(VLOOKUP(B78,Inventario!A:H,8,FALSE()),"") -> 100000 | F78: Efectivo | G78: Jorge Gay Caicedo
A79: 46113 | B79: CAM-OVS-PER-M | C79: =IFERROR(VLOOKUP(B79,Inventario!A:G,2,FALSE()),"") -> Camisa Oversize Peruana M Perla | D79: =IFERROR(VLOOKUP(B79,Inventario!A:G,7,FALSE()),"") -> 37000 | E79: 120000 | F79: Transferencia | H79: Diseño Willie Colón - OK
A80: 46113 | B80: BUZ-OVS-BEIG-L | C80: =IFERROR(VLOOKUP(B80,Inventario!A:G,2,FALSE()),"") -> Buzo Cuello Redondo Oversized L Beige | D80: =IFERROR(VLOOKUP(B80,Inventario!A:G,7,FALSE()),"") -> 55000 | E80: =IFERROR(VLOOKUP(B80,Inventario!A:H,8,FALSE()),"") -> 120000 | F80: Transferencia | H80: OK
A81: 46113 | B81: CAM-REP-1.1 | C81: =IFERROR(VLOOKUP(B81,Inventario!A:G,2,FALSE()),"") -> Camisa Réplica 1.1 | D81: =IFERROR(VLOOKUP(B81,Inventario!A:G,7,FALSE()),"") -> 54000 | E81: =IFERROR(VLOOKUP(B81,Inventario!A:H,8,FALSE()),"") -> 75000 | F81: Efectivo
A82: 46113 | B82: CAM-REP-1.1 | C82: =IFERROR(VLOOKUP(B82,Inventario!A:G,2,FALSE()),"") -> Camisa Réplica 1.1 | D82: =IFERROR(VLOOKUP(B82,Inventario!A:G,7,FALSE()),"") -> 54000 | E82: =IFERROR(VLOOKUP(B82,Inventario!A:H,8,FALSE()),"") -> 75000 | F82: Transferencia | H82: OK
A83: 46118 | B83: CAM-OVS-BLA-M | C83: =IFERROR(VLOOKUP(B83,Inventario!A:G,2,FALSE()),"") -> Camisa Oversize Peruana M Blanco | D83: =IFERROR(VLOOKUP(B83,Inventario!A:G,7,FALSE()),"") -> 37000 | E83: 120000 | F83: Efectivo | G83: Hermano Nataly | H83: Diseño Eminem
A84: 46118 | B84: CAM-BOX-BLA-L | C84: =IFERROR(VLOOKUP(B84,Inventario!A:G,2,FALSE()),"") -> Camisa Boxy fit L Blanco | D84: =IFERROR(VLOOKUP(B84,Inventario!A:G,7,FALSE()),"") -> 37000 | E84: 0 | F84: Efectivo | H84: Regalo a Fotografo
A85: 46118 | B85: CAM-OVS-BLA-XL | C85: =IFERROR(VLOOKUP(B85,Inventario!A:G,2,FALSE()),"") -> Camisa Oversize Peruana XL Blanco | D85: =IFERROR(VLOOKUP(B85,Inventario!A:G,7,FALSE()),"") -> 37000 | E85: 0 | F85: Efectivo | H85: Regalo a Modelo fotos
A86: 46118 | B86: CAM-OVS-PER-XL | C86: =IFERROR(VLOOKUP(B86,Inventario!A:G,2,FALSE()),"") -> Camisa Oversize Peruana XL Perla | D86: =IFERROR(VLOOKUP(B86,Inventario!A:G,7,FALSE()),"") -> 37000 | E86: 0 | F86: Efectivo | H86: Regalo a Modelo fotos
A87: 46120 | B87: BUZ-OVS-NEG-XL | C87: =IFERROR(VLOOKUP(B87,Inventario!A:G,2,FALSE()),"") -> Buzo Cuello Redondo Oversized XL Negro | D87: =IFERROR(VLOOKUP(B87,Inventario!A:G,7,FALSE()),"") -> 55000 | E87: =IFERROR(VLOOKUP(B87,Inventario!A:H,8,FALSE()),"") -> 120000 | F87: Efectivo
A88: 46120 | B88: CAM-REP-1.1 | C88: =IFERROR(VLOOKUP(B88,Inventario!A:G,2,FALSE()),"") -> Camisa Réplica 1.1 | D88: =IFERROR(VLOOKUP(B88,Inventario!A:G,7,FALSE()),"") -> 54000 | E88: =IFERROR(VLOOKUP(B88,Inventario!A:H,8,FALSE()),"") -> 75000 | F88: Efectivo
A89: 46123 | B89: CAM-OVS-PER-M | C89: =IFERROR(VLOOKUP(B89,Inventario!A:G,2,FALSE()),"") -> Camisa Oversize Peruana M Perla | D89: =IFERROR(VLOOKUP(B89,Inventario!A:G,7,FALSE()),"") -> 37000 | E89: =IFERROR(VLOOKUP(B89,Inventario!A:H,8,FALSE()),"") -> 75000 | F89: Efectivo
A90: 46126 | B90: CAM-REP-1.1 | C90: =IFERROR(VLOOKUP(B90,Inventario!A:G,2,FALSE()),"") -> Camisa Réplica 1.1 | D90: =IFERROR(VLOOKUP(B90,Inventario!A:G,7,FALSE()),"") -> 54000 | E90: =IFERROR(VLOOKUP(B90,Inventario!A:H,8,FALSE()),"") -> 75000 | F90: Transferencia | G90: Luis Chef Restaurante
A91: 46126 | B91: CAM-REP-1.1 | C91: =IFERROR(VLOOKUP(B91,Inventario!A:G,2,FALSE()),"") -> Camisa Réplica 1.1 | D91: =IFERROR(VLOOKUP(B91,Inventario!A:G,7,FALSE()),"") -> 54000 | E91: =IFERROR(VLOOKUP(B91,Inventario!A:H,8,FALSE()),"") -> 75000 | F91: Transferencia | G91: Luis Chef Restaurante
A92: 46126 | B92: CAM-REP-1.1 | C92: =IFERROR(VLOOKUP(B92,Inventario!A:G,2,FALSE()),"") -> Camisa Réplica 1.1 | D92: =IFERROR(VLOOKUP(B92,Inventario!A:G,7,FALSE()),"") -> 54000 | E92: =IFERROR(VLOOKUP(B92,Inventario!A:H,8,FALSE()),"") -> 75000 | F92: Transferencia | G92: Luis Chef Restaurante
A93: 46126 | B93: CAM-REP-1.1 | C93: =IFERROR(VLOOKUP(B93,Inventario!A:G,2,FALSE()),"") -> Camisa Réplica 1.1 | D93: =IFERROR(VLOOKUP(B93,Inventario!A:G,7,FALSE()),"") -> 54000 | E93: =IFERROR(VLOOKUP(B93,Inventario!A:H,8,FALSE()),"") -> 75000 | F93: Transferencia | G93: Luis Chef Restaurante
A94: 46126 | B94: BUZ-OVS-NEG-L | C94: =IFERROR(VLOOKUP(B94,Inventario!A:G,2,FALSE()),"") -> Buzo Cuello Redondo Oversized L Negro | D94: =IFERROR(VLOOKUP(B94,Inventario!A:G,7,FALSE()),"") -> 55000 | E94: 100000 | F94: Transferencia | G94: Luis Chef Restaurante
A95: 46126 | B95: PANT-CAF-M | C95: =IFERROR(VLOOKUP(B95,Inventario!A:G,2,FALSE()),"") -> Pantaloneta M Café | D95: =IFERROR(VLOOKUP(B95,Inventario!A:G,7,FALSE()),"") -> 45000 | E95: 68000 | F95: Efectivo | G95: Luis Chef Restaurante
A96: 46127 | B96: BUZ-OVS-NEG-L | C96: =IFERROR(VLOOKUP(B96,Inventario!A:G,2,FALSE()),"") -> Buzo Cuello Redondo Oversized L Negro | D96: =IFERROR(VLOOKUP(B96,Inventario!A:G,7,FALSE()),"") -> 55000 | E96: =IFERROR(VLOOKUP(B96,Inventario!A:H,8,FALSE()),"") -> 120000 | F96: Transferencia
A97: 46128 | B97: CAM-REG-ACID-M | C97: =IFERROR(VLOOKUP(B97,Inventario!A:G,2,FALSE()),"") -> Camisa Regular Peruana M Acid Wash | D97: =IFERROR(VLOOKUP(B97,Inventario!A:G,7,FALSE()),"") -> 36000 | E97: 85000 | F97: Transferencia
A98: 46129 | B98: CAM-OVS-BLA-S | C98: =IFERROR(VLOOKUP(B98,Inventario!A:G,2,FALSE()),"") -> Camisa Oversize Peruana S Blanco | D98: =IFERROR(VLOOKUP(B98,Inventario!A:G,7,FALSE()),"") -> 37000 | E98: 120000 | F98: Efectivo
A99: 46129 | B99: CAM-OVS-BLA-M | C99: =IFERROR(VLOOKUP(B99,Inventario!A:G,2,FALSE()),"") -> Camisa Oversize Peruana M Blanco | D99: =IFERROR(VLOOKUP(B99,Inventario!A:G,7,FALSE()),"") -> 37000 | E99: =IFERROR(VLOOKUP(B99,Inventario!A:H,8,FALSE()),"") -> 75000 | F99: Transferencia
A100: 46129 | B100: CAM-OVS-PER-XL | C100: =IFERROR(VLOOKUP(B100,Inventario!A:G,2,FALSE()),"") -> Camisa Oversize Peruana XL Perla | D100: =IFERROR(VLOOKUP(B100,Inventario!A:G,7,FALSE()),"") -> 37000 | E100: 37000 | F100: Transferencia | H100: Regalo Kathe a Lucho
...

Sheet Caja Diaria
A1: Fecha | B1: Efectivo Inicio | C1: Ventas Efectivo | D1: Ventas Datáfono | E1: Ventas Transf. | F1: Gastos Efectivo | G1: Efectivo Cierre | H1: Diferencia | I1: Notas
A2: 46067 | B2: 0 | C2: 0 | D2: 0 | E2: 120000 | F2: 0 | G2: =B2+C2-F2 -> 0 | H2: =G2-(B2+C2-F2) -> 0 | I2: Claudia Ramírez debe 200.000 de Hoodie Acid Wash M
G3: =B3+C3-F3 -> 0 | H3: =G3-(B3+C3-F3) -> 0
G4: =B4+C4-F4 -> 0 | H4: =G4-(B4+C4-F4) -> 0
G5: =B5+C5-F5 -> 0 | H5: =G5-(B5+C5-F5) -> 0
G6: =B6+C6-F6 -> 0 | H6: =G6-(B6+C6-F6) -> 0
G7: =B7+C7-F7 -> 0 | H7: =G7-(B7+C7-F7) -> 0
G8: =B8+C8-F8 -> 0 | H8: =G8-(B8+C8-F8) -> 0
G9: =B9+C9-F9 -> 0 | H9: =G9-(B9+C9-F9) -> 0
G10: =B10+C10-F10 -> 0 | H10: =G10-(B10+C10-F10) -> 0
G11: =B11+C11-F11 -> 0 | H11: =G11-(B11+C11-F11) -> 0
G12: =B12+C12-F12 -> 0 | H12: =G12-(B12+C12-F12) -> 0
G13: =B13+C13-F13 -> 0 | H13: =G13-(B13+C13-F13) -> 0
G14: =B14+C14-F14 -> 0 | H14: =G14-(B14+C14-F14) -> 0
... G61: =B61+C61-F61 -> 0 | H61: =G61-(B61+C61-F61) -> 0

Sheet Pedidos Proveedores
A1: Fecha Pedido | B1: Proveedor | C1: Descripción | D1: Unidades | E1: Costo Unit. | F1: Total | G1: Estado Pago | H1: Fecha Pago | I1: Notas | L1: Pendiente | M1: =SUMIF($G$2:$G$18,L1,$F$2:$F$18) -> 0 | Q1: Precios Proveedores
A2: 45692 | B2: YOUR BRAND | C2: Hoodie L | D2: 2 | E2: 120000 | F2: =D2*E2 -> 240000 | G2: Pagado | H2: 46057 | I2: 2 Acid Wash gris L | L2: Pagado | M2: =SUMIF($G$2:$G$18,L2,$F$2:$F$18) -> 13206000 | Q2: AUREN | R2: Precio
A3: 45692 | B3: YOUR BRAND | C3: Chompa 320gr Talla L | D3: 4 | E3: 90000 | F3: =D3*E3 -> 360000 | G3: Pagado | I3: 3 Perla y 1 Negro L | L3: Crédito | M3: =SUMIF($G$2:$G$18,L3,$F$2:$F$18) -> 0 | Q3: Regular | R3: 32000
A4: 46062 | B4: YOUR BRAND | C4: Hoodie L | D4: 10 | E4: 120000 | F4: =D4*E4 -> 1200000 | G4: Pagado | I4: 10 Acid Wash gris L | Q4: Oversize | R4: 35000
A5: 46062 | B5: YOUR BRAND | C5: Camiseta Boxy Fit 320gr | D5: 30 | E5: 37000 | F5: =D5*E5 -> 1110000 | G5: Pagado | I5: 10 negras, 10 blancas, 10 plomo plata | Q5: Buso regular | R5: 50000
A6: 46056 | B6: BRACOR | C6: Camiseta Réplica Y/Out 1.1 | D6: 8 | E6: 60000 | F6: =D6*E6 -> 480000 | G6: Pagado | Q6: Buso oversize | R6: 55000
A7: 46056 | B7: BRACOR | C7: Camiseta Réplica 1.1 | D7: 22 | E7: 54000 | F7: =D7*E7 -> 1188000 | G7: Pagado | Q7: Pantaloneta | R7: 45000
A8: 46067 | B8: AUREN | C8: Chaqueta Cortavientos | D8: 36 | E8: 40000 | F8: =D8*E8 -> 1440000 | G8: Pagado | I8: 24 Chaquetas 1 Color y 12 Chaquetas Bicolor | Q8: Jogger | R8: 55000
A9: 46067 | B9: AUREN | C9: Pantalonetas | D9: 12 | E9: 45000 | F9: =D9*E9 -> 540000 | G9: Pagado | I9: 12 Pantalonetas (Negras, Beige y Café) | Q9: Sudadera bota recta | R9: 55000
A10: 46067 | B10: AUREN | C10: Sudadera Bota Recta | D10: 12 | E10: 55000 | F10: =D10*E10 -> 660000 | G10: Pagado | I10: 12 Sudaderas (Negras, Beige y Café) | Q10: Chompa | R10: 75000
A11: 46067 | B11: AUREN | C11: Jogger | D11: 24 | E11: 55000 | F11: =D11*E11 -> 1320000 | G11: Pagado | I11: 12 Jogger (Negras, Beige y Café) | Q11: Chaquetas cortavientos | R11: 40000
A12: 46067 | B12: AUREN | C12: Buso Oversized | D12: 24 | E12: 55000 | F12: =D12*E12 -> 1320000 | G12: Pagado | I12: 24 Busos Oversized (Negro, Beige y Café) | Q12: Sudadera cortavientos | R12: 32000
A13: 46078 | B13: YOUR BRAND | C13: Camiseta Oversized 320gr | D13: 60 | E13: 37000 | F13: =D13*E13 -> 2220000 | G13: Pagado | I13: 20 blancas, 20 negras, 20 perla | Q13: Chaqueta reflectiva | R13: 50000
A14: 46086 | B14: YOUR BRAND | C14: Chompas 320gr | D14: 5 | E14: 90000 | F14: =D14*E14 -> 450000 | G14: Pagado | I14: 3 M y 2 L negros
A15: 46086 | B15: YOUR BRAND | C15: Camiseta Boxy Fit 220gr | D15: 2 | E15: 30000 | F15: =D15*E15 -> 60000 | G15: Pagado | I15: 2 Boxy Fit M de 220gr
A16: 46102 | B16: YOUR BRAND | C16: Camiseta Oversized 320gr | D16: 14 | E16: 37000 | F16: =D16*E16 -> 518000 | G16: Pagado | I16: 4XL Perla, 2L Perla, 4S Negra, 4L Negra
A17: 46112 | B17: AUREN | C17: Sudadera Bota Recta | D17: 1 | E17: =E10 -> 55000 | F17: =D17*E17 -> 55000 | G17: Pagado | I17: 1 Sudadera Beige S
A18: 46112 | B18: AUREN | C18: Pantaloneta | D18: 1 | E18: 45000 | F18: =D18*E18 -> 45000 | G18: Pagado | I18: 1 Pantaloneta Beige S | Q18: ETIQUETAS / MARQUILLAS / EMPAQUES
A19: 46123 | B19: YOUR BRAND | C19: Camiseta Oversized 320gr - Acid Wash | D19: 10 | E19: 36000 | F19: =D19*E19 -> 360000 | G19: Pagado | I19: 10 camisas oversize acid wash Azules
A20: 46135 | B20: YOUR BRAND | C20: Camiseta Oversized 320gr | D20: 3 | E20: 37000 | F20: =D20*E20 -> 111000 | G20: Pagado | I20: 2 negras XL y una negra S
F21: =D21*E21 -> 0
F22: =D22*E22 -> 0
A23: TOTAL PEDIDOS | D23: =SUM(D2:D22) -> 280 | F23: =SUM(F2:F18) -> 13206000 | Q23: Bolsas buenas | R23: 600
Q24: bolsa sencilla | R24: 150

Sheet Gastos
A1: Fecha | B1: Categoría | C1: Monto | D1: Descripción | E1: Método Pago | F1: Responsable | G1: Notas | I1: CATEGORÍAS DISPONIBLES: | L1: RESPONSABLES | M1: TOTAL | P1: Rubro | Q1: Fecha Periódica
A2: 45992 | B2: Arriendo | C2: 404000 | D2: Pago arriendo Diciembre | E2: Transferencia | F2: KATHE | I2: Arriendo | J2: =SUMIF(B:B,I2,C:C) -> 6058000 | L2: ORVANN | M2: =SUMIF($F$2:$F$1010,L2,$C$2:$C$1010) -> 8720295 | P2: Pago Arriendo | Q2: 1 de cada mes
A3: 45992 | B3: Arriendo | C3: 404000 | D3: Pago arriendo Diciembre | E3: Transferencia | F3: ANDRES | I3: Servicios (Agua, Luz, Gas) | J3: =SUMIF(B:B,I3,C:C) -> 563450 | L3: KATHE | M3: =SUMIF($F$2:$F$1010,L3,$C$2:$C$1010) -> 10322128 | N3: =M3-$M$7 -> -62 | P3: Pago Servicios | Q3: 22 de cada mes
A4: 45992 | B4: Arriendo | C4: 404000 | D4: Pago arriendo Diciembre | E4: Transferencia | F4: JP | I4: Internet | J4: =SUMIF(B:B,I4,C:C) -> 66000 | L4: ANDRES | M4: =SUMIF($F$2:$F$1010,L4,$C$2:$C$1010) -> 10318527 | N4: =M4-$M$7 -> -3663 | P4: Pago Internet | Q4: 14 de cada mes
A5: 45998 | B5: Dotación local | C5: 2000000 | D5: Pago arreglo Local | E5: Transferencia | F5: KATHE | I5: Nómina/Vendedor | J5: =SUMIF(B:B,I5,C:C) -> 0 | L5: JP | M5: =SUMIF($F$2:$F$1010,L5,$C$2:$C$1010) -> 10325915 | N5: =M5-$M$7 -> 3725 | P5: Pago Shopify | Q5: 30 de cada mes
A6: 45998 | B6: Dotación local | C6: 2000000 | D6: Pago arreglo Local | E6: Transferencia | F6: ANDRES | I6: Contador | J6: =SUMIF(B:B,I6,C:C) -> 0 | M6: =SUM(M3:M5) -> 30966570 | P6: Pago Correo | Q6: 1 de cada mes
A7: 45998 | B7: Dotación local | C7: 2000000 | D7: Pago arreglo Local | E7: Transferencia | F7: JP | I7: Publicidad/Marketing | J7: =SUMIF(B:B,I7,C:C) -> 2768406 | L7: Aporte por socio | M7: =M6/3 -> 10322190 | P7: Pago Seguro | Q7: 2 de cada mes
A8: 46007 | B8: Dotación local | C8: 117000 | D8: Lavamanos | E8: Transferencia | F8: JP | I8: Empaque (Bolsas, Etiquetas) | J8: =SUMIF(B:B,I8,C:C) -> 1620633
A9: 46007 | B9: Dotación local | C9: 117000 | D9: Lavamanos | E9: Transferencia | F9: ANDRES | I9: Aseo/Mantenimiento | J9: =SUMIF(B:B,I9,C:C) -> 249000
A10: 46007 | B10: Dotación local | C10: 117000 | D10: Lavamanos | E10: Transferencia | F10: KATHE | I10: Transporte | J10: =SUMIF(B:B,I10,C:C) -> 230650
A11: 46008 | B11: Dotación local | C11: 18000 | D11: Percheros pequeños | E11: Transferencia | F11: JP | I11: Comisiones datáfono | J11: =SUMIF(B:B,I11,C:C) -> 0
A12: 46008 | B12: Dotación local | C12: 18000 | D12: Percheros pequeños | E12: Transferencia | F12: ANDRES | I12: Ilustraciones/Diseño | J12: =SUMIF(B:B,I12,C:C) -> 484267
A13: 46008 | B13: Dotación local | C13: 18000 | D13: Percheros pequeños | E13: Transferencia | F13: KATHE | I13: Dotación local | J13: =SUMIF(B:B,I13,C:C) -> 10616900 | L13: DEUDAS
A14: 46018 | B14: Dotación local | C14: 500000 | D14: Pago arreglo Local | E14: Transferencia | F14: ANDRES | I14: Imprevistos | J14: =SUMIF(B:B,I14,C:C) -> 38500 | L14: Prestamista | M14: Monto | N14: Fecha de pago | O14: Notas | P14: Por Socio
A15: 46018 | B15: Dotación local | C15: 100000 | D15: Pago arreglo Local | E15: Transferencia | F15: JP | I15: Mercancía | J15: =SUMIF(B:B,I15,C:C) -> 16590724 | L15: Kathe | M15: 850500 | N15: 46149 | O15: 850.500 de excedente de celular | P15: =M15/3 -> 283500
A16: 46023 | B16: Arriendo | C16: 404000 | D16: Pago arriendo Enero | E16: Transferencia | F16: KATHE | I16: Otro | J16: =SUMIF(B:B,I16,C:C) -> 297300 | P16: =M16/3 -> 0
A17: 46023 | B17: Arriendo | C17: 404000 | D17: Pago arriendo Enero | E17: Transferencia | F17: JP | I17: Seguros | J17: =SUMIF(B:B,I17,C:C) -> 103035 | P17: =M17/3 -> 0
A18: 46023 | B18: Arriendo | C18: 404000 | D18: Pago arriendo Enero | E18: Transferencia | F18: ANDRES | P18: =M18/3 -> 0
A19: 46024 | B19: Publicidad/Marketing | C19: 59682 | D19: Pago mensualidad Freepick y Mockey | E19: Transferencia | F19: JP | I19: RESUMEN GASTOS | P19: =M19/3 -> 0
A20: 46024 | B20: Publicidad/Marketing | C20: 59682 | D20: Pago mensualidad Freepick y Mockey | E20: Transferencia | F20: KATHE | I20: Total gastos: | J20: =SUM(C2:C510) -> 39686865
A21: 46024 | B21: Publicidad/Marketing | C21: 59682 | D21: Pago mensualidad Freepick y Mockey | E21: Transferencia | F21: ANDRES | L21: TOTAL DEUDAS | M21: =SUM(M15:M19) -> 850500
A22: 46032 | B22: Dotación local | C22: 287000 | D22: Espejo, Toldo y Cámaras | E22: Transferencia | F22: JP | L22: Por socio | M22: =M21/3 -> 283500
A23: 46032 | B23: Dotación local | C23: 287000 | D23: Espejo, Toldo y Cámaras | E23: Transferencia | F23: KATHE
A24: 46032 | B24: Dotación local | C24: 287000 | D24: Espejo, Toldo y Cámaras | E24: Transferencia | F24: ANDRES
A25: 46037 | B25: Dotación local | C25: 30000 | D25: Adicional espejo | E25: Transferencia | F25: ANDRES | L25: Otras deudas
A26: 46037 | B26: Dotación local | C26: 30000 | D26: Adicional espejo | E26: Transferencia | F26: JP | L26: Pendiente | M26: Monto | N26: Fecha de pago | O26: Notas
A27: 46037 | B27: Dotación local | C27: 30000 | D27: Adicional espejo | E27: Transferencia | F27: KATHE
A28: 45674 | B28: Dotación local | C28: 220000 | D28: Pago arreglo Local | E28: Transferencia | F28: ANDRES
A29: 45674 | B29: Dotación local | C29: 720000 | D29: Pago arreglo Local | E29: Transferencia | F29: KATHE
A30: 45674 | B30: Dotación local | C30: 60000 | D30: Pago arreglo Local | E30: Transferencia | F30: JP
A31: 46043 | B31: Dotación local | C31: 6700 | D31: Nombre Carpa | E31: Transferencia | F31: ANDRES | L31: TOTAL | M31: =SUM(M27:M30) -> 0
A32: 46043 | B32: Dotación local | C32: 6700 | D32: Nombre Carpa | E32: Transferencia | F32: KATHE | L32: C/U | M32: =M31/3 -> 0
A33: 46043 | B33: Dotación local | C33: 6700 | D33: Nombre Carpa | E33: Transferencia | F33: JP
A34: 46052 | B34: Ilustraciones/Diseño | C34: 140000 | D34: Diseño Colección 1 (Pulp Fiction) | E34: Transferencia | F34: JP
A35: 46052 | B35: Ilustraciones/Diseño | C35: 140000 | D35: Diseño Colección 1 (Pulp Fiction) | E35: Transferencia | F35: KATHE
A36: 46052 | B36: Ilustraciones/Diseño | C36: 140000 | D36: Diseño Colección 1 (Pulp Fiction) | E36: Transferencia | F36: ANDRES
A37: 46056 | B37: Arriendo | C37: 404000 | D37: Pago Arriendo Febrero | E37: Transferencia | F37: JP
A38: 46056 | B38: Arriendo | C38: 404000 | D38: Pago Arriendo Febrero | E38: Transferencia | F38: KATHE
A39: 46056 | B39: Arriendo | C39: 404000 | D39: Pago Arriendo Febrero | E39: Transferencia | F39: ANDRES
A40: 46059 | B40: Dotación local | C40: 400000 | D40: Pago arreglo Local | E40: Transferencia | F40: JP
A41: 46083 | B41: Mercancía | C41: 890000 | D41: Mercancía Your Brand | E41: Transferencia | F41: ANDRES
A42: 46083 | B42: Mercancía | C42: 890000 | D42: Mercancía Your Brand | E42: Transferencia | F42: KATHE
A43: 46083 | B43: Mercancía | C43: 890000 | D43: Mercancía Your Brand | E43: Transferencia | F43: JP
A44: 46057 | B44: Mercancía | C44: 80000 | D44: Mercancía Your Brand | E44: Transferencia | F44: KATHE
... A60: 46069 | B60: Empaque (Bolsas, Etiquetas) | C60: 45000 | D60: Bolsas prendas | E60: Transferencia | F60: JP
A61: 46069 | B61: Dotación local | C61: =150000-134733 -> 15267 | D61: Percheros | E61: Transferencia | F61: KATHE
A62: 46069 | B62: Dotación local | C62: 134733 | D62: Percheros | E62: Transferencia | F62: ANDRES
A63: 46069 | B63: Transporte | C63: 20000 | D63: Domicilio Ganchos | E63: Transferencia | F63: JP
A64: 46070 | B64: Publicidad/Marketing | C64: =394500-217533 -> 176967 | D64: 50% Letrero local | E64: Transferencia | F64: JP
A65: 46070 | B65: Publicidad/Marketing | C65: 217533 | D65: 50% Letrero local | E65: Transferencia | F65: ANDRES
A66: 46070 | B66: Dotación local | C66: 100000 | D66: Percheros | E66: Transferencia | F66: JP
A67: 46071 | B67: Dotación local | C67: 63400 | D67: Percheros | E67: Transferencia | F67: KATHE
A68: 46071 | B68: Dotación local | C68: =190000-C67*2 -> 63200 | D68: Percheros | E68: Transferencia | F68: JP
A69: 46071 | B69: Dotación local | C69: 63400 | D69: Percheros | E69: Transferencia | F69: ANDRES
A70: 46073 | B70: Dotación local | C70: 2700 | D70: Disco corte estantería | E70: Transferencia | F70: JP
A71: 46073 | B71: Dotación local | C71: 2700 | D71: Disco corte estantería | E71: Transferencia | F71: ANDRES
A72: 46073 | B72: Dotación local | C72: 2700 | D72: Disco corte estantería | E72: Transferencia | F72: KATHE
A73: 46074 | B73: Dotación local | C73: 20000 | D73: Pago a Sergio arreglos varios | E73: Transferencia | F73: KATHE
A74: 46074 | B74: Dotación local | C74: 24000 | D74: Arreglos Jorge | E74: Transferencia | F74: KATHE
A75: 46074 | B75: Dotación local | C75: 43000 | D75: Arreglos Jorge | E75: Transferencia | F75: JP
A76: 46074 | B76: Dotación local | C76: 43000 | D76: Arreglos Jorge | E76: Transferencia | F76: ANDRES
A77: 46078 | B77: Mercancía | C77: 13000 | D77: Intereses avances | E77: Transferencia | F77: JP
A78: 46083 | B78: Mercancía | C78: 740000 | D78: Mercancía Your Brand | E78: Transferencia | F78: ANDRES
A79: 46083 | B79: Mercancía | C79: 740000 | D79: Mercancía Your Brand | E79: Transferencia | F79: KATHE
A80: 46083 | B80: Mercancía | C80: 740000 | D80: Mercancía Your Brand | E80: Transferencia | F80: JP
A81: 46078 | B81: Empaque (Bolsas, Etiquetas) | C81: 31466 | D81: 50% etiquetas de lavado | E81: Transferencia | F81: JP
A82: 46078 | B82: Ilustraciones/Diseño | C82: =91000-26733 -> 64267 | D82: Molde Camisas Oversized | E82: Transferencia | F82: ANDRES
A83: 46078 | B83: Empaque (Bolsas, Etiquetas) | C83: 249204 | D83: Marquillas y Etiquetas | E83: Transferencia | F83: JP
A84: 46078 | B84: Empaque (Bolsas, Etiquetas) | C84: 249204 | D84: Marquillas y Etiquetas | E84: Transferencia | F84: KATHE
A85: 46078 | B85: Empaque (Bolsas, Etiquetas) | C85: 249204 | D85: Marquillas y Etiquetas | E85: Transferencia | F85: ANDRES
A86: 46078 | B86: Empaque (Bolsas, Etiquetas) | C86: 36534 | D86: 50% etiquetas de lavado | E86: Transferencia | F86: KATHE
A87: 46078 | B87: Empaque (Bolsas, Etiquetas) | C87: 26733 | D87: Molde Camisas Oversized | E87: Transferencia | F87: KATHE
A88: 46079 | B88: Empaque (Bolsas, Etiquetas) | C88: 19277 | D88: Bolsas para ropa | E88: Efectivo | F88: JP
A89: 46079 | B89: Empaque (Bolsas, Etiquetas) | C89: 9011 | D89: Bolsas para ropa | E89: Efectivo | F89: JP
A90: 46080 | B90: Dotación local | C90: 10000 | D90: Tubo vestier | E90: Transferencia | F90: JP
A91: 46081 | B91: Dotación local | C91: 20000 | D91: Tubo vestier | E91: Efectivo | F91: KATHE
A92: 46081 | B92: Empaque (Bolsas, Etiquetas) | C92: 20000 | D92: 50% etiquetas de lavado | E92: Transferencia | F92: ANDRES
A93: 46083 | B93: Mercancía | C93: 556000 | D93: Replicas Bracor | E93: Transferencia | F93: KATHE
A94: 46083 | B94: Mercancía | C94: 1760000 | D94: Mercancía AUREN | E94: Transferencia | F94: KATHE
... A108: 46086 | B108: Mercancía | C108: 150000 | D108: Buzos negros L YourBrand | E108: Transferencia | F108: ANDRES
A109: 46086 | B109: Mercancía | C109: =60000-23600*2 -> 12800 | D109: 2 Boxy fit 220gr | E109: Transferencia | F109: JP
A110: 46086 | B110: Transporte | C110: 5000 | D110: Parqueadero Transporte | E110: Transferencia | F110: JP
A111: 46086 | B111: Mercancía | C111: 23600 | D111: 2 Boxy fit 220gr | E111: Transferencia | F111: ANDRES
A112: 46086 | B112: Mercancía | C112: 23600 | D112: 2 Boxy fit 220gr | E112: Transferencia | F112: KATHE
A113: 46090 | B113: Empaque (Bolsas, Etiquetas) | C113: 176000 | D113: Marquillas de lavado | E113: Transferencia | F113: ORVANN
A114: 46090 | B114: Transporte | C114: =13500-4500 -> 9000 | D114: Taxi para prendas | E114: Efectivo | F114: JP
A115: 46090 | B115: Transporte | C115: =13100-4500 -> 8600 | D115: Taxi para prendas | E115: Transferencia | F115: ANDRES
A116: 46090 | B116: Transporte | C116: 9000 | D116: Taxi para prendas | E116: Transferencia | F116: KATHE
A117: 46092 | B117: Transporte | C117: 10000 | D117: Parqueadero Transporte | E117: Efectivo | F117: JP
A118: 46092 | B118: Empaque (Bolsas, Etiquetas) | C118: =40800-29500 -> 11300 | D118: Bolsas | E118: Transferencia | F118: JP
A119: 46093 | B119: Transporte | C119: 20000 | D119: Domicilio Ganchos | E119: Efectivo | F119: ORVANN
A120: 46092 | B120: Empaque (Bolsas, Etiquetas) | C120: 160000 | D120: Ganchos | E120: Transferencia | F120: ORVANN
A121: 46095 | B121: Publicidad/Marketing | C121: 15000 | D121: Capcut | E121: Transferencia | F121: ANDRES
A122: 46098 | B122: Otro | C122: =312000-96000 -> 216000 | D122: PRESTAMO A CUMBIA Granizado | E122: Transferencia | F122: ORVANN | G122: PRESTAMO A CUMBIA GRANIZADOS
A123: 46091 | B123: Otro | C123: 20000 | D123: Dar efectivo por transferencia | E123: Efectivo | F123: ORVANN
A124: 46099 | B124: Internet | C124: =23000-14900 -> 8100 | D124: Internet Marzo | E124: Transferencia | F124: JP
A125: 46099 | B125: Internet | C125: 14900 | D125: Internet Marzo | E125: Transferencia | F125: ANDRES
A126: 46099 | B126: Empaque (Bolsas, Etiquetas) | C126: 29500 | D126: Bolsas | E126: Transferencia | F126: KATHE
A127: 46100 | B127: Dotación local | C127: 263000 | D127: Organizadores | E127: Transferencia | F127: ORVANN
A128: 46100 | B128: Transporte | C128: 17000 | D128: Taxi de San Diego a Orvann | E128: Transferencia | F128: ORVANN
...

Sheet Costos Fijos
A1: COSTOS FIJOS MENSUALES
A3: CONCEPTO | B3: MONTO (COP) | C3: NOTAS
A4: Arriendo mensual | B4: 1210000
A5: Servicios públicos | B5: 220000 | C5: Estimado
A6: Internet | B6: 69000 | C6: Primeros dos meses $34.500
A7: Persona punto de venta | C7: Por ahora atienden socios (Una vez haya persona vale 3.000.000 mensual)
A8: Digitales | B8: =100000+53000+60000 -> 213000 | C8: Shopify, Google Workspace (Dominio), Capcut
A9: Seguros | B9: 103000
A10: Imprevistos | B10: =SUM(B4:B6)*0.1 -> 149900 | C10: 10% del total
A12: TOTAL | B12: =SUM(B4:B10) -> 1964900

Sheet Análisis Precios
A1: ANÁLISIS DE COSTO REAL POR TIPO DE PRENDA
A2: Incluye: Prenda + Estampado + Etiquetas + Empaque
A4: COSTOS ADICIONALES (EDITAR EN AZUL) | F4: Siempre precio llevando los diseños listos
A5: Concepto | B5: 1-10 uds | C5: 11-50 uds | D5: 51-100 uds | E5: Más de 100 | F5: Notas
A6: Estampado DTF pequeño (pecho) | B6: =25000/8 -> 3125 | C6: =25000/10 -> 2500 | D6: =25000/10 -> 2500 | E6: =25000/12 -> 2083.3333 | F6: Se vende por metro. El metro vale aproximadamente 25.000. Salen tamaño (Aprox 57 cm de ancho): punto corazon (Logo pequeño), media carta (Logo estandar tipo clemont), carta (Figura tamaño carta), oficio y tabloide (Casi estampado completo). Salen unos 100 punto corazón, unas 15 media carta, unas 8 carta, unas 6 oficio y 2 tabloides.
A7: Estampado DTF grande (espalda) | B7: =25000/2 -> 12500 | C7: =25000/3 -> 8333.3333 | D7: =25000/3 -> 8333.3333 | E7: =25000/4 -> 6250 | F7: Llenar después de cotizar
A8: Estampado Serigrafía (1 color) | B8: $8,000 | C8: $5,000 | D8: $3,500 | E8: $2,500 | F8: El metro de vinilo de alta densidad vale aprox 105.000 (sumando el estampado (72.000) plotteado y descolillado (33.000), si se averigua seguro es más barato) - Solo negro, blanco y rojo normalmente / El metro de vinilo vale aprox 80.000 (sumando el estampado (45.000) plotteado y descolillado (35.000), si se averigua seguro es más barato) - Solo negro, blanco y rojo normalmente. Vinilo sale en un solo color, DTF varios. Vinilo queda con un poco de relieve. DTG no se encontró (Proveedor Santiago)
A9: Etiqueta cuello tejida | B9: 1500 | C9: 1000 | D9: 800 | E9: 600 | F9: Mínimo típico: 100 uds
A10: Hang tag (etiqueta colgante) | B10: 1200 | C10: $800 | D10: $600 | E10: $400 | F10: Con diseño e hilo
A11: Bolsa papel con logo | B11: 1500 | C11: 1000 | D11: 800 | E11: 800
A12: Bolsa premium | B12: 3000 | C12: 3000 | D12: 2500 | E12: 2000 | F12: Bolsa Premium
A13: Sticker logo | B13: 500 | C13: 300 | D13: 200 | E13: 150 | F13: Para sellar bolsa y dejar adentro
A16: COSTO REAL POR TIPO DE PRODUCTO
A17: Tipo Prenda | B17: Costo Base AUREN | C17: Estampado | D17: Etiquetas | E17: Empaque | F17: COSTO TOTAL | G17: Precio Venta Sugerido | H17: Margen %
A18: Camisa Básica (sin estampar) | B18: 37000 | C18: 0 | D18: =$B$9+$B$10 -> 2700 | E18: =$B$11+$B$12+$B$13 -> 5000 | F18: =SUM(B18:E18) -> 44700 | G18: 80000 | H18: =IF(G18>0,(G18-F18)/G18,0) -> 0.44125
A19: Camisa Estampada Pecho | B19: 37000 | C19: =B6 -> 3125 | D19: =$B$9+$B$10 -> 2700 | E19: =$B$11+$B$12+$B$13 -> 5000 | F19: =SUM(B19:E19) -> 47825 | G19: 80000 | H19: =IF(G19>0,(G19-F19)/G19,0) -> 0.4021875
A20: Camisa Estampada Espalda | B20: 37000 | C20: =B7 -> 12500 | D20: =$B$9+$B$10 -> 2700 | E20: =$B$11+$B$12+$B$13 -> 5000 | F20: =SUM(B20:E20) -> 57200 | G20: 80000 | H20: =IF(G20>0,(G20-F20)/G20,0) -> 0.285
A21: Camisa Estampada Full (pecho+espalda) | B21: 37000 | C21: =C19+C20 -> 15625 | D21: =$B$9+$B$10 -> 2700 | E21: =$B$11+$B$12+$B$13 -> 5000 | F21: =SUM(B21:E21) -> 60325 | G21: 80000 | H21: =IF(G21>0,(G21-F21)/G21,0) -> 0.2459375
A22: Chompa Capucha Básica | B22: 76000 | C22: $0 | D22: =$B$9+$B$10 -> 2700 | E22: =$B$11+$B$12+$B$13 -> 5000 | F22: =SUM(B22:E22) -> 83700 | G22: 120000 | H22: =IF(G22>0,(G22-F22)/G22,0) -> 0.3025
A23: Chompa Capucha Estampada | B23: 76000 | C23: =C21 -> 15625 | D23: =$B$9+$B$10 -> 2700 | E23: =$B$11+$B$12+$B$13 -> 5000 | F23: =SUM(B23:E23) -> 99325 | G23: 130000 | H23: =IF(G23>0,(G23-F23)/G23,0) -> 0.23596154
A24: Buzo Cuello Redondo Básico | B24: 56000 | C24: $0 | D24: =$B$9+$B$10 -> 2700 | E24: =$B$11+$B$12+$B$13 -> 5000 | F24: =SUM(B24:E24) -> 63700 | G24: 100000 | H24: =IF(G24>0,(G24-F24)/G24,0) -> 0.363
A25: Buzo Estampado | B25: 56000 | C25: =C23 -> 15625 | D25: =$B$9+$B$10 -> 2700 | E25: =$B$11+$B$12+$B$13 -> 5000 | F25: =SUM(B25:E25) -> 79325 | G25: 120000 | H25: =IF(G25>0,(G25-F25)/G25,0) -> 0.33895833
A26: Jogger Básico | B26: 62000 | C26: $0 | D26: =$B$9+$B$10 -> 2700 | E26: =$B$11+$B$12+$B$13 -> 5000 | F26: =SUM(B26:E26) -> 69700 | G26: 100000 | H26: =IF(G26>0,(G26-F26)/G26,0) -> 0.303
A27: Sudadera Bota Recta Básica | B27: 62000 | C27: $0 | D27: =$B$9+$B$10 -> 2700 | E27: =$B$11+$B$12+$B$13 -> 5000 | F27: =SUM(B27:E27) -> 69700 | G27: 100000 | H27: =IF(G27>0,(G27-F27)/G27,0) -> 0.303
A28: Pantaloneta Básica | B28: 49000 | C28: $0 | D28: =$B$9+$B$10 -> 2700 | E28: =$B$11+$B$12+$B$13 -> 5000 | F28: =SUM(B28:E28) -> 56700 | G28: 80000 | H28: =IF(G28>0,(G28-F28)/G28,0) -> 0.29125
A29: Chaqueta Cortavientos Básica | B29: 45000 | C29: $0 | D29: =$B$9+$B$10 -> 2700 | E29: =$B$11+$B$12+$B$13 -> 5000 | F29: =SUM(B29:E29) -> 52700 | G29: 80000 | H29: =IF(G29>0,(G29-F29)/G29,0) -> 0.34125
A30: Chaqueta Cortavientos Estampada | B30: 45000 | C30: =C25 -> 15625 | D30: =$B$9+$B$10 -> 2700 | E30: =$B$11+$B$12+$B$13 -> 5000 | F30: =SUM(B30:E30) -> 68325 | G30: 100000 | H30: =IF(G30>0,(G30-F30)/G30,0) -> 0.31675
A34: ESCENARIOS DE PRECIO DE VENTA - CAMISA ESTAMPADA
A35: Escenario | B35: Costo Total | C35: Precio Venta | D35: Margen $ | E35: Margen % | F35: Comentario
A36: Económico (réplica) | B36: =F21 -> 60325 | C36: 80000 | D36: =C36-B36 -> 19675 | E36: =IF(C36>0,(C36-B36)/C36,0) -> 0.2459375 | F36: Competir con réplicas baratas
A37: Estándar | B37: =F21 -> 60325 | C37: 90000 | D37: =C37-B37 -> 29675 | E37: =IF(C37>0,(C37-B37)/C37,0) -> 0.32972222 | F37: Precio medio del mercado
A38: Premium ORVANN | B38: =F21 -> 60325 | C38: 110000 | D38: =C38-B38 -> 49675 | E38: =IF(C38>0,(C38-B38)/C38,0) -> 0.45159091 | F38: Marca propia, diseño exclusivo
A39: Ultra Premium (edición limitada) | B39: =F21*1.1 -> 66357.5 | C39: 140000 | D39: =C39-B39 -> 73642.5 | E39: =IF(C39>0,(C39-B39)/C39,0) -> 0.52601786 | F39: Colección especial, empaque VHS/Vinilo
A42: NOTAS IMPORTANTES:
A43: Los precios en AZUL son inputs
A44: Para réplicas (Clemont, etc): menor margen pero mayor volumen
A45: Para colecciones ORVANN: mayor margen, menor volumen, más exclusividad

Sheet P.Eq  Proyeccion
A1: MODELO FINANCIERO — ORVANN
A2: Punto de Equilibrio y Proyección de Flujo de Caja a 6 Meses
A4: 1. SUPUESTOS DEL MODELO
A5: Fuente de datos: | B5: Calculado de 38 ventas reales registradas
A7: Costos fijos mensuales | B7: ='Costos Fijos'!B12 -> 1964900
A8: Precio promedio de venta por prenda | B8: =Resumen!B22 -> 91764.706
A9: Costo promedio por prenda | B9: =Resumen!B21 -> 41000
A10: Margen bruto promedio por prenda | B10: =B8-B9 -> 50764.706
A11: Margen bruto % | B11: =B10/B8 -> 0.55320513
A13: 2. PUNTO DE EQUILIBRIO
A14: Fórmula: Costos Fijos / Margen por prenda
A16: Prendas a vender por MES para cubrir costos | B16: =ROUNDUP(B7/B10,0) -> 39
A17: Prendas a vender por DÍA (26 días/mes) | B17: =ROUNDUP(B16/26,0) -> 2
A18: Ventas mensuales mínimas para equilibrio | B18: =B16*B8 -> 3578823.5
A20: 3. PROYECCIÓN FLUJO DE CAJA — 6 MESES (Escenario Base)
A21: Escenario de ventas (prendas/día) | B21: =B17+1 -> 3 | C21: ← Cambiar para simular
B23: Mes 1 | C23: Mes 2 | D23: Mes 3 | E23: Mes 4 | F23: Mes 5 | G23: Mes 6 | H23: TOTAL
A24: Días operativos | B24: 26 | C24: 26 | D24: 26 | E24: 26 | F24: 26 | G24: 26 | H24: =SUM(B24:G24) -> 156
A25: Prendas vendidas | B25: =$B$21*B24 -> 78 | C25: =$B$21*C24 -> 78 | D25: =$B$21*D24 -> 78 | E25: =$B$21*E24 -> 78 | F25: =$B$21*F24 -> 78 | G25: =$B$21*G24 -> 78 | H25: =SUM(B25:G25) -> 468
A27: INGRESOS
A28: Ventas brutas | B28: =B25*$B$8 -> 7157647.1 | C28: =C25*$B$8 -> 7157647.1 | D28: =D25*$B$8 -> 7157647.1 | E28: =E25*$B$8 -> 7157647.1 | F28: =F25*$B$8 -> 7157647.1 | G28: =G25*$B$8 -> 7157647.1 | H28: =SUM(B28:G28) -> 42945882
A30: EGRESOS
A31: Costo mercancía | B31: =B25*$B$9 -> 3198000 | C31: =C25*$B$9 -> 3198000 | D31: =D25*$B$9 -> 3198000 | E31: =E25*$B$9 -> 3198000 | F31: =F25*$B$9 -> 3198000 | G31: =G25*$B$9 -> 3198000 | H31: =SUM(B31:G31) -> 19188000
A32: Estampaciones y empaques (8%) | B32: =B31*8% -> 255840 | C32: =C31*8% -> 255840 | D32: =D31*8% -> 255840 | E32: =E31*8% -> 255840 | F32: =F31*8% -> 255840 | G32: =G31*8% -> 255840 | H32: =SUM(B32:G32) -> 1535040
A33: Costos fijos | B33: =$B$7 -> 1964900 | C33: =$B$7 -> 1964900 | D33: =$B$7 -> 1964900 | E33: =$B$7 -> 1964900 | F33: =$B$7 -> 1964900 | G33: =$B$7 -> 1964900 | H33: =SUM(B33:G33) -> 11789400
A34: Total egresos | B34: =B31+B32+B33 -> 5418740 | C34: =C31+C32+C33 -> 5418740 | D34: =D31+D32+D33 -> 5418740 | E34: =E31+E32+E33 -> 5418740 | F34: =F31+F32+F33 -> 5418740 | G34: =G31+G32+G33 -> 5418740 | H34: =H31+H32+H33 -> 32512440
A36: RESULTADO
A37: Utilidad mensual | B37: =B28-B34 -> 1738907.1 | C37: =C28-C34 -> 1738907.1 | D37: =D28-D34 -> 1738907.1 | E37: =E28-E34 -> 1738907.1 | F37: =F28-F34 -> 1738907.1 | G37: =G28-G34 -> 1738907.1 | H37: =SUM(B37:G37) -> 10433442
A38: Utilidad por socio (3) | B38: =B37/3 -> 579635.69 | C38: =C37/3 -> 579635.69 | D38: =D37/3 -> 579635.69 | E38: =E37/3 -> 579635.69 | F38: =F37/3 -> 579635.69 | G38: =G37/3 -> 579635.69 | H38: =H37/3 -> 3477814.1
A39: Margen neto % | B39: =IFERROR(B37/B28,0) -> 0.24294395 | C39: =IFERROR(C37/C28,0) -> 0.24294395 | D39: =IFERROR(D37/D28,0) -> 0.24294395 | E39: =IFERROR(E37/E28,0) -> 0.24294395 | F39: =IFERROR(F37/F28,0) -> 0.24294395 | G39: =IFERROR(G37/G28,0) -> 0.24294395 | H39: =IFERROR(H37/H28,0) -> 0.24294395
A41: 4. COMPARACIÓN DE ESCENARIOS (Mensual)
B43: Conservador | C43: Base | D43: Optimista | E43: Con Empleado
A44: Prendas/día | B44: 2 | C44: =B21 -> 3 | D44: 5 | E44: 6
A45: Prendas/mes (26 días) | B45: =B44*26 -> 52 | C45: =C44*26 -> 78 | D45: =D44*26 -> 130 | E45: =E44*26 -> 156
A47: Ingresos mensuales | B47: =B45*$B$8 -> 4771764.7 | C47: =C45*$B$8 -> 7157647.1 | D47: =D45*$B$8 -> 11929412 | E47: =E45*$B$8 -> 14315294
A48: Costo mercancía + estampado | B48: =B45*$B$9*1.08 -> 2302560 | C48: =C45*$B$9*1.08 -> 3453840 | D48: =D45*$B$9*1.08 -> 5756400 | E48: =E45*$B$9*1.08 -> 6907680
A49: Costos fijos | B49: =$B$7 -> 1964900 | C49: =$B$7 -> 1964900 | D49: =$B$7 -> 1964900 | E49: =$B$7+3000000 -> 4964900
A50: Total egresos | B50: =B48+B49 -> 4267460 | C50: =C48+C49 -> 5418740 | D50: =D48+D49 -> 7721300 | E50: =E48+E49 -> 11872580
A52: UTILIDAD MENSUAL | B52: =B47-B50 -> 504304.71 | C52: =C47-C50 -> 1738907.1 | D52: =D47-D50 -> 4208111.8 | E52: =E47-E50 -> 2442714.1
A53: UTILIDAD POR SOCIO | B53: =B52/3 -> 168101.57 | C53: =C52/3 -> 579635.69 | D53: =D52/3 -> 1402703.9 | E53: =E52/3 -> 814238.04
A54: Margen neto % | B54: =IFERROR(B52/B47,0) -> 0.10568516 | C54: =IFERROR(C52/C47,0) -> 0.24294395 | D54: =IFERROR(D52/D47,0) -> 0.35275099 | E54: =IFERROR(E52/E47,0) -> 0.17063667
A56: 5. TABLA DE SENSIBILIDAD — Utilidad Mensual según Prendas/día y Precio Promedio
A57: Utilidad = (Precio - Costo×1.08) × Prendas×26 - Costos Fijos
A58: Prendas/día ↓ | Precio Promedio → | B58: 70000 | C58: 80000 | D58: 90000 | E58: =B8 -> 91764.706 | F58: 100000 | G58: 110000 | H58: 120000
A59: 1 | B59: =(B$58-$B$9*1.08)*$A59*26-$B$7 -> -1296180 | C59: =(C$58-$B$9*1.08)*$A59*26-$B$7 -> -1036180 | D59: =(D$58-$B$9*1.08)*$A59*26-$B$7 -> -776180 | E59: =(E$58-$B$9*1.08)*$A59*26-$B$7 -> -730297.65 | F59: =(F$58-$B$9*1.08)*$A59*26-$B$7 -> -516180 | G59: =(G$58-$B$9*1.08)*$A59*26-$B$7 -> -256180 | H59: =(H$58-$B$9*1.08)*$A59*26-$B$7 -> 3820
A60: 2 | B60: =(B$58-$B$9*1.08)*$A60*26-$B$7 -> -627460 | C60: =(C$58-$B$9*1.08)*$A60*26-$B$7 -> -107460 | D60: =(D$58-$B$9*1.08)*$A60*26-$B$7 -> 412540 | E60: =(E$58-$B$9*1.08)*$A60*26-$B$7 -> 504304.71 | F60: =(F$58-$B$9*1.08)*$A60*26-$B$7 -> 932540 | G60: =(G$58-$B$9*1.08)*$A60*26-$B$7 -> 1452540 | H60: =(H$58-$B$9*1.08)*$A60*26-$B$7 -> 1972540
A61: 3 | B61: =(B$58-$B$9*1.08)*$A61*26-$B$7 -> 41260 | C61: =(C$58-$B$9*1.08)*$A61*26-$B$7 -> 821260 | D61: =(D$58-$B$9*1.08)*$A61*26-$B$7 -> 1601260 | E61: =(E$58-$B$9*1.08)*$A61*26-$B$7 -> 1738907.1 | F61: =(F$58-$B$9*1.08)*$A61*26-$B$7 -> 2381260 | G61: =(G$58-$B$9*1.08)*$A61*26-$B$7 -> 3161260 | H61: =(H$58-$B$9*1.08)*$A61*26-$B$7 -> 3941260
A62: 4 | B62: =(B$58-$B$9*1.08)*$A62*26-$B$7 -> 709980 | C62: =(C$58-$B$9*1.08)*$A62*26-$B$7 -> 1749980 | D62: =(D$58-$B$9*1.08)*$A62*26-$B$7 -> 2789980 | E62: =(E$58-$B$9*1.08)*$A62*26-$B$7 -> 2973509.4 | F62: =(F$58-$B$9*1.08)*$A62*26-$B$7 -> 3829980 | G62: =(G$58-$B$9*1.08)*$A62*26-$B$7 -> 4869980 | H62: =(H$58-$B$9*1.08)*$A62*26-$B$7 -> 5909980
A63: 5 | B63: =(B$58-$B$9*1.08)*$A63*26-$B$7 -> 1378700 | C63: =(C$58-$B$9*1.08)*$A63*26-$B$7 -> 2678700 | D63: =(D$58-$B$9*1.08)*$A63*26-$B$7 -> 3978700 | E63: =(E$58-$B$9*1.08)*$A63*26-$B$7 -> 4208111.8 | F63: =(F$58-$B$9*1.08)*$A63*26-$B$7 -> 5278700 | G63: =(G$58-$B$9*1.08)*$A63*26-$B$7 -> 6578700 | H63: =(H$58-$B$9*1.08)*$A63*26-$B$7 -> 7878700
A64: 6 | B64: =(B$58-$B$9*1.08)*$A64*26-$B$7 -> 2047420 | C64: =(C$58-$B$9*1.08)*$A64*26-$B$7 -> 3607420 | D64: =(D$58-$B$9*1.08)*$A64*26-$B$7 -> 5167420 | E64: =(E$58-$B$9*1.08)*$A64*26-$B$7 -> 5442714.1 | F64: =(F$58-$B$9*1.08)*$A64*26-$B$7 -> 6727420 | G64: =(G$58-$B$9*1.08)*$A64*26-$B$7 -> 8287420 | H64: =(H$58-$B$9*1.08)*$A64*26-$B$7 -> 9847420
A65: 7 | B65: =(B$58-$B$9*1.08)*$A65*26-$B$7 -> 2716140 | C65: =(C$58-$B$9*1.08)*$A65*26-$B$7 -> 4536140 | D65: =(D$58-$B$9*1.08)*$A65*26-$B$7 -> 6356140 | E65: =(E$58-$B$9*1.08)*$A65*26-$B$7 -> 6677316.5 | F65: =(F$58-$B$9*1.08)*$A65*26-$B$7 -> 8176140 | G65: =(G$58-$B$9*1.08)*$A65*26-$B$7 -> 9996140 | H65: =(H$58-$B$9*1.08)*$A65*26-$B$7 -> 11816140
A67: 6. INTERPRETACIÓN Y NOTAS CLAVE
A69: PUNTO DE EQUILIBRIO:
A70: • Con los precios y costos actuales, ORVANN necesita vender mínimo 43 prendas/mes (~2/día) para cubrir costos fijos.
A71: • Esto equivale a ventas mínimas de $4,148,382 COP mensuales.
A73: ESCENARIOS:
A74: • Conservador (2/día): Apenas cubre costos. Riesgo de pérdida si bajan ventas.
A75: • Base (3-4/día): Genera utilidad moderada. Meta realista para primeros meses.
A76: • Optimista (5/día): Utilidad sana para reinvertir y crecer.
A77: • Con Empleado (6/día + $3M nómina): Muestra cuánto se necesita si contratan vendedor.

Sheet Cotizador
A1: COTIZADOR DE COMPRAS - ORVANN | C1: Estampado grande DTG | D1: Estampado Punto Corazón DTG | E1: Punto Corazón bordado | F1: Etiquetas Espalda | G1: Marquillas lavado | H1: Bolsa
C2: 12000 | D2: 2000 | E2: 7000 | F2: 600 | G2: 600 | H2: 1000
A3: CATÁLOGO DE PRODUCTOS (Referencia de Costos)
A4: Tipo Producto | B4: Proveedor | C4: Costo Base | D4: Estampado Punto Corazón | E4: Bordado Punto Corazón | F4: Estampado Completo | G4: Etiquetas | H4: Empaque | I4: Costo Unitario | J4: Precio Venta Unitario | K4: Ganancia | L4: Margen | M4: Precio unitario x3 | N4: Precio x3 | O4: Ganancia x3 | P4: Margen x3 | Q4: Precio unitario x6 | R4: Precio x6 | S4: Ganancia x6 | T4: Margen x6 | U4: Precio Unit x12 | V4: Precio x12 | W4: Ganancia x12 | X4: Margen x12 | Y4: Precio Unit x60 + | Z4: Precio x60 + | AA4: Ganancia x60 + | AB4: Margen x60 +
A5: Camisa Oversize | B5: AUREN | C5: 35000 | G5: =$F$2+$G$2 -> 1200 | H5: =$H$2 -> 1000 | I5: =SUM(C5:H5) -> 37200 | J5: 75000 | K5: =J5-I5 -> 37800 | L5: =IF(J5>0,(J5-$I5)/J5,0) -> 0.504 | M5: =ROUNDUP($J5*0.9,-3) -> 68000 | N5: =M5*3 -> 204000 | O5: =N5-I5*3 -> 92400 | P5: =IF(N5>0,(N5-$I5*3)/N5,0) -> 0.45294118 | Q5: =ROUNDUP($J5*0.85,-3) -> 64000 | R5: =Q5*6 -> 384000 | S5: =R5-I5*6 -> 160800 | T5: =IF(R5>0,(R5-$I5*6)/R5,0) -> 0.41875 | U5: =ROUNDUP($J5*0.8,-3) -> 60000 | V5: =U5*12 -> 720000 | W5: =V5-I5*12 -> 273600 | X5: =IF(V5>0,(V5-$I5*12)/V5,0) -> 0.38 | Y5: =ROUNDUP($J5*0.7,-3) -> 53000 | Z5: =Y5*60 -> 3180000 | AA5: =Z5-I5*60 -> 948000 | AB5: =IF(Z5>0,(Z5-$I5*60)/Z5,0) -> 0.29811321
A6: Camisa Oversize Peruana Estampada Punto Corazón | B6: YOUR BRAND | C6: 37000 | D6: =$D$2 -> 2000 | G6: =$F$2+$G$2 -> 1200 | H6: =$H$2 -> 1000 | I6: =SUM(C6:H6) -> 41200 | J6: 120000 | K6: =J6-I6 -> 78800 | L6: =IF(J6>0,(J6-$I6)/J6,0) -> 0.65666667 | M6: =ROUNDUP($J6*0.9,-3) -> 108000 | N6: =M6*3 -> 324000 | O6: =N6-I6*3 -> 200400 | P6: =IF(N6>0,(N6-$I6*3)/N6,0) -> 0.61851852 | Q6: =ROUNDUP($J6*0.85,-3) -> 102000 | R6: =Q6*6 -> 612000 | S6: =R6-I6*6 -> 364800 | T6: =IF(R6>0,(R6-$I6*6)/R6,0) -> 0.59607843 | U6: =ROUNDUP($J6*0.8,-3) -> 96000 | V6: =U6*12 -> 1152000 | W6: =V6-I6*12 -> 657600 | X6: =IF(V6>0,(V6-$I6*12)/V6,0) -> 0.57083333 | Y6: =ROUNDUP($J6*0.7,-3) -> 84000 | Z6: =Y6*60 -> 5040000 | AA6: =Z6-I6*60 -> 2568000 | AB6: =IF(Z6>0,(Z6-$I6*60)/Z6,0) -> 0.50952381
A7: Camisa Oversize Peruana Bordada Punto Corazón | B7: YOUR BRAND | C7: 37000 | E7: =$E$2 -> 7000 | G7: =$F$2+$G$2 -> 1200 | H7: =$H$2 -> 1000 | I7: =SUM(C7:H7) -> 46200 | J7: 120000 | K7: =J7-I7 -> 73800 | L7: =IF(J7>0,(J7-$I7)/J7,0) -> 0.615 | M7: =ROUNDUP($J7*0.9,-3) -> 108000 | N7: =M7*3 -> 324000 | O7: =N7-I7*3 -> 185400 | P7: =IF(N7>0,(N7-$I7*3)/N7,0) -> 0.57222222 | Q7: =ROUNDUP($J7*0.85,-3) -> 102000 | R7: =Q7*6 -> 612000 | S7: =R7-I7*6 -> 334800 | T7: =IF(R7>0,(R7-$I7*6)/R7,0) -> 0.54705882 | U7: =ROUNDUP($J7*0.8,-3) -> 96000 | V7: =U7*12 -> 1152000 | W7: =V7-I7*12 -> 597600 | X7: =IF(V7>0,(V7-$I7*12)/V7,0) -> 0.51875 | Y7: =ROUNDUP($J7*0.7,-3) -> 84000 | Z7: =Y7*60 -> 5040000 | AA7: =Z7-I7*60 -> 2268000 | AB7: =IF(Z7>0,(Z7-$I7*60)/Z7,0) -> 0.45
A8: Camisa Oversize Peruana Bordado Punto Corazón + Estampado Completo | B8: YOUR BRAND | C8: 37000 | E8: =$E$2 -> 7000 | F8: =$C$2 -> 12000 | G8: =$F$2+$G$2 -> 1200 | H8: =$H$2 -> 1000 | I8: =SUM(C8:H8) -> 58200 | J8: 120000 | K8: =J8-I8 -> 61800 | L8: =IF(J8>0,(J8-$I8)/J8,0) -> 0.515 | M8: =ROUNDUP($J8*0.9,-3) -> 108000 | N8: =M8*3 -> 324000 | O8: =N8-I8*3 -> 149400 | P8: =IF(N8>0,(N8-$I8*3)/N8,0) -> 0.46111111 | Q8: =ROUNDUP($J8*0.85,-3) -> 102000 | R8: =Q8*6 -> 612000 | S8: =R8-I8*6 -> 262800 | T8: =IF(R8>0,(R8-$I8*6)/R8,0) -> 0.42941176 | U8: =ROUNDUP($J8*0.8,-3) -> 96000 | V8: =U8*12 -> 1152000 | W8: =V8-I8*12 -> 453600 | X8: =IF(V8>0,(V8-$I8*12)/V8,0) -> 0.39375 | Y8: =ROUNDUP($J8*0.7,-3) -> 84000 | Z8: =Y8*60 -> 5040000 | AA8: =Z8-I8*60 -> 1548000 | AB8: =IF(Z8>0,(Z8-$I8*60)/Z8,0) -> 0.30714286
A9: Camisa Oversize Peruana Estampado Punto Corazón + Estampado Completo | B9: YOUR BRAND | C9: 37000 | D9: =$D$2 -> 2000 | F9: =$C$2 -> 12000 | G9: =$F$2+$G$2 -> 1200 | H9: =$H$2 -> 1000 | I9: =SUM(C9:H9) -> 53200 | J9: 120000 | K9: =J9-I9 -> 66800 | L9: =IF(J9>0,(J9-$I9)/J9,0) -> 0.55666667 | M9: =ROUNDUP($J9*0.9,-3) -> 108000 | N9: =M9*3 -> 324000 | O9: =N9-I9*3 -> 164400 | P9: =IF(N9>0,(N9-$I9*3)/N9,0) -> 0.50740741 | Q9: =ROUNDUP($J9*0.85,-3) -> 102000 | R9: =Q9*6 -> 612000 | S9: =R9-I9*6 -> 292800 | T9: =IF(R9>0,(R9-$I9*6)/R9,0) -> 0.47843137 | U9: =ROUNDUP($J9*0.8,-3) -> 96000 | V9: =U9*12 -> 1152000 | W9: =V9-I9*12 -> 513600 | X9: =IF(V9>0,(V9-$I9*12)/V9,0) -> 0.44583333 | Y9: =ROUNDUP($J9*0.7,-3) -> 84000 | Z9: =Y9*60 -> 5040000 | AA9: =Z9-I9*60 -> 1848000 | AB9: =IF(Z9>0,(Z9-$I9*60)/Z9,0) -> 0.36666667
A10: Camisa Oversize Peruana Básica | B10: YOUR BRAND | C10: 37000 | G10: =$F$2+$G$2 -> 1200 | H10: =$H$2 -> 1000 | I10: =SUM(C10:H10) -> 39200 | J10: 75000 | K10: =J10-I10 -> 35800 | L10: =IF(J10>0,(J10-$I10)/J10,0) -> 0.47733333 | M10: =ROUNDUP($J10*0.9,-3) -> 68000 | N10: =M10*3 -> 204000 | O10: =N10-I10*3 -> 86400 | P10: =IF(N10>0,(N10-$I10*3)/N10,0) -> 0.42352941 | Q10: =ROUNDUP($J10*0.85,-3) -> 64000 | R10: =Q10*6 -> 384000 | S10: =R10-I10*6 -> 148800 | T10: =IF(R10>0,(R10-$I10*6)/R10,0) -> 0.3875 | U10: =ROUNDUP($J10*0.8,-3) -> 60000 | V10: =U10*12 -> 720000 | W10: =V10-I10*12 -> 249600 | X10: =IF(V10>0,(V10-$I10*12)/V10,0) -> 0.34666667 | Y10: =ROUNDUP($J10*0.7,-3) -> 53000 | Z10: =Y10*60 -> 3180000 | AA10: =Z10-I10*60 -> 828000 | AB10: =IF(Z10>0,(Z10-$I10*60)/Z10,0) -> 0.26037736
A11: Camisa Regular Peruana Estampada Punto Corazón | B11: YOUR BRAND | C11: 37000 | D11: =$D$2 -> 2000 | G11: =$F$2+$G$2 -> 1200 | H11: =$H$2 -> 1000 | I11: =SUM(C11:H11) -> 41200 | J11: 120000 | K11: =J11-I11 -> 78800 | L11: =IF(J11>0,(J11-$I11)/J11,0) -> 0.65666667 | M11: =ROUNDUP($J11*0.9,-3) -> 108000 | N11: =M11*3 -> 324000 | O11: =N11-I11*3 -> 200400 | P11: =IF(N11>0,(N11-$I11*3)/N11,0) -> 0.61851852 | Q11: =ROUNDUP($J11*0.85,-3) -> 102000 | R11: =Q11*6 -> 612000 | S11: =R11-I11*6 -> 364800 | T11: =IF(R11>0,(R11-$I11*6)/R11,0) -> 0.59607843 | U11: =ROUNDUP($J11*0.8,-3) -> 96000 | V11: =U11*12 -> 1152000 | W11: =V11-I11*12 -> 657600 | X11: =IF(V11>0,(V11-$I11*12)/V11,0) -> 0.57083333 | Y11: =ROUNDUP($J11*0.7,-3) -> 84000 | Z11: =Y11*60 -> 5040000 | AA11: =Z11-I11*60 -> 2568000 | AB11: =IF(Z11>0,(Z11-$I11*60)/Z11,0) -> 0.50952381
A12: Camisa Regular Peruana Bordada Punto Corazón | B12: YOUR BRAND | C12: 37000 | E12: =$E$2 -> 7000 | G12: =$F$2+$G$2 -> 1200 | H12: =$H$2 -> 1000 | I12: =SUM(C12:H12) -> 46200 | J12: 120000 | K12: =J12-I12 -> 73800 | L12: =IF(J12>0,(J12-$I12)/J12,0) -> 0.615 | M12: =ROUNDUP($J12*0.9,-3) -> 108000 | N12: =M12*3 -> 324000 | O12: =N12-I12*3 -> 185400 | P12: =IF(N12>0,(N12-$I12*3)/N12,0) -> 0.57222222 | Q12: =ROUNDUP($J12*0.85,-3) -> 102000 | R12: =Q12*6 -> 612000 | S12: =R12-I12*6 -> 334800 | T12: =IF(R12>0,(R12-$I12*6)/R12,0) -> 0.54705882 | U12: =ROUNDUP($J12*0.8,-3) -> 96000 | V12: =U12*12 -> 1152000 | W12: =V12-I12*12 -> 597600 | X12: =IF(V12>0,(V12-$I12*12)/V12,0) -> 0.51875 | Y12: =ROUNDUP($J12*0.7,-3) -> 84000 | Z12: =Y12*60 -> 5040000 | AA12: =Z12-I12*60 -> 2268000 | AB12: =IF(Z12>0,(Z12-$I12*60)/Z12,0) -> 0.45
A13: Camisa Regular Peruana Bordado Punto Corazón + Estampado Completo | B13: YOUR BRAND | C13: 37000 | E13: =$E$2 -> 7000 | F13: =$C$2 -> 12000 | G13: =$F$2+$G$2 -> 1200 | H13: =$H$2 -> 1000 | I13: =SUM(C13:H13) -> 58200 | J13: 120000 | K13: =J13-I13 -> 61800 | L13: =IF(J13>0,(J13-$I13)/J13,0) -> 0.515 | M13: =ROUNDUP($J13*0.9,-3) -> 108000 | N13: =M13*3 -> 324000 | O13: =N13-I13*3 -> 149400 | P13: =IF(N13>0,(N13-$I13*3)/N13,0) -> 0.46111111 | Q13: =ROUNDUP($J13*0.85,-3) -> 102000 | R13: =Q13*6 -> 612000 | S13: =R13-I13*6 -> 262800 | T13: =IF(R13>0,(R13-$I13*6)/R13,0) -> 0.42941176 | U13: =ROUNDUP($J13*0.8,-3) -> 96000 | V13: =U13*12 -> 1152000 | W13: =V13-I13*12 -> 453600 | X13: =IF(V13>0,(V13-$I13*12)/V13,0) -> 0.39375 | Y13: =ROUNDUP($J13*0.7,-3) -> 84000 | Z13: =Y13*60 -> 5040000 | AA13: =Z13-I13*60 -> 1548000 | AB13: =IF(Z13>0,(Z13-$I13*60)/Z13,0) -> 0.30714286
A14: Camisa Regular Peruana Estampado Punto Corazón + Estampado Completo | B14: YOUR BRAND | C14: 37000 | D14: =$D$2 -> 2000 | F14: =$C$2 -> 12000 | G14: =$F$2+$G$2 -> 1200 | H14: =$H$2 -> 1000 | I14: =SUM(C14:H14) -> 53200 | J14: 120000 | K14: =J14-I14 -> 66800 | L14: =IF(J14>0,(J14-$I14)/J14,0) -> 0.55666667 | M14: =ROUNDUP($J14*0.9,-3) -> 108000 | N14: =M14*3 -> 324000 | O14: =N14-I14*3 -> 164400 | P14: =IF(N14>0,(N14-$I14*3)/N14,0) -> 0.50740741 | Q14: =ROUNDUP($J14*0.85,-3) -> 102000 | R14: =Q14*6 -> 612000 | S14: =R14-I14*6 -> 292800 | T14: =IF(R14>0,(R14-$I14*6)/R14,0) -> 0.47843137 | U14: =ROUNDUP($J14*0.8,-3) -> 96000 | V14: =U14*12 -> 1152000 | W14: =V14-I14*12 -> 513600 | X14: =IF(V14>0,(V14-$I14*12)/V14,0) -> 0.44583333 | Y14: =ROUNDUP($J14*0.7,-3) -> 84000 | Z14: =Y14*60 -> 5040000 | AA14: =Z14-I14*60 -> 1848000 | AB14: =IF(Z14>0,(Z14-$I14*60)/Z14,0) -> 0.36666667
A15: Camisa Regular Peruana Básica | B15: YOUR BRAND | C15: 37000 | G15: =$F$2+$G$2 -> 1200 | H15: =$H$2 -> 1000 | I15: =SUM(C15:H15) -> 39200 | J15: 75000 | K15: =J15-I15 -> 35800 | L15: =IF(J15>0,(J15-$I15)/J15,0) -> 0.47733333 | M15: =ROUNDUP($J15*0.9,-3) -> 68000 | N15: =M15*3 -> 204000 | O15: =N15-I15*3 -> 86400 | P15: =IF(N15>0,(N15-$I15*3)/N15,0) -> 0.42352941 | Q15: =ROUNDUP($J15*0.85,-3) -> 64000 | R15: =Q15*6 -> 384000 | S15: =R15-I15*6 -> 148800 | T15: =IF(R15>0,(R15-$I15*6)/R15,0) -> 0.3875 | U15: =ROUNDUP($J15*0.8,-3) -> 60000 | V15: =U15*12 -> 720000 | W15: =V15-I15*12 -> 249600 | X15: =IF(V15>0,(V15-$I15*12)/V15,0) -> 0.34666667 | Y15: =ROUNDUP($J15*0.7,-3) -> 53000 | Z15: =Y15*60 -> 3180000 | AA15: =Z15-I15*60 -> 828000 | AB15: =IF(Z15>0,(Z15-$I15*60)/Z15,0) -> 0.26037736
A16: Camisa Boxy fit Peruana Estampada Punto Corazón | B16: YOUR BRAND | C16: 37000 | D16: =$D$2 -> 2000 | G16: =$F$2+$G$2 -> 1200 | H16: =$H$2 -> 1000 | I16: =SUM(C16:H16) -> 41200 | J16: 120000 | K16: =J16-I16 -> 78800 | L16: =IF(J16>0,(J16-$I16)/J16,0) -> 0.65666667 | M16: =ROUNDUP($J16*0.9,-3) -> 108000 | N16: =M16*3 -> 324000 | O16: =N16-I16*3 -> 200400 | P16: =IF(N16>0,(N16-$I16*3)/N16,0) -> 0.61851852 | Q16: =ROUNDUP($J16*0.85,-3) -> 102000 | R16: =Q16*6 -> 612000 | S16: =R16-I16*6 -> 364800 | T16: =IF(R16>0,(R16-$I16*6)/R16,0) -> 0.59607843 | U16: =ROUNDUP($J16*0.8,-3) -> 96000 | V16: =U16*12 -> 1152000 | W16: =V16-I16*12 -> 657600 | X16: =IF(V16>0,(V16-$I16*12)/V16,0) -> 0.57083333 | Y16: =ROUNDUP($J16*0.7,-3) -> 84000 | Z16: =Y16*60 -> 5040000 | AA16: =Z16-I16*60 -> 2568000 | AB16: =IF(Z16>0,(Z16-$I16*60)/Z16,0) -> 0.50952381
A17: Camisa Boxy fit Peruana Bordada Punto Corazón | B17: YOUR BRAND | C17: 37000 | E17: =$E$2 -> 7000 | G17: =$F$2+$G$2 -> 1200 | H17: =$H$2 -> 1000 | I17: =SUM(C17:H17) -> 46200 | J17: 120000 | K17: =J17-I17 -> 73800 | L17: =IF(J17>0,(J17-$I17)/J17,0) -> 0.615 | M17: =ROUNDUP($J17*0.9,-3) -> 108000 | N17: =M17*3 -> 324000 | O17: =N17-I17*3 -> 185400 | P17: =IF(N17>0,(N17-$I17*3)/N17,0) -> 0.57222222 | Q17: =ROUNDUP($J17*0.85,-3) -> 102000 | R17: =Q17*6 -> 612000 | S17: =R17-I17*6 -> 334800 | T17: =IF(R17>0,(R17-$I17*6)/R17,0) -> 0.54705882 | U17: =ROUNDUP($J17*0.8,-3) -> 96000 | V17: =U17*12 -> 1152000 | W17: =V17-I17*12 -> 597600 | X17: =IF(V17>0,(V17-$I17*12)/V17,0) -> 0.51875 | Y17: =ROUNDUP($J17*0.7,-3) -> 84000 | Z17: =Y17*60 -> 5040000 | AA17: =Z17-I17*60 -> 2268000 | AB17: =IF(Z17>0,(Z17-$I17*60)/Z17,0) -> 0.45
A18: Camisa Boxy fit Peruana Bordado Punto Corazón + Estampado Completo | B18: YOUR BRAND | C18: 37000 | E18: =$E$2 -> 7000 | F18: =$C$2 -> 12000 | G18: =$F$2+$G$2 -> 1200 | H18: =$H$2 -> 1000 | I18: =SUM(C18:H18) -> 58200 | J18: 120000 | K18: =J18-I18 -> 61800 | L18: =IF(J18>0,(J18-$I18)/J18,0) -> 0.515 | M18: =ROUNDUP($J18*0.9,-3) -> 108000 | N18: =M18*3 -> 324000 | O18: =N18-I18*3 -> 149400 | P18: =IF(N18>0,(N18-$I18*3)/N18,0) -> 0.46111111 | Q18: =ROUNDUP($J18*0.85,-3) -> 102000 | R18: =Q18*6 -> 612000 | S18: =R18-I18*6 -> 262800 | T18: =IF(R18>0,(R18-$I18*6)/R18,0) -> 0.42941176 | U18: =ROUNDUP($J18*0.8,-3) -> 96000 | V18: =U18*12 -> 1152000 | W18: =V18-I18*12 -> 453600 | X18: =IF(V18>0,(V18-$I18*12)/V18,0) -> 0.39375 | Y18: =ROUNDUP($J18*0.7,-3) -> 84000 | Z18: =Y18*60 -> 5040000 | AA18: =Z18-I18*60 -> 1548000 | AB18: =IF(Z18>0,(Z18-$I18*60)/Z18,0) -> 0.30714286
A19: Camisa Boxy fit Peruana Estampado Punto Corazón + Estampado Completo | B19: YOUR BRAND | C19: 37000 | D19: =$D$2 -> 2000 | F19: =$C$2 -> 12000 | G19: =$F$2+$G$2 -> 1200 | H19: =$H$2 -> 1000 | I19: =SUM(C19:H19) -> 53200 | J19: 120000 | K19: =J19-I19 -> 66800 | L19: =IF(J19>0,(J19-$I19)/J19,0) -> 0.55666667 | M19: =ROUNDUP($J19*0.9,-3) -> 108000 | N19: =M19*3 -> 324000 | O19: =N19-I19*3 -> 164400 | P19: =IF(N19>0,(N19-$I19*3)/N19,0) -> 0.50740741 | Q19: =ROUNDUP($J19*0.85,-3) -> 102000 | R19: =Q19*6 -> 612000 | S19: =R19-I19*6 -> 292800 | T19: =IF(R19>0,(R19-$I19*6)/R19,0) -> 0.47843137 | U19: =ROUNDUP($J19*0.8,-3) -> 96000 | V19: =U19*12 -> 1152000 | W19: =V19-I19*12 -> 513600 | X19: =IF(V19>0,(V19-$I19*12)/V19,0) -> 0.44583333 | Y19: =ROUNDUP($J19*0.7,-3) -> 84000 | Z19: =Y19*60 -> 5040000 | AA19: =Z19-I19*60 -> 1848000 | AB19: =IF(Z19>0,(Z19-$I19*60)/Z19,0) -> 0.36666667
A20: Camisa Boxy fit Peruana Básica | B20: YOUR BRAND | C20: 37000 | G20: =$F$2+$G$2 -> 1200 | H20: =$H$2 -> 1000 | I20: =SUM(C20:H20) -> 39200 | J20: 75000 | K20: =J20-I20 -> 35800 | L20: =IF(J20>0,(J20-$I20)/J20,0) -> 0.47733333 | M20: =ROUNDUP($J20*0.9,-3) -> 68000 | N20: =M20*3 -> 204000 | O20: =N20-I20*3 -> 86400 | P20: =IF(N20>0,(N20-$I20*3)/N20,0) -> 0.42352941 | Q20: =ROUNDUP($J20*0.85,-3) -> 64000 | R20: =Q20*6 -> 384000 | S20: =R20-I20*6 -> 148800 | T20: =IF(R20>0,(R20-$I20*6)/R20,0) -> 0.3875 | U20: =ROUNDUP($J20*0.8,-3) -> 60000 | V20: =U20*12 -> 720000 | W20: =V20-I20*12 -> 249600 | X20: =IF(V20>0,(V20-$I20*12)/V20,0) -> 0.34666667 | Y20: =ROUNDUP($J20*0.7,-3) -> 53000 | Z20: =Y20*60 -> 3180000 | AA20: =Z20-I20*60 -> 828000 | AB20: =IF(Z20>0,(Z20-$I20*60)/Z20,0) -> 0.26037736
A21: Chompa Capucha Peruana Bordada Punto Corazón | B21: YOUR BRAND | C21: 90000 | E21: =$E$2 -> 7000 | G21: =$F$2+$G$2 -> 1200 | H21: =$H$2 -> 1000 | I21: =SUM(C21:H21) -> 99200 | J21: 180000 | K21: =J21-I21 -> 80800 | L21: =IF(J21>0,(J21-$I21)/J21,0) -> 0.44888889 | M21: =ROUNDUP($J21*0.9,-3) -> 162000 | N21: =M21*3 -> 486000 | O21: =N21-I21*3 -> 188400 | P21: =IF(N21>0,(N21-$I21*3)/N21,0) -> 0.38765432 | Q21: =ROUNDUP($J21*0.85,-3) -> 153000 | R21: =Q21*6 -> 918000 | S21: =R21-I21*6 -> 322800 | T21: =IF(R21>0,(R21-$I21*6)/R21,0) -> 0.35163399 | U21: =ROUNDUP($J21*0.8,-3) -> 144000 | V21: =U21*12 -> 1728000 | W21: =V21-I21*12 -> 537600 | X21: =IF(V21>0,(V21-$I21*12)/V21,0) -> 0.31111111 | Y21: =ROUNDUP($J21*0.7,-3) -> 126000 | Z21: =Y21*60 -> 7560000 | AA21: =Z21-I21*60 -> 1608000 | AB21: =IF(Z21>0,(Z21-$I21*60)/Z21,0) -> 0.21269841
A22: Chompa Capucha Peruana Básica | B22: YOUR BRAND | C22: 90000 | G22: =$F$2+$G$2 -> 1200 | H22: =$H$2 -> 1000 | I22: =SUM(C22:H22) -> 92200 | J22: 180000 | K22: =J22-I22 -> 87800 | L22: =IF(J22>0,(J22-$I22)/J22,0) -> 0.48777778 | M22: =ROUNDUP($J22*0.9,-3) -> 162000 | N22: =M22*3 -> 486000 | O22: =N22-I22*3 -> 209400 | P22: =IF(N22>0,(N22-$I22*3)/N22,0) -> 0.4308642 | Q22: =ROUNDUP($J22*0.85,-3) -> 153000 | R22: =Q22*6 -> 918000 | S22: =R22-I22*6 -> 364800 | T22: =IF(R22>0,(R22-$I22*6)/R22,0) -> 0.39738562 | U22: =ROUNDUP($J22*0.8,-3) -> 144000 | V22: =U22*12 -> 1728000 | W22: =V22-I22*12 -> 621600 | X22: =IF(V22>0,(V22-$I22*12)/V22,0) -> 0.35972222 | Y22: =ROUNDUP($J22*0.7,-3) -> 126000 | Z22: =Y22*60 -> 7560000 | AA22: =Z22-I22*60 -> 2028000 | AB22: =IF(Z22>0,(Z22-$I22*60)/Z22,0) -> 0.26825397
A23: Hoodie Peruano Acid Wash Bordada Punto Corazón | B23: YOUR BRAND | C23: 120000 | E23: =$E$2 -> 7000 | G23: =$F$2+$G$2 -> 1200 | H23: =$H$2 -> 1000 | I23: =SUM(C23:H23) -> 129200 | J23: 200000 | K23: =J23-I23 -> 70800 | L23: =IF(J23>0,(J23-$I23)/J23,0) -> 0.354 | M23: =ROUNDUP($J23*0.9,-3) -> 180000 | N23: =M23*3 -> 540000 | O23: =N23-I23*3 -> 152400 | P23: =IF(N23>0,(N23-$I23*3)/N23,0) -> 0.28222222 | Q23: =ROUNDUP($J23*0.85,-3) -> 170000 | R23: =Q23*6 -> 1020000 | S23: =R23-I23*6 -> 244800 | T23: =IF(R23>0,(R23-$I23*6)/R23,0) -> 0.24 | U23: =ROUNDUP($J23*0.8,-3) -> 160000 | V23: =U23*12 -> 1920000 | W23: =V23-I23*12 -> 369600 | X23: =IF(V23>0,(V23-$I23*12)/V23,0) -> 0.1925 | Y23: =ROUNDUP($J23*0.7,-3) -> 140000 | Z23: =Y23*60 -> 8400000 | AA23: =Z23-I23*60 -> 648000 | AB23: =IF(Z23>0,(Z23-$I23*60)/Z23,0) -> 0.077142857
A24: Hoodie Peruano Acid Wash Básico | B24: YOUR BRAND | C24: 120000 | G24: =$F$2+$G$2 -> 1200 | H24: =$H$2 -> 1000 | I24: =SUM(C24:H24) -> 122200 | J24: 190000 | K24: =J24-I24 -> 67800 | L24: =IF(J24>0,(J24-$I24)/J24,0) -> 0.35684211 | M24: =ROUNDUP($J24*0.9,-3) -> 171000 | N24: =M24*3 -> 513000 | O24: =N24-I24*3 -> 146400 | P24: =IF(N24>0,(N24-$I24*3)/N24,0) -> 0.28538012 | Q24: =ROUNDUP($J24*0.85,-3) -> 162000 | R24: =Q24*6 -> 972000 | S24: =R24-I24*6 -> 238800 | T24: =IF(R24>0,(R24-$I24*6)/R24,0) -> 0.24567901 | U24: =ROUNDUP($J24*0.8,-3) -> 152000 | V24: =U24*12 -> 1824000 | W24: =V24-I24*12 -> 357600 | X24: =IF(V24>0,(V24-$I24*12)/V24,0) -> 0.19605263 | Y24: =ROUNDUP($J24*0.7,-3) -> 133000 | Z24: =Y24*60 -> 7980000 | AA24: =Z24-I24*60 -> 648000 | AB24: =IF(Z24>0,(Z24-$I24*60)/Z24,0) -> 0.081203008
A25: Buzo Cuello Redondo Regular Bordada Punto Corazón | B25: AUREN | C25: 50000 | E25: =$E$2 -> 7000 | G25: =$F$2+$G$2 -> 1200 | H25: =$H$2 -> 1000 | I25: =SUM(C25:H25) -> 59200 | J25: 120000 | K25: =J25-I25 -> 60800 | L25: =IF(J25>0,(J25-$I25)/J25,0) -> 0.50666667 | M25: =ROUNDUP($J25*0.9,-3) -> 108000 | N25: =M25*3 -> 324000 | O25: =N25-I25*3 -> 146400 | P25: =IF(N25>0,(N25-$I25*3)/N25,0) -> 0.45185185 | Q25: =ROUNDUP($J25*0.85,-3) -> 102000 | R25: =Q25*6 -> 612000 | S25: =R25-I25*6 -> 256800 | T25: =IF(R25>0,(R25-$I25*6)/R25,0) -> 0.41960784 | U25: =ROUNDUP($J25*0.8,-3) -> 96000 | V25: =U25*12 -> 1152000 | W25: =V25-I25*12 -> 441600 | X25: =IF(V25>0,(V25-$I25*12)/V25,0) -> 0.38333333 | Y25: =ROUNDUP($J25*0.7,-3) -> 84000 | Z25: =Y25*60 -> 5040000 | AA25: =Z25-I25*60 -> 1488000 | AB25: =IF(Z25>0,(Z25-$I25*60)/Z25,0) -> 0.2952381
A26: Buzo Cuello Redondo Regular + Estampado Completo | B26: AUREN | C26: 50000 | F26: =$C$2 -> 12000 | G26: =$F$2+$G$2 -> 1200 | H26: =$H$2 -> 1000 | I26: =SUM(C26:H26) -> 64200 | J26: 130000 | K26: =J26-I26 -> 65800 | L26: =IF(J26>0,(J26-$I26)/J26,0) -> 0.50615385 | M26: =ROUNDUP($J26*0.9,-3) -> 117000 | N26: =M26*3 -> 351000 | O26: =N26-I26*3 -> 158400 | P26: =IF(N26>0,(N26-$I26*3)/N26,0) -> 0.45128205 | Q26: =ROUNDUP($J26*0.85,-3) -> 111000 | R26: =Q26*6 -> 666000 | S26: =R26-I26*6 -> 280800 | T26: =IF(R26>0,(R26-$I26*6)/R26,0) -> 0.42162162 | U26: =ROUNDUP($J26*0.8,-3) -> 104000 | V26: =U26*12 -> 1248000 | W26: =V26-I26*12 -> 477600 | X26: =IF(V26>0,(V26-$I26*12)/V26,0) -> 0.38269231 | Y26: =ROUNDUP($J26*0.7,-3) -> 91000 | Z26: =Y26*60 -> 5460000 | AA26: =Z26-I26*60 -> 1608000 | AB26: =IF(Z26>0,(Z26-$I26*60)/Z26,0) -> 0.29450549
A27: Buzo Cuello Redondo Regular Bordado Punto Corazón + Estampado Completo | B27: AUREN | C27: 50000 | E27: =$E$2 -> 7000 | F27: =$C$2 -> 12000 | G27: =$F$2+$G$2 -> 1200 | H27: =$H$2 -> 1000 | I27: =SUM(C27:H27) -> 71200 | J27: 140000 | K27: =J27-I27 -> 68800 | L27: =IF(J27>0,(J27-$I27)/J27,0) -> 0.49142857 | M27: =ROUNDUP($J27*0.9,-3) -> 126000 | N27: =M27*3 -> 378000 | O27: =N27-I27*3 -> 164400 | P27: =IF(N27>0,(N27-$I27*3)/N27,0) -> 0.43492063 | Q27: =ROUNDUP($J27*0.85,-3) -> 119000 | R27: =Q27*6 -> 714000 | S27: =R27-I27*6 -> 286800 | T27: =IF(R27>0,(R27-$I27*6)/R27,0) -> 0.40168067 | U27: =ROUNDUP($J27*0.8,-3) -> 112000 | V27: =U27*12 -> 1344000 | W27: =V27-I27*12 -> 489600 | X27: =IF(V27>0,(V27-$I27*12)/V27,0) -> 0.36428571 | Y27: =ROUNDUP($J27*0.7,-3) -> 98000 | Z27: =Y27*60 -> 5880000 | AA27: =Z27-I27*60 -> 1608000 | AB27: =IF(Z27>0,(Z27-$I27*60)/Z27,0) -> 0.27346939
A28: Buzo Cuello Redondo Regular Estampado Punto Corazón + Estampado Completo | B28: AUREN | C28: 50000 | D28: =$D$2 -> 2000 | F28: =$C$2 -> 12000 | G28: =$F$2+$G$2 -> 1200 | H28: =$H$2 -> 1000 | I28: =SUM(C28:H28) -> 66200 | J28: 140000 | K28: =J28-I28 -> 73800 | L28: =IF(J28>0,(J28-$I28)/J28,0) -> 0.52714286 | M28: =ROUNDUP($J28*0.9,-3) -> 126000 | N28: =M28*3 -> 378000 | O28: =N28-I28*3 -> 179400 | P28: =IF(N28>0,(N28-$I28*3)/N28,0) -> 0.47460317 | Q28: =ROUNDUP($J28*0.85,-3) -> 119000 | R28: =Q28*6 -> 714000 | S28: =R28-I28*6 -> 316800 | T28: =IF(R28>0,(R28-$I28*6)/R28,0) -> 0.44369748 | U28: =ROUNDUP($J28*0.8,-3) -> 112000 | V28: =U28*12 -> 1344000 | W28: =V28-I28*12 -> 549600 | X28: =IF(V28>0,(V28-$I28*12)/V28,0) -> 0.40892857 | Y28: =ROUNDUP($J28*0.7,-3) -> 98000 | Z28: =Y28*60 -> 5880000 | AA28: =Z28-I28*60 -> 1908000 | AB28: =IF(Z28>0,(Z28-$I28*60)/Z28,0) -> 0.3244898
A29: Buzo Cuello Redondo Regular Básico | B29: AUREN | C29: 50000 | G29: =$F$2+$G$2 -> 1200 | H29: =$H$2 -> 1000 | I29: =SUM(C29:H29) -> 52200 | J29: 120000 | K29: =J29-I29 -> 67800 | L29: =IF(J29>0,(J29-$I29)/J29,0) -> 0.565 | M29: =ROUNDUP($J29*0.9,-3) -> 108000 | N29: =M29*3 -> 324000 | O29: =N29-I29*3 -> 167400 | P29: =IF(N29>0,(N29-$I29*3)/N29,0) -> 0.51666667 | Q29: =ROUNDUP($J29*0.85,-3) -> 102000 | R29: =Q29*6 -> 612000 | S29: =R29-I29*6 -> 298800 | T29: =IF(R29>0,(R29-$I29*6)/R29,0) -> 0.48823529 | U29: =ROUNDUP($J29*0.8,-3) -> 96000 | V29: =U29*12 -> 1152000 | W29: =V29-I29*12 -> 525600 | X29: =IF(V29>0,(V29-$I29*12)/V29,0) -> 0.45625 | Y29: =ROUNDUP($J29*0.7,-3) -> 84000 | Z29: =Y29*60 -> 5040000 | AA29: =Z29-I29*60 -> 1908000 | AB29: =IF(Z29>0,(Z29-$I29*60)/Z29,0) -> 0.37857143
A30: Buzo Cuello Redondo Oversized Bordada Punto Corazón | B30: AUREN | C30: 55000 | E30: =$E$2 -> 7000 | G30: =$F$2+$G$2 -> 1200 | H30: =$H$2 -> 1000 | I30: =SUM(C30:H30) -> 64200 | J30: 120000 | K30: =J30-I30 -> 55800 | L30: =IF(J30>0,(J30-$I30)/J30,0) -> 0.465 | M30: =ROUNDUP($J30*0.9,-3) -> 108000 | N30: =M30*3 -> 324000 | O30: =N30-I30*3 -> 131400 | P30: =IF(N30>0,(N30-$I30*3)/N30,0) -> 0.40555556 | Q30: =ROUNDUP($J30*0.85,-3) -> 102000 | R30: =Q30*6 -> 612000 | S30: =R30-I30*6 -> 226800 | T30: =IF(R30>0,(R30-$I30*6)/R30,0) -> 0.37058824 | U30: =ROUNDUP($J30*0.8,-3) -> 96000 | V30: =U30*12 -> 1152000 | W30: =V30-I30*12 -> 381600 | X30: =IF(V30>0,(V30-$I30*12)/V30,0) -> 0.33125 | Y30: =ROUNDUP($J30*0.7,-3) -> 84000 | Z30: =Y30*60 -> 5040000 | AA30: =Z30-I30*60 -> 1188000 | AB30: =IF(Z30>0,(Z30-$I30*60)/Z30,0) -> 0.23571429
A31: Buzo Cuello Redondo Oversized + Estampado Completo | B31: AUREN | C31: 55000 | F31: =$C$2 -> 12000 | G31: =$F$2+$G$2 -> 1200 | H31: =$H$2 -> 1000 | I31: =SUM(C31:H31) -> 69200 | J31: 130000 | K31: =J31-I31 -> 60800 | L31: =IF(J31>0,(J31-$I31)/J31,0) -> 0.46769231 | M31: =ROUNDUP($J31*0.9,-3) -> 117000 | N31: =M31*3 -> 351000 | O31: =N31-I31*3 -> 143400 | P31: =IF(N31>0,(N31-$I31*3)/N31,0) -> 0.40854701 | Q31: =ROUNDUP($J31*0.85,-3) -> 111000 | R31: =Q31*6 -> 666000 | S31: =R31-I31*6 -> 250800 | T31: =IF(R31>0,(R31-$I31*6)/R31,0) -> 0.37657658 | U31: =ROUNDUP($J31*0.8,-3) -> 104000 | V31: =U31*12 -> 1248000 | W31: =V31-I31*12 -> 417600 | X31: =IF(V31>0,(V31-$I31*12)/V31,0) -> 0.33461538 | Y31: =ROUNDUP($J31*0.7,-3) -> 91000 | Z31: =Y31*60 -> 5460000 | AA31: =Z31-I31*60 -> 1308000 | AB31: =IF(Z31>0,(Z31-$I31*60)/Z31,0) -> 0.23956044
A32: Buzo Cuello Redondo Oversized Bordado Punto Corazón + Estampado Completo | B32: AUREN | C32: 55000 | E32: =$E$2 -> 7000 | F32: =$C$2 -> 12000 | G32: =$F$2+$G$2 -> 1200 | H32: =$H$2 -> 1000 | I32: =SUM(C32:H32) -> 76200 | J32: 140000 | K32: =J32-I32 -> 63800 | L32: =IF(J32>0,(J32-$I32)/J32,0) -> 0.45571429 | M32: =ROUNDUP($J32*0.9,-3) -> 126000 | N32: =M32*3 -> 378000 | O32: =N32-I32*3 -> 149400 | P32: =IF(N32>0,(N32-$I32*3)/N32,0) -> 0.3952381 | Q32: =ROUNDUP($J32*0.85,-3) -> 119000 | R32: =Q32*6 -> 714000 | S32: =R32-I32*6 -> 256800 | T32: =IF(R32>0,(R32-$I32*6)/R32,0) -> 0.35966387 | U32: =ROUNDUP($J32*0.8,-3) -> 112000 | V32: =U32*12 -> 1344000 | W32: =V32-I32*12 -> 429600 | X32: =IF(V32>0,(V32-$I32*12)/V32,0) -> 0.31964286 | Y32: =ROUNDUP($J32*0.7,-3) -> 98000 | Z32: =Y32*60 -> 5880000 | AA32: =Z32-I32*60 -> 1308000 | AB32: =IF(Z32>0,(Z32-$I32*60)/Z32,0) -> 0.22244898
A33: Buzo Cuello Redondo Oversized Estampado Punto Corazón + Estampado Completo | B33: AUREN | C33: 55000 | D33: =$D$2 -> 2000 | F33: =$C$2 -> 12000 | G33: =$F$2+$G$2 -> 1200 | H33: =$H$2 -> 1000 | I33: =SUM(C33:H33) -> 71200 | J33: 140000 | K33: =J33-I33 -> 68800 | L33: =IF(J33>0,(J33-$I33)/J33,0) -> 0.49142857 | M33: =ROUNDUP($J33*0.9,-3) -> 126000 | N33: =M33*3 -> 378000 | O33: =N33-I33*3 -> 164400 | P33: =IF(N33>0,(N33-$I33*3)/N33,0) -> 0.43492063 | Q33: =ROUNDUP($J33*0.85,-3) -> 119000 | R33: =Q33*6 -> 714000 | S33: =R33-I33*6 -> 286800 | T33: =IF(R33>0,(R33-$I33*6)/R33,0) -> 0.40168067 | U33: =ROUNDUP($J33*0.8,-3) -> 112000 | V33: =U33*12 -> 1344000 | W33: =V33-I33*12 -> 489600 | X33: =IF(V33>0,(V33-$I33*12)/V33,0) -> 0.36428571 | Y33: =ROUNDUP($J33*0.7,-3) -> 98000 | Z33: =Y33*60 -> 5880000 | AA33: =Z33-I33*60 -> 1608000 | AB33: =IF(Z33>0,(Z33-$I33*60)/Z33,0) -> 0.27346939
A34: Buzo Cuello Redondo Oversized Básico | B34: AUREN | C34: 55000 | G34: =$F$2+$G$2 -> 1200 | H34: =$H$2 -> 1000 | I34: =SUM(C34:H34) -> 57200 | J34: 120000 | K34: =J34-I34 -> 62800 | L34: =IF(J34>0,(J34-$I34)/J34,0) -> 0.52333333 | M34: =ROUNDUP($J34*0.9,-3) -> 108000 | N34: =M34*3 -> 324000 | O34: =N34-I34*3 -> 152400 | P34: =IF(N34>0,(N34-$I34*3)/N34,0) -> 0.47037037 | Q34: =ROUNDUP($J34*0.85,-3) -> 102000 | R34: =Q34*6 -> 612000 | S34: =R34-I34*6 -> 268800 | T34: =IF(R34>0,(R34-$I34*6)/R34,0) -> 0.43921569 | U34: =ROUNDUP($J34*0.8,-3) -> 96000 | V34: =U34*12 -> 1152000 | W34: =V34-I34*12 -> 465600 | X34: =IF(V34>0,(V34-$I34*12)/V34,0) -> 0.40416667 | Y34: =ROUNDUP($J34*0.7,-3) -> 84000 | Z34: =Y34*60 -> 5040000 | AA34: =Z34-I34*60 -> 1608000 | AB34: =IF(Z34>0,(Z34-$I34*60)/Z34,0) -> 0.31904762
A35: Jogger Largo | B35: AUREN | C35: 55000 | G35: =$F$2+$G$2 -> 1200 | H35: =$H$2 -> 1000 | I35: =SUM(C35:H35) -> 57200 | J35: 100000 | K35: =J35-I35 -> 42800 | L35: =IF(J35>0,(J35-$I35)/J35,0) -> 0.428 | M35: =ROUNDUP($J35*0.9,-3) -> 90000 | N35: =M35*3 -> 270000 | O35: =N35-I35*3 -> 98400 | P35: =IF(N35>0,(N35-$I35*3)/N35,0) -> 0.36444444 | Q35: =ROUNDUP($J35*0.85,-3) -> 85000 | R35: =Q35*6 -> 510000 | S35: =R35-I35*6 -> 166800 | T35: =IF(R35>0,(R35-$I35*6)/R35,0) -> 0.32705882 | U35: =ROUNDUP($J35*0.8,-3) -> 80000 | V35: =U35*12 -> 960000 | W35: =V35-I35*12 -> 273600 | X35: =IF(V35>0,(V35-$I35*12)/V35,0) -> 0.285 | Y35: =ROUNDUP($J35*0.7,-3) -> 70000 | Z35: =Y35*60 -> 4200000 | AA35: =Z35-I35*60 -> 768000 | AB35: =IF(Z35>0,(Z35-$I35*60)/Z35,0) -> 0.18285714
A36: Sudadera Bota Recta | B36: AUREN | C36: 55000 | G36: =$F$2+$G$2 -> 1200 | H36: =$H$2 -> 1000 | I36: =SUM(C36:H36) -> 57200 | J36: 100000 | K36: =J36-I36 -> 42800 | L36: =IF(J36>0,(J36-$I36)/J36,0) -> 0.428 | M36: =ROUNDUP($J36*0.9,-3) -> 90000 | N36: =M36*3 -> 270000 | O36: =N36-I36*3 -> 98400 | P36: =IF(N36>0,(N36-$I36*3)/N36,0) -> 0.36444444 | Q36: =ROUNDUP($J36*0.85,-3) -> 85000 | R36: =Q36*6 -> 510000 | S36: =R36-I36*6 -> 166800 | T36: =IF(R36>0,(R36-$I36*6)/R36,0) -> 0.32705882 | U36: =ROUNDUP($J36*0.8,-3) -> 80000 | V36: =U36*12 -> 960000 | W36: =V36-I36*12 -> 273600 | X36: =IF(V36>0,(V36-$I36*12)/V36,0) -> 0.285 | Y36: =ROUNDUP($J36*0.7,-3) -> 70000 | Z36: =Y36*60 -> 4200000 | AA36: =Z36-I36*60 -> 768000 | AB36: =IF(Z36>0,(Z36-$I36*60)/Z36,0) -> 0.18285714
A37: Pantaloneta | B37: AUREN | C37: 45000 | G37: =$F$2+$G$2 -> 1200 | H37: =$H$2 -> 1000 | I37: =SUM(C37:H37) -> 47200 | J37: 90000 | K37: =J37-I37 -> 42800 | L37: =IF(J37>0,(J37-$I37)/J37,0) -> 0.47555556 | M37: =ROUNDUP($J37*0.9,-3) -> 81000 | N37: =M37*3 -> 243000 | O37: =N37-I37*3 -> 101400 | P37: =IF(N37>0,(N37-$I37*3)/N37,0) -> 0.41728395 | Q37: =ROUNDUP($J37*0.85,-3) -> 77000 | R37: =Q37*6 -> 462000 | S37: =R37-I37*6 -> 178800 | T37: =IF(R37>0,(R37-$I37*6)/R37,0) -> 0.38701299 | U37: =ROUNDUP($J37*0.8,-3) -> 72000 | V37: =U37*12 -> 864000 | W37: =V37-I37*12 -> 297600 | X37: =IF(V37>0,(V37-$I37*12)/V37,0) -> 0.34444444 | Y37: =ROUNDUP($J37*0.7,-3) -> 63000 | Z37: =Y37*60 -> 3780000 | AA37: =Z37-I37*60 -> 948000 | AB37: =IF(Z37>0,(Z37-$I37*60)/Z37,0) -> 0.25079365
A38: Chaqueta Cortavientos | B38: AUREN | C38: 40000 | G38: =$F$2+$G$2 -> 1200 | H38: =$H$2 -> 1000 | I38: =SUM(C38:H38) -> 42200 | J38: 110000 | K38: =J38-I38 -> 67800 | L38: =IF(J38>0,(J38-$I38)/J38,0) -> 0.61636364 | M38: =ROUNDUP($J38*0.9,-3) -> 99000 | N38: =M38*3 -> 297000 | O38: =N38-I38*3 -> 170400 | P38: =IF(N38>0,(N38-$I38*3)/N38,0) -> 0.57373737 | Q38: =ROUNDUP($J38*0.85,-3) -> 94000 | R38: =Q38*6 -> 564000 | S38: =R38-I38*6 -> 310800 | T38: =IF(R38>0,(R38-$I38*6)/R38,0) -> 0.55106383 | U38: =ROUNDUP($J38*0.8,-3) -> 88000 | V38: =U38*12 -> 1056000 | W38: =V38-I38*12 -> 549600 | X38: =IF(V38>0,(V38-$I38*12)/V38,0) -> 0.52045455 | Y38: =ROUNDUP($J38*0.7,-3) -> 77000 | Z38: =Y38*60 -> 4620000 | AA38: =Z38-I38*60 -> 2088000 | AB38: =IF(Z38>0,(Z38-$I38*60)/Z38,0) -> 0.45194805
A39: Sudadera Cortavientos | B39: AUREN | C39: 32000 | G39: =$F$2+$G$2 -> 1200 | H39: =$H$2 -> 1000 | I39: =SUM(C39:H39) -> 34200 | J39: 75000 | K39: =J39-I39 -> 40800 | L39: =IF(J39>0,(J39-$I39)/J39,0) -> 0.544 | M39: =ROUNDUP($J39*0.9,-3) -> 68000 | N39: =M39*3 -> 204000 | O39: =N39-I39*3 -> 101400 | P39: =IF(N39>0,(N39-$I39*3)/N39,0) -> 0.49705882 | Q39: =ROUNDUP($J39*0.85,-3) -> 64000 | R39: =Q39*6 -> 384000 | S39: =R39-I39*6 -> 178800 | T39: =IF(R39>0,(R39-$I39*6)/R39,0) -> 0.465625 | U39: =ROUNDUP($J39*0.8,-3) -> 60000 | V39: =U39*12 -> 720000 | W39: =V39-I39*12 -> 309600 | X39: =IF(V39>0,(V39-$I39*12)/V39,0) -> 0.43 | Y39: =ROUNDUP($J39*0.7,-3) -> 53000 | Z39: =Y39*60 -> 3180000 | AA39: =Z39-I39*60 -> 1128000 | AB39: =IF(Z39>0,(Z39-$I39*60)/Z39,0) -> 0.35471698
A40: Gorra | C40: 25000 | E40: 7000 | G40: =$F$2+$G$2 -> 1200 | H40: =$H$2 -> 1000 | I40: =SUM(C40:H40) -> 34200 | J40: 65000 | K40: =J40-I40 -> 30800 | L40: =IF(J40>0,(J40-$I40)/J40,0) -> 0.47384615 | M40: =ROUNDUP($J40*0.9,-3) -> 59000 | N40: =M40*3 -> 177000 | O40: =N40-I40*3 -> 74400 | P40: =IF(N40>0,(N40-$I40*3)/N40,0) -> 0.42033898 | Q40: =ROUNDUP($J40*0.85,-3) -> 56000 | R40: =Q40*6 -> 336000 | S40: =R40-I40*6 -> 130800 | T40: =IF(R40>0,(R40-$I40*6)/R40,0) -> 0.38928571 | U40: =ROUNDUP($J40*0.8,-3) -> 52000 | V40: =U40*12 -> 624000 | W40: =V40-I40*12 -> 213600 | X40: =IF(V40>0,(V40-$I40*12)/V40,0) -> 0.34230769 | Y40: =ROUNDUP($J40*0.7,-3) -> 46000 | Z40: =Y40*60 -> 2760000 | AA40: =Z40-I40*60 -> 708000 | AB40: =IF(Z40>0,(Z40-$I40*60)/Z40,0) -> 0.25652174
A41: Camisa Réplica Y/Out | B41: BRACOR | C41: 60000 | G41: =$F$2+$G$2 -> 1200 | H41: =$H$2 -> 1000 | I41: =SUM(C41:H41) -> 62200 | J41: 75000 | K41: =J41-I41 -> 12800 | L41: =IF(J41>0,(J41-$I41)/J41,0) -> 0.17066667 | M41: 75000 | N41: =M41*3 -> 225000 | O41: =N41-I41*3 -> 38400 | P41: =IF(N41>0,(N41-$I41*3)/N41,0) -> 0.17066667 | Q41: 72000 | R41: =Q41*6 -> 432000 | S41: =R41-I41*6 -> 58800 | T41: =IF(R41>0,(R41-$I41*6)/R41,0) -> 0.13611111 | U41: 70000 | V41: =U41*12 -> 840000 | W41: =V41-I41*12 -> 93600 | X41: =IF(V41>0,(V41-$I41*12)/V41,0) -> 0.11142857 | Y41: 65000 | Z41: =Y41*60 -> 3900000 | AA41: =Z41-I41*60 -> 168000 | AB41: =IF(Z41>0,(Z41-$I41*60)/Z41,0) -> 0.043076923
A42: Camisa Réplica 1.1 | B42: BRACOR | C42: 54000 | G42: =$F$2+$G$2 -> 1200 | H42: =$H$2 -> 1000 | I42: =SUM(C42:H42) -> 56200 | J42: 75000 | K42: =J42-I42 -> 18800 | L42: =IF(J42>0,(J42-$I42)/J42,0) -> 0.25066667 | M42: 75000 | N42: =M42*3 -> 225000 | O42: =N42-I42*3 -> 56400 | P42: =IF(N42>0,(N42-$I42*3)/N42,0) -> 0.25066667 | Q42: 72000 | R42: =Q42*6 -> 432000 | S42: =R42-I42*6 -> 94800 | T42: =IF(R42>0,(R42-$I42*6)/R42,0) -> 0.21944444 | U42: 70000 | V42: =U42*12 -> 840000 | W42: =V42-I42*12 -> 165600 | X42: =IF(V42>0,(V42-$I42*12)/V42,0) -> 0.19714286 | Y42: 65000 | Z42: =Y42*60 -> 3900000 | AA42: =Z42-I42*60 -> 528000 | AB42: =IF(Z42>0,(Z42-$I42*60)/Z42,0) -> 0.13538462
A44: PLANIFICADOR DE COMPRA
A47: Tipo Producto | B47: Talla | C47: Color | D47: Estampado | E47: Cantidad | F47: Provedor | G47: Costo Prenda | H47: Costo Estampado | I47: Costo Etiquetas | J47: Costo Empaque | K47: COSTO TOTAL | L47: Precio Venta Unit. | M47: VENTA TOTAL | N47: Costo Unitario | P47: Margen | Q47: Nombre | R47: Productos | T47: Cantidad | V47: Costo Prendas | Y47: Costo Unitario | Z47: Precio Venta Unit. | AB47: Margen | AC47: Precio unitario x3 | AD47: Precio x3 | AE47: Margen x3 | AF47: Precio unitario x6 | AG47: Precio x6 | AH47: Margen x6 | AI47: Precio Unit x12 | AJ47: Precio x12 + | AK47: Margen x12
A48: Camisa Oversize Peruana | B48: S | C48: Negro | D48: Sin estampar | E48: 1 | F48: =IF(A48="","",VLOOKUP(A48,Cotizador!$A$5:$J$43,2,FALSE)) -> #N/A | G48: =IF(A48="","",VLOOKUP(A48,Cotizador!$A$5:$J$43,3,FALSE)) -> #N/A | H48: =IF(OR(A48="",D48=""),"",IF(D48="Sin estampar",0,IF(D48="Pecho",VLOOKUP(A48,Cotizador!$A$5:$J$43,4,FALSE),IF(D48="Espalda",VLOOKUP(A48,Cotizador!$A$5:$J$43,5,FALSE),VLOOKUP(A48,Cotizador!$A$5:$J$43,4,FALSE)+VLOOKUP(A48,Cotizador!$A$5:$J$43,5,FALSE))))) -> 0 | I48: =IF(A48="","",VLOOKUP(A48,Cotizador!$A$5:$J$43,6,FALSE)) -> #N/A | J48: =IF(A48="","",VLOOKUP(A48,Cotizador!$A$5:$J$43,7,FALSE)) -> #N/A | K48: =IF(OR(A48="",E48=""),"",(G48+H48+I48+J48)*E48) -> #N/A | L48: =IF(A48="","",IF(D48="Sin estampar",VLOOKUP(A48,Cotizador!$A$5:$J$43,8,FALSE),IF(D48="Pecho",VLOOKUP(A48,Cotizador!$A$5:$J$43,10,FALSE),VLOOKUP(A48,Cotizador!$A$5:$J$43,9,FALSE)))) -> #N/A | M48: =IF(OR(A48="",E48=""),"",L48*E48) -> #N/A | N48: =+G48+H48+I48+J48 -> #N/A | P48: =IF(L48>0,(L48-N48)/L48,0) -> #N/A | Q48: =CONCATENATE(A48," ",B48," ",C48) -> Camisa Oversize Peruana S Negro | R48: {=+_xludf.UNIQUE(Q48:Q185)} -> #NAME? | T48: =SUMIF($Q$48:$Q$181,R48,$E$48:$E$181) -> 0 | V48: =E48*G48 -> #N/A | Y48: =N48 -> #N/A | Z48: =L48 -> #N/A | AB48: =P48 -> #N/A | AC48: =ROUNDUP(L48*0.85,-3) -> #N/A | AD48: =AC48*3 -> #N/A | AE48: =IF(AC48>0,(AC48-N48)/AC48,0) -> #N/A | AF48: =ROUNDUP(L48*0.825,-3) -> #N/A | AG48: =AF48*6 -> #N/A | AH48: =IF(AF48>0,(AF48-N48)/AF48,0) -> #N/A | AI48: =ROUNDUP(L48*0.75,-3) -> #N/A | AJ48: =AI48*12 -> #N/A | AK48: =IF(AI48>0,(AI48-N48)/AI48,0) -> #N/A
A49: Camisa Oversize Peruana | B49: M | C49: Negro | D49: Sin estampar | E49: 4 | F49: =IF(A49="","",VLOOKUP(A49,Cotizador!$A$5:$J$43,2,FALSE)) -> #N/A | G49: =IF(A49="","",VLOOKUP(A49,Cotizador!$A$5:$J$43,3,FALSE)) -> #N/A | H49: =IF(OR(A49="",D49=""),"",IF(D49="Sin estampar",0,IF(D49="Pecho",VLOOKUP(A49,Cotizador!$A$5:$J$43,4,FALSE),IF(D49="Espalda",VLOOKUP(A49,Cotizador!$A$5:$J$43,5,FALSE),VLOOKUP(A49,Cotizador!$A$5:$J$43,4,FALSE)+VLOOKUP(A49,Cotizador!$A$5:$J$43,5,FALSE))))) -> 0 | I49: =IF(A49="","",VLOOKUP(A49,Cotizador!$A$5:$J$43,6,FALSE)) -> #N/A | J49: =IF(A49="","",VLOOKUP(A49,Cotizador!$A$5:$J$43,7,FALSE)) -> #N/A | K49: =IF(OR(A49="",E49=""),"",(G49+H49+I49+J49)*E49) -> #N/A | L49: =IF(A49="","",IF(D49="Sin estampar",VLOOKUP(A49,Cotizador!$A$5:$J$43,8,FALSE),IF(D49="Pecho",VLOOKUP(A49,Cotizador!$A$5:$J$43,10,FALSE),VLOOKUP(A49,Cotizador!$A$5:$J$43,9,FALSE)))) -> #N/A | M49: =IF(OR(A49="",E49=""),"",L49*E49) -> #N/A | N49: =+G49+H49+I49+J49 -> #N/A | P49: =IF(L49>0,(L49-N49)/L49,0) -> #N/A | Q49: =CONCATENATE(A49," ",B49," ",C49) -> Camisa Oversize Peruana M Negro | R49: #NAME? | T49: =SUMIF($Q$48:$Q$181,R49,$E$48:$E$181) -> 0 | V49: =E49*G49 -> #N/A | Y49: =N49 -> #N/A | Z49: =L49 -> #N/A | AB49: =P49 -> #N/A | AC49: =ROUNDUP(L49*0.85,-3) -> #N/A | AD49: =AC49*3 -> #N/A | AE49: =IF(AC49>0,(AC49-N49)/AC49,0) -> #N/A | AF49: =ROUNDUP(L49*0.825,-3) -> #N/A | AG49: =AF49*6 -> #N/A | AH49: =IF(AF49>0,(AF49-N49)/AF49,0) -> #N/A | AI49: =ROUNDUP(L49*0.75,-3) -> #N/A | AJ49: =AI49*12 -> #N/A | AK49: =IF(AI49>0,(AI49-N49)/AI49,0) -> #N/A
A50: Camisa Oversize Peruana | B50: L | C50: Negro | D50: Sin estampar | E50: 4 | F50: =IF(A50="","",VLOOKUP(A50,Cotizador!$A$5:$J$43,2,FALSE)) -> #N/A | G50: =IF(A50="","",VLOOKUP(A50,Cotizador!$A$5:$J$43,3,FALSE)) -> #N/A | H50: =IF(OR(A50="",D50=""),"",IF(D50="Sin estampar",0,IF(D50="Pecho",VLOOKUP(A50,Cotizador!$A$5:$J$43,4,FALSE),IF(D50="Espalda",VLOOKUP(A50,Cotizador!$A$5:$J$43,5,FALSE),VLOOKUP(A50,Cotizador!$A$5:$J$43,4,FALSE)+VLOOKUP(A50,Cotizador!$A$5:$J$43,5,FALSE))))) -> 0 | I50: =IF(A50="","",VLOOKUP(A50,Cotizador!$A$5:$J$43,6,FALSE)) -> #N/A | J50: =IF(A50="","",VLOOKUP(A50,Cotizador!$A$5:$J$43,7,FALSE)) -> #N/A | K50: =IF(OR(A50="",E50=""),"",(G50+H50+I50+J50)*E50) -> #N/A | L50: =IF(A50="","",IF(D50="Sin estampar",VLOOKUP(A50,Cotizador!$A$5:$J$43,8,FALSE),IF(D50="Pecho",VLOOKUP(A50,Cotizador!$A$5:$J$43,10,FALSE),VLOOKUP(A50,Cotizador!$A$5:$J$43,9,FALSE)))) -> #N/A | M50: =IF(OR(A50="",E50=""),"",L50*E50) -> #N/A | N50: =+G50+H50+I50+J50 -> #N/A | P50: =IF(L50>0,(L50-N50)/L50,0) -> #N/A | Q50: =CONCATENATE(A50," ",B50," ",C50) -> Camisa Oversize Peruana L Negro | R50: #NAME? | T50: =SUMIF($Q$48:$Q$181,R50,$E$48:$E$181) -> 0 | V50: =E50*G50 -> #N/A | Y50: =N50 -> #N/A | Z50: =L50 -> #N/A | AB50: =P50 -> #N/A | AC50: =ROUNDUP(L50*0.85,-3) -> #N/A | AD50: =AC50*3 -> #N/A | AE50: =IF(AC50>0,(AC50-N50)/AC50,0) -> #N/A | AF50: =ROUNDUP(L50*0.825,-3) -> #N/A | AG50: =AF50*6 -> #N/A | AH50: =IF(AF50>0,(AF50-N50)/AF50,0) -> #N/A | AI50: =ROUNDUP(L50*0.75,-3) -> #N/A | AJ50: =AI50*12 -> #N/A | AK50: =IF(AI50>0,(AI50-N50)/AI50,0) -> #N/A
A51: Camisa Oversize Peruana | B51: XL | C51: Negro | D51: Sin estampar | E51: 4 | F51: =IF(A51="","",VLOOKUP(A51,Cotizador!$A$5:$J$43,2,FALSE)) -> #N/A | G51: =IF(A51="","",VLOOKUP(A51,Cotizador!$A$5:$J$43,3,FALSE)) -> #N/A | H51: =IF(OR(A51="",D51=""),"",IF(D51="Sin estampar",0,IF(D51="Pecho",VLOOKUP(A51,Cotizador!$A$5:$J$43,4,FALSE),IF(D51="Espalda",VLOOKUP(A51,Cotizador!$A$5:$J$43,5,FALSE),VLOOKUP(A51,Cotizador!$A$5:$J$43,4,FALSE)+VLOOKUP(A51,Cotizador!$A$5:$J$43,5,FALSE))))) -> 0 | I51: =IF(A51="","",VLOOKUP(A51,Cotizador!$A$5:$J$43,6,FALSE)) -> #N/A | J51: =IF(A51="","",VLOOKUP(A51,Cotizador!$A$5:$J$43,7,FALSE)) -> #N/A | K51: =IF(OR(A51="",E51=""),"",(G51+H51+I51+J51)*E51) -> #N/A | L51: =IF(A51="","",IF(D51="Sin estampar",VLOOKUP(A51,Cotizador!$A$5:$J$43,8,FALSE),IF(D51="Pecho",VLOOKUP(A51,Cotizador!$A$5:$J$43,10,FALSE),VLOOKUP(A51,Cotizador!$A$5:$J$43,9,FALSE)))) -> #N/A | M51: =IF(OR(A51="",E51=""),"",L51*E51) -> #N/A | N51: =+G51+H51+I51+J51 -> #N/A | P51: =IF(L51>0,(L51-N51)/L51,0) -> #N/A | Q51: =CONCATENATE(A51," ",B51," ",C51) -> Camisa Oversize Peruana XL Negro | R51: #NAME? | T51: =SUMIF($Q$48:$Q$181,R51,$E$48:$E$181) -> 0 | V51: =E51*G51 -> #N/A | Y51: =N51 -> #N/A | Z51: =L51 -> #N/A | AB51: =P51 -> #N/A | AC51: =ROUNDUP(L51*0.85,-3) -> #N/A | AD51: =AC51*3 -> #N/A | AE51: =IF(AC51>0,(AC51-N51)/AC51,0) -> #N/A | AF51: =ROUNDUP(L51*0.825,-3) -> #N/A | AG51: =AF51*6 -> #N/A | AH51: =IF(AF51>0,(AF51-N51)/AF51,0) -> #N/A | AI51: =ROUNDUP(L51*0.75,-3) -> #N/A | AJ51: =AI51*12 -> #N/A | AK51: =IF(AI51>0,(AI51-N51)/AI51,0) -> #N/A
A52: Camisa Oversize Peruana | B52: S | C52: Blanco | D52: Sin estampar | E52: 1 | F52: =IF(A52="","",VLOOKUP(A52,Cotizador!$A$5:$J$43,2,FALSE)) -> #N/A | G52: =IF(A52="","",VLOOKUP(A52,Cotizador!$A$5:$J$43,3,FALSE)) -> #N/A | H52: =IF(OR(A52="",D52=""),"",IF(D52="Sin estampar",0,IF(D52="Pecho",VLOOKUP(A52,Cotizador!$A$5:$J$43,4,FALSE),IF(D52="Espalda",VLOOKUP(A52,Cotizador!$A$5:$J$43,5,FALSE),VLOOKUP(A52,Cotizador!$A$5:$J$43,4,FALSE)+VLOOKUP(A52,Cotizador!$A$5:$J$43,5,FALSE))))) -> 0 | I52: =IF(A52="","",VLOOKUP(A52,Cotizador!$A$5:$J$43,6,FALSE)) -> #N/A | J52: =IF(A52="","",VLOOKUP(A52,Cotizador!$A$5:$J$43,7,FALSE)) -> #N/A | K52: =IF(OR(A52="",E52=""),"",(G52+H52+I52+J52)*E52) -> #N/A | L52: =IF(A52="","",IF(D52="Sin estampar",VLOOKUP(A52,Cotizador!$A$5:$J$43,8,FALSE),IF(D52="Pecho",VLOOKUP(A52,Cotizador!$A$5:$J$43,10,FALSE),VLOOKUP(A52,Cotizador!$A$5:$J$43,9,FALSE)))) -> #N/A | M52: =IF(OR(A52="",E52=""),"",L52*E52) -> #N/A | N52: =+G52+H52+I52+J52 -> #N/A | P52: =IF(L52>0,(L52-N52)/L52,0) -> #N/A | Q52: =CONCATENATE(A52," ",B52," ",C52) -> Camisa Oversize Peruana S Blanco | R52: #NAME? | T52: =SUMIF($Q$48:$Q$181,R52,$E$48:$E$181) -> 0 | V52: =E52*G52 -> #N/A | Y52: =N52 -> #N/A | Z52: =L52 -> #N/A | AB52: =P52 -> #N/A | AC52: =ROUNDUP(L52*0.85,-3) -> #N/A | AD52: =AC52*3 -> #N/A | AE52: =IF(AC52>0,(AC52-N52)/AC52,0) -> #N/A | AF52: =ROUNDUP(L52*0.825,-3) -> #N/A | AG52: =AF52*6 -> #N/A | AH52: =IF(AF52>0,(AF52-N52)/AF52,0) -> #N/A | AI52: =ROUNDUP(L52*0.75,-3) -> #N/A | AJ52: =AI52*12 -> #N/A | AK52: =IF(AI52>0,(AI52-N52)/AI52,0) -> #N/A
A53: Camisa Oversize Peruana | B53: M | C53: Blanco | D53: Sin estampar | E53: 4 | F53: =IF(A53="","",VLOOKUP(A53,Cotizador!$A$5:$J$43,2,FALSE)) -> #N/A | G53: =IF(A53="","",VLOOKUP(A53,Cotizador!$A$5:$J$43,3,FALSE)) -> #N/A | H53: =IF(OR(A53="",D53=""),"",IF(D53="Sin estampar",0,IF(D53="Pecho",VLOOKUP(A53,Cotizador!$A$5:$J$43,4,FALSE),IF(D53="Espalda",VLOOKUP(A53,Cotizador!$A$5:$J$43,5,FALSE),VLOOKUP(A53,Cotizador!$A$5:$J$43,4,FALSE)+VLOOKUP(A53,Cotizador!$A$5:$J$43,5,FALSE))))) -> 0 | I53: =IF(A53="","",VLOOKUP(A53,Cotizador!$A$5:$J$43,6,FALSE)) -> #N/A | J53: =IF(A53="","",VLOOKUP(A53,Cotizador!$A$5:$J$43,7,FALSE)) -> #N/A | K53: =IF(OR(A53="",E53=""),"",(G53+H53+I53+J53)*E53) -> #N/A | L53: =IF(A53="","",IF(D53="Sin estampar",VLOOKUP(A53,Cotizador!$A$5:$J$43,8,FALSE),IF(D53="Pecho",VLOOKUP(A53,Cotizador!$A$5:$J$43,10,FALSE),VLOOKUP(A53,Cotizador!$A$5:$J$43,9,FALSE)))) -> #N/A | M53: =IF(OR(A53="",E53=""),"",L53*E53) -> #N/A | N53: =+G53+H53+I53+J53 -> #N/A | P53: =IF(L53>0,(L53-N53)/L53,0) -> #N/A | Q53: =CONCATENATE(A53," ",B53," ",C53) -> Camisa Oversize Peruana M Blanco | R53: #NAME? | T53: =SUMIF($Q$48:$Q$181,R53,$E$48:$E$181) -> 0 | V53: =E53*G53 -> #N/A | Y53: =N53 -> #N/A | Z53: =L53 -> #N/A | AB53: =P53 -> #N/A | AC53: =ROUNDUP(L53*0.85,-3) -> #N/A | AD53: =AC53*3 -> #N/A | AE53: =IF(AC53>0,(AC53-N53)/AC53,0) -> #N/A | AF53: =ROUNDUP(L53*0.825,-3) -> #N/A | AG53: =AF53*6 -> #N/A | AH53: =IF(AF53>0,(AF53-N53)/AF53,0) -> #N/A | AI53: =ROUNDUP(L53*0.75,-3) -> #N/A | AJ53: =AI53*12 -> #N/A | AK53: =IF(AI53>0,(AI53-N53)/AI53,0) -> #N/A
A54: Camisa Oversize Peruana | B54: L | C54: Blanco | D54: Sin estampar | E54: 4 | F54: =IF(A54="","",VLOOKUP(A54,Cotizador!$A$5:$J$43,2,FALSE)) -> #N/A | G54: =IF(A54="","",VLOOKUP(A54,Cotizador!$A$5:$J$43,3,FALSE)) -> #N/A | H54: =IF(OR(A54="",D54=""),"",IF(D54="Sin estampar",0,IF(D54="Pecho",VLOOKUP(A54,Cotizador!$A$5:$J$43,4,FALSE),IF(D54="Espalda",VLOOKUP(A54,Cotizador!$A$5:$J$43,5,FALSE),VLOOKUP(A54,Cotizador!$A$5:$J$43,4,FALSE)+VLOOKUP(A54,Cotizador!$A$5:$J$43,5,FALSE))))) -> 0 | I54: =IF(A54="","",VLOOKUP(A54,Cotizador!$A$5:$J$43,6,FALSE)) -> #N/A | J54: =IF(A54="","",VLOOKUP(A54,Cotizador!$A$5:$J$43,7,FALSE)) -> #N/A | K54: =IF(OR(A54="",E54=""),"",(G54+H54+I54+J54)*E54) -> #N/A | L54: =IF(A54="","",IF(D54="Sin estampar",VLOOKUP(A54,Cotizador!$A$5:$J$43,8,FALSE),IF(D54="Pecho",VLOOKUP(A54,Cotizador!$A$5:$J$43,10,FALSE),VLOOKUP(A54,Cotizador!$A$5:$J$43,9,FALSE)))) -> #N/A | M54: =IF(OR(A54="",E54=""),"",L54*E54) -> #N/A | N54: =+G54+H54+I54+J54 -> #N/A | P54: =IF(L54>0,(L54-N54)/L54,0) -> #N/A | Q54: =CONCATENATE(A54," ",B54," ",C54) -> Camisa Oversize Peruana L Blanco | R54: #NAME? | T54: =SUMIF($Q$48:$Q$181,R54,$E$48:$E$181) -> 0 | V54: =E54*G54 -> #N/A | Y54: =N54 -> #N/A | Z54: =L54 -> #N/A | AB54: =P54 -> #N/A | AC54: =ROUNDUP(L54*0.85,-3) -> #N/A | AD54: =AC54*3 -> #N/A | AE54: =IF(AC54>0,(AC54-N54)/AC54,0) -> #N/A | AF54: =ROUNDUP(L54*0.825,-3) -> #N/A | AG54: =AF54*6 -> #N/A | AH54: =IF(AF54>0,(AF54-N54)/AF54,0) -> #N/A | AI54: =ROUNDUP(L54*0.75,-3) -> #N/A | AJ54: =AI54*12 -> #N/A | AK54: =IF(AI54>0,(AI54-N54)/AI54,0) -> #N/A
A55: Camisa Oversize Peruana | B55: XL | C55: Blanco | D55: Sin estampar | E55: 4 | F55: =IF(A55="","",VLOOKUP(A55,Cotizador!$A$5:$J$43,2,FALSE)) -> #N/A | G55: =IF(A55="","",VLOOKUP(A55,Cotizador!$A$5:$J$43,3,FALSE)) -> #N/A | H55: =IF(OR(A55="",D55=""),"",IF(D55="Sin estampar",0,IF(D55="Pecho",VLOOKUP(A55,Cotizador!$A$5:$J$43,4,FALSE),IF(D55="Espalda",VLOOKUP(A55,Cotizador!$A$5:$J$43,5,FALSE),VLOOKUP(A55,Cotizador!$A$5:$J$43,4,FALSE)+VLOOKUP(A55,Cotizador!$A$5:$J$43,5,FALSE))))) -> 0 | I55: =IF(A55="","",VLOOKUP(A55,Cotizador!$A$5:$J$43,6,FALSE)) -> #N/A | J55: =IF(A55="","",VLOOKUP(A55,Cotizador!$A$5:$J$43,7,FALSE)) -> #N/A | K55: =IF(OR(A55="",E55=""),"",(G55+H55+I55+J55)*E55) -> #N/A | L55: =IF(A55="","",IF(D55="Sin estampar",VLOOKUP(A55,Cotizador!$A$5:$J$43,8,FALSE),IF(D55="Pecho",VLOOKUP(A55,Cotizador!$A$5:$J$43,10,FALSE),VLOOKUP(A55,Cotizador!$A$5:$J$43,9,FALSE)))) -> #N/A | M55: =IF(OR(A55="",E55=""),"",L55*E55) -> #N/A | N55: =+G55+H55+I55+J55 -> #N/A | P55: =IF(L55>0,(L55-N55)/L55,0) -> #N/A | Q55: =CONCATENATE(A55," ",B55," ",C55) -> Camisa Oversize Peruana XL Blanco | R55: #NAME? | T55: =SUMIF($Q$48:$Q$181,R55,$E$48:$E$181) -> 0 | V55: =E55*G55 -> #N/A | Y55: =N55 -> #N/A | Z55: =L55 -> #N/A | AB55: =P55 -> #N/A | AC55: =ROUNDUP(L55*0.85,-3) -> #N/A | AD55: =AC55*3 -> #N/A | AE55: =IF(AC55>0,(AC55-N55)/AC55,0) -> #N/A | AF55: =ROUNDUP(L55*0.825,-3) -> #N/A | AG55: =AF55*6 -> #N/A | AH55: =IF(AF55>0,(AF55-N55)/AF55,0) -> #N/A | AI55: =ROUNDUP(L55*0.75,-3) -> #N/A | AJ55: =AI55*12 -> #N/A | AK55: =IF(AI55>0,(AI55-N55)/AI55,0) -> #N/A
A56: Camisa Oversize Peruana | B56: S | C56: Perla | D56: Sin estampar | E56: 1 | F56: =IF(A56="","",VLOOKUP(A56,Cotizador!$A$5:$J$43,2,FALSE)) -> #N/A | G56: =IF(A56="","",VLOOKUP(A56,Cotizador!$A$5:$J$43,3,FALSE)) -> #N/A | H56: =IF(OR(A56="",D56=""),"",IF(D56="Sin estampar",0,IF(D56="Pecho",VLOOKUP(A56,Cotizador!$A$5:$J$43,4,FALSE),IF(D56="Espalda",VLOOKUP(A56,Cotizador!$A$5:$J$43,5,FALSE),VLOOKUP(A56,Cotizador!$A$5:$J$43,4,FALSE)+VLOOKUP(A56,Cotizador!$A$5:$J$43,5,FALSE))))) -> 0 | I56: =IF(A56="","",VLOOKUP(A56,Cotizador!$A$5:$J$43,6,FALSE)) -> #N/A | J56: =IF(A56="","",VLOOKUP(A56,Cotizador!$A$5:$J$43,7,FALSE)) -> #N/A | K56: =IF(OR(A56="",E56=""),"",(G56+H56+I56+J56)*E56) -> #N/A | L56: =IF(A56="","",IF(D56="Sin estampar",VLOOKUP(A56,Cotizador!$A$5:$J$43,8,FALSE),IF(D56="Pecho",VLOOKUP(A56,Cotizador!$A$5:$J$43,10,FALSE),VLOOKUP(A56,Cotizador!$A$5:$J$43,9,FALSE)))) -> #N/A | M56: =IF(OR(A56="",E56=""),"",L56*E56) -> #N/A | N56: =+G56+H56+I56+J56 -> #N/A | P56: =IF(L56>0,(L56-N56)/L56,0) -> #N/A | Q56: =CONCATENATE(A56," ",B56," ",C56) -> Camisa Oversize Peruana S Perla | R56: #NAME? | T56: =SUMIF($Q$48:$Q$181,R56,$E$48:$E$181) -> 0 | V56: =E56*G56 -> #N/A | Y56: =N56 -> #N/A | Z56: =L56 -> #N/A | AB56: =P56 -> #N/A | AC56: =ROUNDUP(L56*0.85,-3) -> #N/A | AD56: =AC56*3 -> #N/A | AE56: =IF(AC56>0,(AC56-N56)/AC56,0) -> #N/A | AF56: =ROUNDUP(L56*0.825,-3) -> #N/A | AG56: =AF56*6 -> #N/A | AH56: =IF(AF56>0,(AF56-N56)/AF56,0) -> #N/A | AI56: =ROUNDUP(L56*0.75,-3) -> #N/A | AJ56: =AI56*12 -> #N/A | AK56: =IF(AI56>0,(AI56-N56)/AI56,0) -> #N/A
A57: Camisa Oversize Peruana | B57: M | C57: Perla | D57: Sin estampar | E57: 4 | F57: =IF(A57="","",VLOOKUP(A57,Cotizador!$A$5:$J$43,2,FALSE)) -> #N/A | G57: =IF(A57="","",VLOOKUP(A57,Cotizador!$A$5:$J$43,3,FALSE)) -> #N/A | H57: =IF(OR(A57="",D57=""),"",IF(D57="Sin estampar",0,IF(D57="Pecho",VLOOKUP(A57,Cotizador!$A$5:$J$43,4,FALSE),IF(D57="Espalda",VLOOKUP(A57,Cotizador!$A$5:$J$43,5,FALSE),VLOOKUP(A57,Cotizador!$A$5:$J$43,4,FALSE)+VLOOKUP(A57,Cotizador!$A$5:$J$43,5,FALSE))))) -> 0 | I57: =IF(A57="","",VLOOKUP(A57,Cotizador!$A$5:$J$43,6,FALSE)) -> #N/A | J57: =IF(A57="","",VLOOKUP(A57,Cotizador!$A$5:$J$43,7,FALSE)) -> #N/A | K57: =IF(OR(A57="",E57=""),"",(G57+H57+I57+J57)*E57) -> #N/A | L57: =IF(A57="","",IF(D57="Sin estampar",VLOOKUP(A57,Cotizador!$A$5:$J$43,8,FALSE),IF(D57="Pecho",VLOOKUP(A57,Cotizador!$A$5:$J$43,10,FALSE),VLOOKUP(A57,Cotizador!$A$5:$J$43,9,FALSE)))) -> #N/A | M57: =IF(OR(A57="",E57=""),"",L57*E57) -> #N/A | N57: =+G57+H57+I57+J57 -> #N/A | P57: =IF(L57>0,(L57-N57)/L57,0) -> #N/A | Q57: =CONCATENATE(A57," ",B57," ",C57) -> Camisa Oversize Peruana M Perla | R57: #NAME? | T57: =SUMIF($Q$48:$Q$181,R57,$E$48:$E$181) -> 0 | V57: =E57*G57 -> #N/A | Y57: =N57 -> #N/A | Z57: =L57 -> #N/A | AB57: =P57 -> #N/A | AC57: =ROUNDUP(L57*0.85,-3) -> #N/A | AD57: =AC57*3 -> #N/A | AE57: =IF(AC57>0,(AC57-N57)/AC57,0) -> #N/A | AF57: =ROUNDUP(L57*0.825,-3) -> #N/A | AG57: =AF57*6 -> #N/A | AH57: =IF(AF57>0,(AF57-N57)/AF57,0) -> #N/A | AI57: =ROUNDUP(L57*0.75,-3) -> #N/A | AJ57: =AI57*12 -> #N/A | AK57: =IF(AI57>0,(AI57-N57)/AI57,0) -> #N/A
A58: Camisa Oversize Peruana | B58: L | C58: Perla | D58: Sin estampar | E58: 4 | F58: =IF(A58="","",VLOOKUP(A58,Cotizador!$A$5:$J$43,2,FALSE)) -> #N/A | G58: =IF(A58="","",VLOOKUP(A58,Cotizador!$A$5:$J$43,3,FALSE)) -> #N/A | H58: =IF(OR(A58="",D58=""),"",IF(D58="Sin estampar",0,IF(D58="Pecho",VLOOKUP(A58,Cotizador!$A$5:$J$43,4,FALSE),IF(D58="Espalda",VLOOKUP(A58,Cotizador!$A$5:$J$43,5,FALSE),VLOOKUP(A58,Cotizador!$A$5:$J$43,4,FALSE)+VLOOKUP(A58,Cotizador!$A$5:$J$43,5,FALSE))))) -> 0 | I58: =IF(A58="","",VLOOKUP(A58,Cotizador!$A$5:$J$43,6,FALSE)) -> #N/A | J58: =IF(A58="","",VLOOKUP(A58,Cotizador!$A$5:$J$43,7,FALSE)) -> #N/A | K58: =IF(OR(A58="",E58=""),"",(G58+H58+I58+J58)*E58) -> #N/A | L58: =IF(A58="","",IF(D58="Sin estampar",VLOOKUP(A58,Cotizador!$A$5:$J$43,8,FALSE),IF(D58="Pecho",VLOOKUP(A58,Cotizador!$A$5:$J$43,10,FALSE),VLOOKUP(A58,Cotizador!$A$5:$J$43,9,FALSE)))) -> #N/A | M58: =IF(OR(A58="",E58=""),"",L58*E58) -> #N/A | N58: =+G58+H58+I58+J58 -> #N/A | P58: =IF(L58>0,(L58-N58)/L58,0) -> #N/A | Q58: =CONCATENATE(A58," ",B58," ",C58) -> Camisa Oversize Peruana L Perla | R58: #NAME? | T58: =SUMIF($Q$48:$Q$181,R58,$E$48:$E$181) -> 0 | V58: =E58*G58 -> #N/A | Y58: =N58 -> #N/A | Z58: =L58 -> #N/A | AB58: =P58 -> #N/A | AC58: =ROUNDUP(L58*0.85,-3) -> #N/A | AD58: =AC58*3 -> #N/A | AE58: =IF(AC58>0,(AC58-N58)/AC58,0) -> #N/A | AF58: =ROUNDUP(L58*0.825,-3) -> #N/A | AG58: =AF58*6 -> #N/A | AH58: =IF(AF58>0,(AF58-N58)/AF58,0) -> #N/A | AI58: =ROUNDUP(L58*0.75,-3) -> #N/A | AJ58: =AI58*12 -> #N/A | AK58: =IF(AI58>0,(AI58-N58)/AI58,0) -> #N/A
A59: Camisa Oversize Peruana | B59: XL | C59: Perla | D59: Sin estampar | E59: 4 | F59: =IF(A59="","",VLOOKUP(A59,Cotizador!$A$5:$J$43,2,FALSE)) -> #N/A | G59: =IF(A59="","",VLOOKUP(A59,Cotizador!$A$5:$J$43,3,FALSE)) -> #N/A | H59: =IF(OR(A59="",D59=""),"",IF(D59="Sin estampar",0,IF(D59="Pecho",VLOOKUP(A59,Cotizador!$A$5:$J$43,4,FALSE),IF(D59="Espalda",VLOOKUP(A59,Cotizador!$A$5:$J$43,5,FALSE),VLOOKUP(A59,Cotizador!$A$5:$J$43,4,FALSE)+VLOOKUP(A59,Cotizador!$A$5:$J$43,5,FALSE))))) -> 0 | I59: =IF(A59="","",VLOOKUP(A59,Cotizador!$A$5:$J$43,6,FALSE)) -> #N/A | J59: =IF(A59="","",VLOOKUP(A59,Cotizador!$A$5:$J$43,7,FALSE)) -> #N/A | K59: =IF(OR(A59="",E59=""),"",(G59+H59+I59+J59)*E59) -> #N/A | L59: =IF(A59="","",IF(D59="Sin estampar",VLOOKUP(A59,Cotizador!$A$5:$J$43,8,FALSE),IF(D59="Pecho",VLOOKUP(A59,Cotizador!$A$5:$J$43,10,FALSE),VLOOKUP(A59,Cotizador!$A$5:$J$43,9,FALSE)))) -> #N/A | M59: =IF(OR(A59="",E59=""),"",L59*E59) -> #N/A | N59: =+G59+H59+I59+J59 -> #N/A | P59: =IF(L59>0,(L59-N59)/L59,0) -> #N/A | Q59: =CONCATENATE(A59," ",B59," ",C59) -> Camisa Oversize Peruana XL Perla | R59: #NAME? | T59: =SUMIF($Q$48:$Q$181,R59,$E$48:$E$181) -> 0 | V59: =E59*G59 -> #N/A | Y59: =N59 -> #N/A | Z59: =L59 -> #N/A | AB59: =P59 -> #N/A | AC59: =ROUNDUP(L59*0.85,-3) -> #N/A | AD59: =AC59*3 -> #N/A | AE59: =IF(AC59>0,(AC59-N59)/AC59,0) -> #N/A | AF59: =ROUNDUP(L59*0.825,-3) -> #N/A | AG59: =AF59*6 -> #N/A | AH59: =IF(AF59>0,(AF59-N59)/AF59,0) -> #N/A | AI59: =ROUNDUP(L59*0.75,-3) -> #N/A | AJ59: =AI59*12 -> #N/A | AK59: =IF(AI59>0,(AI59-N59)/AI59,0) -> #N/A
A60: Camisa Oversize Peruana | B60: S | C60: Beige | D60: Sin estampar | E60: 1 | F60: =IF(A60="","",VLOOKUP(A60,Cotizador!$A$5:$J$43,2,FALSE)) -> #N/A | G60: =IF(A60="","",VLOOKUP(A60,Cotizador!$A$5:$J$43,3,FALSE)) -> #N/A | H60: =IF(OR(A60="",D60=""),"",IF(D60="Sin estampar",0,IF(D60="Pecho",VLOOKUP(A60,Cotizador!$A$5:$J$43,4,FALSE),IF(D60="Espalda",VLOOKUP(A60,Cotizador!$A$5:$J$43,5,FALSE),VLOOKUP(A60,Cotizador!$A$5:$J$43,4,FALSE)+VLOOKUP(A60,Cotizador!$A$5:$J$43,5,FALSE))))) -> 0 | I60: =IF(A60="","",VLOOKUP(A60,Cotizador!$A$5:$J$43,6,FALSE)) -> #N/A | J60: =IF(A60="","",VLOOKUP(A60,Cotizador!$A$5:$J$43,7,FALSE)) -> #N/A | K60: =IF(OR(A60="",E60=""),"",(G60+H60+I60+J60)*E60) -> #N/A | L60: =IF(A60="","",IF(D60="Sin estampar",VLOOKUP(A60,Cotizador!$A$5:$J$43,8,FALSE),IF(D60="Pecho",VLOOKUP(A60,Cotizador!$A$5:$J$43,10,FALSE),VLOOKUP(A60,Cotizador!$A$5:$J$43,9,FALSE)))) -> #N/A | M60: =IF(OR(A60="",E60=""),"",L60*E60) -> #N/A | N60: =+G60+H60+I60+J60 -> #N/A | P60: =IF(L60>0,(L60-N60)/L60,0) -> #N/A | Q60: =CONCATENATE(A60," ",B60," ",C60) -> Camisa Oversize Peruana S Beige | R60: #NAME? | T60: =SUMIF($Q$48:$Q$181,R60,$E$48:$E$181) -> 0 | V60: =E60*G60 -> #N/A | Y60: =N60 -> #N/A | Z60: =L60 -> #N/A | AB60: =P60 -> #N/A | AC60: =ROUNDUP(L60*0.85,-3) -> #N/A | AD60: =AC60*3 -> #N/A | AE60: =IF(AC60>0,(AC60-N60)/AC60,0) -> #N/A | AF60: =ROUNDUP(L60*0.825,-3) -> #N/A | AG60: =AF60*6 -> #N/A | AH60: =IF(AF60>0,(AF60-N60)/AF60,0) -> #N/A | AI60: =ROUNDUP(L60*0.75,-3) -> #N/A | AJ60: =AI60*12 -> #N/A | AK60: =IF(AI60>0,(AI60-N60)/AI60,0) -> #N/A
... A95: Camisa Oversize Peruana | B95: XL | C95: Negro | D95: Full (Pecho+Espalda) | E95: 2 | F95: =IF(A95="","",VLOOKUP(A95,Cotizador!$A$5:$J$43,2,FALSE)) -> #N/A | G95: =IF(A95="","",VLOOKUP(A95,Cotizador!$A$5:$J$43,3,FALSE)) -> #N/A | H95: =IF(OR(A95="",D95=""),"",IF(D95="Sin estampar",0,IF(D95="Pecho",VLOOKUP(A95,Cotizador!$A$5:$J$43,4,FALSE),IF(D95="Espalda",VLOOKUP(A95,Cotizador!$A$5:$J$43,5,FALSE),VLOOKUP(A95,Cotizador!$A$5:$J$43,4,FALSE)+VLOOKUP(A95,Cotizador!$A$5:$J$43,5,FALSE))))) -> #N/A | I95: =IF(A95="","",VLOOKUP(A95,Cotizador!$A$5:$J$43,6,FALSE)) -> #N/A | J95: =IF(A95="","",VLOOKUP(A95,Cotizador!$A$5:$J$43,7,FALSE)) -> #N/A | K95: =IF(OR(A95="",E95=""),"",(G95+H95+I95+J95)*E95) -> #N/A | L95: =IF(A95="","",IF(D95="Sin estampar",VLOOKUP(A95,Cotizador!$A$5:$J$43,8,FALSE),IF(D95="Pecho",VLOOKUP(A95,Cotizador!$A$5:$J$43,10,FALSE),VLOOKUP(A95,Cotizador!$A$5:$J$43,9,FALSE)))) -> #N/A | M95: =IF(OR(A95="",E95=""),"",L95*E95) -> #N/A | N95: =+G95+H95+I95+J95 -> #N/A | P95: =IF(L95>0,(L95-N95)/L95,0) -> #N/A | Q95: =CONCATENATE(A95," ",B95," ",C95) -> Camisa Oversize Peruana XL Negro | R95: #NAME? | T95: =SUMIF($Q$48:$Q$181,R95,$E$48:$E$181) -> 0 | V95: =E95*G95 -> #N/A | Y95: =N95 -> #N/A | Z95: =L95 -> #N/A | AB95: =P95 -> #N/A | AC95: =ROUNDUP(L95*0.85,-3) -> #N/A | AD95: =AC95*3 -> #N/A | AE95: =IF(AC95>0,(AC95-N95)/AC95,0) -> #N/A | AF95: =ROUNDUP(L95*0.825,-3) -> #N/A | AG95: =AF95*6 -> #N/A | AH95: =IF(AF95>0,(AF95-N95)/AF95,0) -> #N/A | AI95: =ROUNDUP(L95*0.75,-3) -> #N/A | AJ95: =AI95*12 -> #N/A | AK95: =IF(AI95>0,(AI95-N95)/AI95,0) -> #N/A
A96: Camisa Boxy fit | B96: S | C96: Negro | D96: Sin estampar | E96: 1 | F96: YOUR BRAND | G96: =IF(A96="","",VLOOKUP(A96,Cotizador!$A$5:$J$43,3,FALSE)) -> #N/A | H96: =IF(OR(A96="",D96=""),"",IF(D96="Sin estampar",0,IF(D96="Pecho",VLOOKUP(A96,Cotizador!$A$5:$J$43,4,FALSE),IF(D96="Espalda",VLOOKUP(A96,Cotizador!$A$5:$J$43,5,FALSE),VLOOKUP(A96,Cotizador!$A$5:$J$43,4,FALSE)+VLOOKUP(A96,Cotizador!$A$5:$J$43,5,FALSE))))) -> 0 | I96: =IF(A96="","",VLOOKUP(A96,Cotizador!$A$5:$J$43,6,FALSE)) -> #N/A | J96: =IF(A96="","",VLOOKUP(A96,Cotizador!$A$5:$J$43,7,FALSE)) -> #N/A | K96: =IF(OR(A96="",E96=""),"",(G96+H96+I96+J96)*E96) -> #N/A | L96: =IF(A96="","",IF(D96="Sin estampar",VLOOKUP(A96,Cotizador!$A$5:$J$43,8,FALSE),IF(D96="Pecho",VLOOKUP(A96,Cotizador!$A$5:$J$43,10,FALSE),VLOOKUP(A96,Cotizador!$A$5:$J$43,9,FALSE)))) -> #N/A | M96: =IF(OR(A96="",E96=""),"",L96*E96) -> #N/A | N96: =+G96+H96+I96+J96 -> #N/A | P96: =IF(L96>0,(L96-N96)/L96,0) -> #N/A | Q96: =CONCATENATE(A96," ",B96," ",C96) -> Camisa Boxy fit S Negro | R96: #NAME? | T96: =SUMIF($Q$48:$Q$181,R96,$E$48:$E$181) -> 0 | V96: =E96*G96 -> #N/A | Y96: =N96 -> #N/A | Z96: =L96 -> #N/A | AB96: =P96 -> #N/A | AC96: =ROUNDUP(L96*0.85,-3) -> #N/A | AD96: =AC96*3 -> #N/A | AE96: =IF(AC96>0,(AC96-N96)/AC96,0) -> #N/A | AF96: =ROUNDUP(L96*0.825,-3) -> #N/A | AG96: =AF96*6 -> #N/A | AH96: =IF(AF96>0,(AF96-N96)/AF96,0) -> #N/A | AI96: =ROUNDUP(L96*0.75,-3) -> #N/A | AJ96: =AI96*12 -> #N/A | AK96: =IF(AI96>0,(AI96-N96)/AI96,0) -> #N/A
A97: Camisa Boxy fit | B97: M | C97: Negro | D97: Sin estampar | E97: 2 | F97: YOUR BRAND | G97: =IF(A97="","",VLOOKUP(A97,Cotizador!$A$5:$J$43,3,FALSE)) -> #N/A | H97: =IF(OR(A97="",D97=""),"",IF(D97="Sin estampar",0,IF(D97="Pecho",VLOOKUP(A97,Cotizador!$A$5:$J$43,4,FALSE),IF(D97="Espalda",VLOOKUP(A97,Cotizador!$A$5:$J$43,5,FALSE),VLOOKUP(A97,Cotizador!$A$5:$J$43,4,FALSE)+VLOOKUP(A97,Cotizador!$A$5:$J$43,5,FALSE))))) -> 0 | I97: =IF(A97="","",VLOOKUP(A97,Cotizador!$A$5:$J$43,6,FALSE)) -> #N/A | J97: =IF(A97="","",VLOOKUP(A97,Cotizador!$A$5:$J$43,7,FALSE)) -> #N/A | K97: =IF(OR(A97="",E97=""),"",(G97+H97+I97+J97)*E97) -> #N/A | L97: =IF(A97="","",IF(D97="Sin estampar",VLOOKUP(A97,Cotizador!$A$5:$J$43,8,FALSE),IF(D97="Pecho",VLOOKUP(A97,Cotizador!$A$5:$J$43,10,FALSE),VLOOKUP(A97,Cotizador!$A$5:$J$43,9,FALSE)))) -> #N/A | M97: =IF(OR(A97="",E97=""),"",L97*E97) -> #N/A | N97: =+G97+H97+I97+J97 -> #N/A | P97: =IF(L97>0,(L97-N97)/L97,0) -> #N/A | Q97: =CONCATENATE(A97," ",B97," ",C97) -> Camisa Boxy fit M Negro | R97: #NAME? | T97: =SUMIF($Q$48:$Q$181,R97,$E$48:$E$181) -> 0 | V97: =E97*G97 -> #N/A | Y97: =N97 -> #N/A | Z97: =L97 -> #N/A | AB97: =P97 -> #N/A | AC97: =ROUNDUP(L97*0.85,-3) -> #N/A | AD97: =AC97*3 -> #N/A | AE97: =IF(AC97>0,(AC97-N97)/AC97,0) -> #N/A | AF97: =ROUNDUP(L97*0.825,-3) -> #N/A | AG97: =AF97*6 -> #N/A | AH97: =IF(AF97>0,(AF97-N97)/AF97,0) -> #N/A | AI97: =ROUNDUP(L97*0.75,-3) -> #N/A | AJ97: =AI97*12 -> #N/A | AK97: =IF(AI97>0,(AI97-N97)/AI97,0) -> #N/A
A98: Camisa Boxy fit | B98: L | C98: Negro | D98: Sin estampar | E98: 2 | F98: YOUR BRAND | G98: =IF(A98="","",VLOOKUP(A98,Cotizador!$A$5:$J$43,3,FALSE)) -> #N/A | H98: =IF(OR(A98="",D98=""),"",IF(D98="Sin estampar",0,IF(D98="Pecho",VLOOKUP(A98,Cotizador!$A$5:$J$43,4,FALSE),IF(D98="Espalda",VLOOKUP(A98,Cotizador!$A$5:$J$43,5,FALSE),VLOOKUP(A98,Cotizador!$A$5:$J$43,4,FALSE)+VLOOKUP(A98,Cotizador!$A$5:$J$43,5,FALSE))))) -> 0 | I98: =IF(A98="","",VLOOKUP(A98,Cotizador!$A$5:$J$43,6,FALSE)) -> #N/A | J98: =IF(A98="","",VLOOKUP(A98,Cotizador!$A$5:$J$43,7,FALSE)) -> #N/A | K98: =IF(OR(A98="",E98=""),"",(G98+H98+I98+J98)*E98) -> #N/A | L98: =IF(A98="","",IF(D98="Sin estampar",VLOOKUP(A98,Cotizador!$A$5:$J$43,8,FALSE),IF(D98="Pecho",VLOOKUP(A98,Cotizador!$A$5:$J$43,10,FALSE),VLOOKUP(A98,Cotizador!$A$5:$J$43,9,FALSE)))) -> #N/A | M98: =IF(OR(A98="",E98=""),"",L98*E98) -> #N/A | N98: =+G98+H98+I98+J98 -> #N/A | P98: =IF(L98>0,(L98-N98)/L98,0) -> #N/A | Q98: =CONCATENATE(A98," ",B98," ",C98) -> Camisa Boxy fit L Negro | R98: #NAME? | T98: =SUMIF($Q$48:$Q$181,R98,$E$48:$E$181) -> 0 | V98: =E98*G98 -> #N/A | Y98: =N98 -> #N/A | Z98: =L98 -> #N/A | AB98: =P98 -> #N/A | AC98: =ROUNDUP(L98*0.85,-3) -> #N/A | AD98: =AC98*3 -> #N/A | AE98: =IF(AC98>0,(AC98-N98)/AC98,0) -> #N/A | AF98: =ROUNDUP(L98*0.825,-3) -> #N/A | AG98: =AF98*6 -> #N/A | AH98: =IF(AF98>0,(AF98-N98)/AF98,0) -> #N/A | AI98: =ROUNDUP(L98*0.75,-3) -> #N/A | AJ98: =AI98*12 -> #N/A | AK98: =IF(AI98>0,(AI98-N98)/AI98,0) -> #N/A
A99: Camisa Boxy fit | B99: S | C99: Blanco | D99: Sin estampar | E99: 1 | F99: YOUR BRAND | G99: =IF(A99="","",VLOOKUP(A99,Cotizador!$A$5:$J$43,3,FALSE)) -> #N/A | H99: =IF(OR(A99="",D99=""),"",IF(D99="Sin estampar",0,IF(D99="Pecho",VLOOKUP(A99,Cotizador!$A$5:$J$43,4,FALSE),IF(D99="Espalda",VLOOKUP(A99,Cotizador!$A$5:$J$43,5,FALSE),VLOOKUP(A99,Cotizador!$A$5:$J$43,4,FALSE)+VLOOKUP(A99,Cotizador!$A$5:$J$43,5,FALSE))))) -> 0 | I99: =IF(A99="","",VLOOKUP(A99,Cotizador!$A$5:$J$43,6,FALSE)) -> #N/A | J99: =IF(A99="","",VLOOKUP(A99,Cotizador!$A$5:$J$43,7,FALSE)) -> #N/A | K99: =IF(OR(A99="",E99=""),"",(G99+H99+I99+J99)*E99) -> #N/A | L99: =IF(A99="","",IF(D99="Sin estampar",VLOOKUP(A99,Cotizador!$A$5:$J$43,8,FALSE),IF(D99="Pecho",VLOOKUP(A99,Cotizador!$A$5:$J$43,10,FALSE),VLOOKUP(A99,Cotizador!$A$5:$J$43,9,FALSE)))) -> #N/A | M99: =IF(OR(A99="",E99=""),"",L99*E99) -> #N/A | N99: =+G99+H99+I99+J99 -> #N/A | P99: =IF(L99>0,(L99-N99)/L99,0) -> #N/A | Q99: =CONCATENATE(A99," ",B99," ",C99) -> Camisa Boxy fit S Blanco | R99: #NAME? | T99: =SUMIF($Q$48:$Q$181,R99,$E$48:$E$181) -> 0 | V99: =E99*G99 -> #N/A | Y99: =N99 -> #N/A | Z99: =L99 -> #N/A | AB99: =P99 -> #N/A | AC99: =ROUNDUP(L99*0.85,-3) -> #N/A | AD99: =AC99*3 -> #N/A | AE99: =IF(AC99>0,(AC99-N99)/AC99,0) -> #N/A | AF99: =ROUNDUP(L99*0.825,-3) -> #N/A | AG99: =AF99*6 -> #N/A | AH99: =IF(AF99>0,(AF99-N99)/AF99,0) -> #N/A | AI99: =ROUNDUP(L99*0.75,-3) -> #N/A | AJ99: =AI99*12 -> #N/A | AK99: =IF(AI99>0,(AI99-N99)/AI99,0) -> #N/A
A100: Camisa Boxy fit | B100: M | C100: Blanco | D100: Sin estampar | E100: 2 | F100: YOUR BRAND | G100: =IF(A100="","",VLOOKUP(A100,Cotizador!$A$5:$J$43,3,FALSE)) -> #N/A | H100: =IF(OR(A100="",D100=""),"",IF(D100="Sin estampar",0,IF(D100="Pecho",VLOOKUP(A100,Cotizador!$A$5:$J$43,4,FALSE),IF(D100="Espalda",VLOOKUP(A100,Cotizador!$A$5:$J$43,5,FALSE),VLOOKUP(A100,Cotizador!$A$5:$J$43,4,FALSE)+VLOOKUP(A100,Cotizador!$A$5:$J$43,5,FALSE))))) -> 0 | I100: =IF(A100="","",VLOOKUP(A100,Cotizador!$A$5:$J$43,6,FALSE)) -> #N/A | J100: =IF(A100="","",VLOOKUP(A100,Cotizador!$A$5:$J$43,7,FALSE)) -> #N/A | K100: =IF(OR(A100="",E100=""),"",(G100+H100+I100+J100)*E100) -> #N/A | L100: =IF(A100="","",IF(D100="Sin estampar",VLOOKUP(A100,Cotizador!$A$5:$J$43,8,FALSE),IF(D100="Pecho",VLOOKUP(A100,Cotizador!$A$5:$J$43,10,FALSE),VLOOKUP(A100,Cotizador!$A$5:$J$43,9,FALSE)))) -> #N/A | M100: =IF(OR(A100="",E100=""),"",L100*E100) -> #N/A | N100: =+G100+H100+I100+J100 -> #N/A | P100: =IF(L100>0,(L100-N100)/L100,0) -> #N/A | Q100: =CONCATENATE(A100," ",B100," ",C100) -> Camisa Boxy fit M Blanco | R100: #NAME? | T100: =SUMIF($Q$48:$Q$181,R100,$E$48:$E$181) -> 0 | V100: =E100*G100 -> #N/A | Y100: =N100 -> #N/A | Z100: =L100 -> #N/A | AB100: =P100 -> #N/A | AC100: =ROUNDUP(L100*0.85,-3) -> #N/A | AD100: =AC100*3 -> #N/A | AE100: =IF(AC100>0,(AC100-N100)/AC100,0) -> #N/A | AF100: =ROUNDUP(L100*0.825,-3) -> #N/A | AG100: =AF100*6 -> #N/A | AH100: =IF(AF100>0,(AF100-N100)/AF100,0) -> #N/A | AI100: =ROUNDUP(L100*0.75,-3) -> #N/A | AJ100: =AI100*12 -> #N/A | AK100: =IF(AI100>0,(AI100-N100)/AI100,0) -> #N/A
A101: Camisa Boxy fit | B101: L | C101: Blanco | D101: Sin estampar | E101: 2 | F101: YOUR BRAND | G101: =IF(A101="","",VLOOKUP(A101,Cotizador!$A$5:$J$43,3,FALSE)) -> #N/A | H101: =IF(OR(A101="",D101=""),"",IF(D101="Sin estampar",0,IF(D101="Pecho",VLOOKUP(A101,Cotizador!$A$5:$J$43,4,FALSE),IF(D101="Espalda",VLOOKUP(A101,Cotizador!$A$5:$J$43,5,FALSE),VLOOKUP(A101,Cotizador!$A$5:$J$43,4,FALSE)+VLOOKUP(A101,Cotizador!$A$5:$J$43,5,FALSE))))) -> 0 | I101: =IF(A101="","",VLOOKUP(A101,Cotizador!$A$5:$J$43,6,FALSE)) -> #N/A | J101: =IF(A101="","",VLOOKUP(A101,Cotizador!$A$5:$J$43,7,FALSE)) -> #N/A | K101: =IF(OR(A101="",E101=""),"",(G101+H101+I101+J101)*E101) -> #N/A | L101: =IF(A101="","",IF(D101="Sin estampar",VLOOKUP(A101,Cotizador!$A$5:$J$43,8,FALSE),IF(D101="Pecho",VLOOKUP(A101,Cotizador!$A$5:$J$43,10,FALSE),VLOOKUP(A101,Cotizador!$A$5:$J$43,9,FALSE)))) -> #N/A | M101: =IF(OR(A101="",E101=""),"",L101*E101) -> #N/A | N101: =+G101+H101+I101+J101 -> #N/A | P101: =IF(L101>0,(L101-N101)/L101,0) -> #N/A | Q101: =CONCATENATE(A101," ",B101," ",C101) -> Camisa Boxy fit L Blanco | R101: #NAME? | T101: =SUMIF($Q$48:$Q$181,R101,$E$48:$E$181) -> 0 | V101: =E101*G101 -> #N/A | Y101: =N101 -> #N/A | Z101: =L101 -> #N/A | AB101: =P101 -> #N/A | AC101: =ROUNDUP(L101*0.85,-3) -> #N/A | AD101: =AC101*3 -> #N/A | AE101: =IF(AC101>0,(AC101-N101)/AC101,0) -> #N/A | AF101: =ROUNDUP(L101*0.825,-3) -> #N/A | AG101: =AF101*6 -> #N/A | AH101: =IF(AF101>0,(AF101-N101)/AF101,0) -> #N/A | AI101: =ROUNDUP(L101*0.75,-3) -> #N/A | AJ101: =AI101*12 -> #N/A | AK101: =IF(AI101>0,(AI101-N101)/AI101,0) -> #N/A
A102: Camisa Boxy fit | B102: S | C102: Plomo Plata | D102: Sin estampar | E102: 1 | F102: YOUR BRAND | G102: =IF(A102="","",VLOOKUP(A102,Cotizador!$A$5:$J$43,3,FALSE)) -> #N/A | H102: =IF(OR(A102="",D102=""),"",IF(D102="Sin estampar",0,IF(D102="Pecho",VLOOKUP(A102,Cotizador!$A$5:$J$43,4,FALSE),IF(D102="Espalda",VLOOKUP(A102,Cotizador!$A$5:$J$43,5,FALSE),VLOOKUP(A102,Cotizador!$A$5:$J$43,4,FALSE)+VLOOKUP(A102,Cotizador!$A$5:$J$43,5,FALSE))))) -> 0 | I102: =IF(A102="","",VLOOKUP(A102,Cotizador!$A$5:$J$43,6,FALSE)) -> #N/A | J102: =IF(A102="","",VLOOKUP(A102,Cotizador!$A$5:$J$43,7,FALSE)) -> #N/A | K102: =IF(OR(A102="",E102=""),"",(G102+H102+I102+J102)*E102) -> #N/A | L102: =IF(A102="","",IF(D102="Sin estampar",VLOOKUP(A102,Cotizador!$A$5:$J$43,8,FALSE),IF(D102="Pecho",VLOOKUP(A102,Cotizador!$A$5:$J$43,10,FALSE),VLOOKUP(A102,Cotizador!$A$5:$J$43,9,FALSE)))) -> #N/A | M102: =IF(OR(A102="",E102=""),"",L102*E102) -> #N/A | N102: =+G102+H102+I102+J102 -> #N/A | P102: =IF(L102>0,(L102-N102)/L102,0) -> #N/A | Q102: =CONCATENATE(A102," ",B102," ",C102) -> Camisa Boxy fit S Plomo Plata | R102: #NAME? | T102: =SUMIF($Q$48:$Q$181,R102,$E$48:$E$181) -> 0 | V102: =E102*G102 -> #N/A | Y102: =N102 -> #N/A | Z102: =L102 -> #N/A | AB102: =P102 -> #N/A | AC102: =ROUNDUP(L102*0.85,-3) -> #N/A | AD102: =AC102*3 -> #N/A | AE102: =IF(AC102>0,(AC102-N102)/AC102,0) -> #N/A | AF102: =ROUNDUP(L102*0.825,-3) -> #N/A | AG102: =AF102*6 -> #N/A | AH102: =IF(AF102>0,(AF102-N102)/AF102,0) -> #N/A | AI102: =ROUNDUP(L102*0.75,-3) -> #N/A | AJ102: =AI102*12 -> #N/A | AK102: =IF(AI102>0,(AI102-N102)/AI102,0) -> #N/A
A103: Camisa Boxy fit | B103: M | C103: Plomo Plata | D103: Sin estampar | E103: 2 | F103: YOUR BRAND | G103: =IF(A103="","",VLOOKUP(A103,Cotizador!$A$5:$J$43,3,FALSE)) -> #N/A | H103: =IF(OR(A103="",D103=""),"",IF(D103="Sin estampar",0,IF(D103="Pecho",VLOOKUP(A103,Cotizador!$A$5:$J$43,4,FALSE),IF(D103="Espalda",VLOOKUP(A103,Cotizador!$A$5:$J$43,5,FALSE),VLOOKUP(A103,Cotizador!$A$5:$J$43,4,FALSE)+VLOOKUP(A103,Cotizador!$A$5:$J$43,5,FALSE))))) -> 0 | I103: =IF(A103="","",VLOOKUP(A103,Cotizador!$A$5:$J$43,6,FALSE)) -> #N/A | J103: =IF(A103="","",VLOOKUP(A103,Cotizador!$A$5:$J$43,7,FALSE)) -> #N/A | K103: =IF(OR(A103="",E103=""),"",(G103+H103+I103+J103)*E103) -> #N/A | L103: =IF(A103="","",IF(D103="Sin estampar",VLOOKUP(A103,Cotizador!$A$5:$J$43,8,FALSE),IF(D103="Pecho",VLOOKUP(A103,Cotizador!$A$5:$J$43,10,FALSE),VLOOKUP(A103,Cotizador!$A$5:$J$43,9,FALSE)))) -> #N/A | M103: =IF(OR(A103="",E103=""),"",L103*E103) -> #N/A | N103: =+G103+H103+I103+J103 -> #N/A | P103: =IF(L103>0,(L103-N103)/L103,0) -> #N/A | Q103: =CONCATENATE(A103," ",B103," ",C103) -> Camisa Boxy fit M Plomo Plata | R103: #NAME? | T103: =SUMIF($Q$48:$Q$181,R103,$E$48:$E$181) -> 0 | V103: =E103*G103 -> #N/A | Y103: =N103 -> #N/A | Z103: =L103 -> #N/A | AB103: =P103 -> #N/A | AC103: =ROUNDUP(L103*0.85,-3) -> #N/A | AD103: =AC103*3 -> #N/A | AE103: =IF(AC103>0,(AC103-N103)/AC103,0) -> #N/A | AF103: =ROUNDUP(L103*0.825,-3) -> #N/A | AG103: =AF103*6 -> #N/A | AH103: =IF(AF103>0,(AF103-N103)/AF103,0) -> #N/A | AI103: =ROUNDUP(L103*0.75,-3) -> #N/A | AJ103: =AI103*12 -> #N/A | AK103: =IF(AI103>0,(AI103-N103)/AI103,0) -> #N/A
A104: Camisa Boxy fit | B104: L | C104: Plomo Plata | D104: Sin estampar | E104: 2 | F104: YOUR BRAND | G104: =IF(A104="","",VLOOKUP(A104,Cotizador!$A$5:$J$43,3,FALSE)) -> #N/A | H104: =IF(OR(A104="",D104=""),"",IF(D104="Sin estampar",0,IF(D104="Pecho",VLOOKUP(A104,Cotizador!$A$5:$J$43,4,FALSE),IF(D104="Espalda",VLOOKUP(A104,Cotizador!$A$5:$J$43,5,FALSE),VLOOKUP(A104,Cotizador!$A$5:$J$43,4,FALSE)+VLOOKUP(A104,Cotizador!$A$5:$J$43,5,FALSE))))) -> 0 | I104: =IF(A104="","",VLOOKUP(A104,Cotizador!$A$5:$J$43,6,FALSE)) -> #N/A | J104: =IF(A104="","",VLOOKUP(A104,Cotizador!$A$5:$J$43,7,FALSE)) -> #N/A | K104: =IF(OR(A104="",E104=""),"",(G104+H104+I104+J104)*E104) -> #N/A | L104: =IF(A104="","",IF(D104="Sin estampar",VLOOKUP(A104,Cotizador!$A$5:$J$43,8,FALSE),IF(D104="Pecho",VLOOKUP(A104,Cotizador!$A$5:$J$43,10,FALSE),VLOOKUP(A104,Cotizador!$A$5:$J$43,9,FALSE)))) -> #N/A | M104: =IF(OR(A104="",E104=""),"",L104*E104) -> #N/A | N104: =+G104+H104+I104+J104 -> #N/A | P104: =IF(L104>0,(L104-N104)/L104,0) -> #N/A | Q104: =CONCATENATE(A104," ",B104," ",C104) -> Camisa Boxy fit L Plomo Plata | R104: #NAME? | T104: =SUMIF($Q$48:$Q$181,R104,$E$48:$E$181) -> 0 | V104: =E104*G104 -> #N/A | Y104: =N104 -> #N/A | Z104: =L104 -> #N/A | AB104: =P104 -> #N/A | AC104: =ROUNDUP(L104*0.85,-3) -> #N/A | AD104: =AC104*3 -> #N/A | AE104: =IF(AC104>0,(AC104-N104)/AC104,0) -> #N/A | AF104: =ROUNDUP(L104*0.825,-3) -> #N/A | AG104: =AF104*6 -> #N/A | AH104: =IF(AF104>0,(AF104-N104)/AF104,0) -> #N/A | AI104: =ROUNDUP(L104*0.75,-3) -> #N/A | AJ104: =AI104*12 -> #N/A | AK104: =IF(AI104>0,(AI104-N104)/AI104,0) -> #N/A
A105: Camisa Boxy fit | B105: S | C105: Negro | D105: Pecho | E105: 1 | F105: YOUR BRAND | G105: =IF(A105="","",VLOOKUP(A105,Cotizador!$A$5:$J$43,3,FALSE)) -> #N/A | H105: =IF(OR(A105="",D105=""),"",IF(D105="Sin estampar",0,IF(D105="Pecho",VLOOKUP(A105,Cotizador!$A$5:$J$43,4,FALSE),IF(D105="Espalda",VLOOKUP(A105,Cotizador!$A$5:$J$43,5,FALSE),VLOOKUP(A105,Cotizador!$A$5:$J$43,4,FALSE)+VLOOKUP(A105,Cotizador!$A$5:$J$43,5,FALSE))))) -> #N/A | I105: =IF(A105="","",VLOOKUP(A105,Cotizador!$A$5:$J$43,6,FALSE)) -> #N/A | J105: =IF(A105="","",VLOOKUP(A105,Cotizador!$A$5:$J$43,7,FALSE)) -> #N/A | K105: =IF(OR(A105="",E105=""),"",(G105+H105+I105+J105)*E105) -> #N/A | L105: =IF(A105="","",IF(D105="Sin estampar",VLOOKUP(A105,Cotizador!$A$5:$J$43,8,FALSE),IF(D105="Pecho",VLOOKUP(A105,Cotizador!$A$5:$J$43,10,FALSE),VLOOKUP(A105,Cotizador!$A$5:$J$43,9,FALSE)))) -> #N/A | M105: =IF(OR(A105="",E105=""),"",L105*E105) -> #N/A | N105: =+G105+H105+I105+J105 -> #N/A | P105: =IF(L105>0,(L105-N105)/L105,0) -> #N/A | Q105: =CONCATENATE(A105," ",B105," ",C105) -> Camisa Boxy fit S Negro | R105: #NAME? | T105: =SUMIF($Q$48:$Q$181,R105,$E$48:$E$181) -> 0 | V105: =E105*G105 -> #N/A | Y105: =N105 -> #N/A | Z105: =L105 -> #N/A | AB105: =P105 -> #N/A | AC105: =ROUNDUP(L105*0.85,-3) -> #N/A | AD105: =AC105*3 -> #N/A | AE105: =IF(AC105>0,(AC105-N105)/AC105,0) -> #N/A | AF105: =ROUNDUP(L105*0.825,-3) -> #N/A | AG105: =AF105*6 -> #N/A | AH105: =IF(AF105>0,(AF105-N105)/AF105,0) -> #N/A | AI105: =ROUNDUP(L105*0.75,-3) -> #N/A | AJ105: =AI105*12 -> #N/A | AK105: =IF(AI105>0,(AI105-N105)/AI105,0) -> #N/A
A106: Camisa Boxy fit | B106: M | C106: Negro | D106: Pecho | E106: 2 | F106: YOUR BRAND | G106: =IF(A106="","",VLOOKUP(A106,Cotizador!$A$5:$J$43,3,FALSE)) -> #N/A | H106: =IF(OR(A106="",D106=""),"",IF(D106="Sin estampar",0,IF(D106="Pecho",VLOOKUP(A106,Cotizador!$A$5:$J$43,4,FALSE),IF(D106="Espalda",VLOOKUP(A106,Cotizador!$A$5:$J$43,5,FALSE),VLOOKUP(A106,Cotizador!$A$5:$J$43,4,FALSE)+VLOOKUP(A106,Cotizador!$A$5:$J$43,5,FALSE))))) -> #N/A | I106: =IF(A106="","",VLOOKUP(A106,Cotizador!$A$5:$J$43,6,FALSE)) -> #N/A | J106: =IF(A106="","",VLOOKUP(A106,Cotizador!$A$5:$J$43,7,FALSE)) -> #N/A | K106: =IF(OR(A106="",E106=""),"",(G106+H106+I106+J106)*E106) -> #N/A | L106: =IF(A106="","",IF(D106="Sin estampar",VLOOKUP(A106,Cotizador!$A$5:$J$43,8,FALSE),IF(D106="Pecho",VLOOKUP(A106,Cotizador!$A$5:$J$43,10,FALSE),VLOOKUP(A106,Cotizador!$A$5:$J$43,9,FALSE)))) -> #N/A | M106: =IF(OR(A106="",E106=""),"",L106*E106) -> #N/A | N106: =+G106+H106+I106+J106 -> #N/A | P106: =IF(L106>0,(L106-N106)/L106,0) -> #N/A | Q106: =CONCATENATE(A106," ",B106," ",C106) -> Camisa Boxy fit M Negro | R106: #NAME? | T106: =SUMIF($Q$48:$Q$181,R106,$E$48:$E$181) -> 0 | V106: =E106*G106 -> #N/A | Y106: =N106 -> #N/A | Z106: =L106 -> #N/A | AB106: =P106 -> #N/A | AC106: =ROUNDUP(L106*0.85,-3) -> #N/A | AD106: =AC106*3 -> #N/A | AE106: =IF(AC106>0,(AC106-N106)/AC106,0) -> #N/A | AF106: =ROUNDUP(L106*0.825,-3) -> #N/A | AG106: =AF106*6 -> #N/A | AH106: =IF(AF106>0,(AF106-N106)/AF106,0) -> #N/A | AI106: =ROUNDUP(L106*0.75,-3) -> #N/A | AJ106: =AI106*12 -> #N/A | AK106: =IF(AI106>0,(AI106-N106)/AI106,0) -> #N/A
A107: Camisa Boxy fit | B107: L | C107: Negro | D107: Pecho | E107: 2 | F107: YOUR BRAND | G107: =IF(A107="","",VLOOKUP(A107,Cotizador!$A$5:$J$43,3,FALSE)) -> #N/A | H107: =IF(OR(A107="",D107=""),"",IF(D107="Sin estampar",0,IF(D107="Pecho",VLOOKUP(A107,Cotizador!$A$5:$J$43,4,FALSE),IF(D107="Espalda",VLOOKUP(A107,Cotizador!$A$5:$J$43,5,FALSE),VLOOKUP(A107,Cotizador!$A$5:$J$43,4,FALSE)+VLOOKUP(A107,Cotizador!$A$5:$J$43,5,FALSE))))) -> #N/A | I107: =IF(A107="","",VLOOKUP(A107,Cotizador!$A$5:$J$43,6,FALSE)) -> #N/A | J107: =IF(A107="","",VLOOKUP(A107,Cotizador!$A$5:$J$43,7,FALSE)) -> #N/A | K107: =IF(OR(A107="",E107=""),"",(G107+H107+I107+J107)*E107) -> #N/A | L107: =IF(A107="","",IF(D107="Sin estampar",VLOOKUP(A107,Cotizador!$A$5:$J$43,8,FALSE),IF(D107="Pecho",VLOOKUP(A107,Cotizador!$A$5:$J$43,10,FALSE),VLOOKUP(A107,Cotizador!$A$5:$J$43,9,FALSE)))) -> #N/A | M107: =IF(OR(A107="",E107=""),"",L107*E107) -> #N/A | N107: =+G107+H107+I107+J107 -> #N/A | P107: =IF(L107>0,(L107-N107)/L107,0) -> #N/A | Q107: =CONCATENATE(A107," ",B107," ",C107) -> Camisa Boxy fit L Negro | R107: #NAME? | T107: =SUMIF($Q$48:$Q$181,R107,$E$48:$E$181) -> 0 | V107: =E107*G107 -> #N/A | Y107: =N107 -> #N/A | Z107: =L107 -> #N/A | AB107: =P107 -> #N/A | AC107: =ROUNDUP(L107*0.85,-3) -> #N/A | AD107: =AC107*3 -> #N/A | AE107: =IF(AC107>0,(AC107-N107)/AC107,0) -> #N/A | AF107: =ROUNDUP(L107*0.825,-3) -> #N/A | AG107: =AF107*6 -> #N/A | AH107: =IF(AF107>0,(AF107-N107)/AF107,0) -> #N/A | AI107: =ROUNDUP(L107*0.75,-3) -> #N/A | AJ107: =AI107*12 -> #N/A | AK107: =IF(AI107>0,(AI107-N107)/AI107,0) -> #N/A
... A113: Camisa Boxy fit | B113: L | C113: Plomo Plata | D113: Pecho | E113: 2 | F113: YOUR BRAND | G113: =IF(A113="","",VLOOKUP(A113,Cotizador!$A$5:$J$43,3,FALSE)) -> #N/A | H113: =IF(OR(A113="",D113=""),"",IF(D113="Sin estampar",0,IF(D113="Pecho",VLOOKUP(A113,Cotizador!$A$5:$J$43,4,FALSE),IF(D113="Espalda",VLOOKUP(A113,Cotizador!$A$5:$J$43,5,FALSE),VLOOKUP(A113,Cotizador!$A$5:$J$43,4,FALSE)+VLOOKUP(A113,Cotizador!$A$5:$J$43,5,FALSE))))) -> #N/A | I113: =IF(A113="","",VLOOKUP(A113,Cotizador!$A$5:$J$43,6,FALSE)) -> #N/A | J113: =IF(A113="","",VLOOKUP(A113,Cotizador!$A$5:$J$43,7,FALSE)) -> #N/A | K113: =IF(OR(A113="",E113=""),"",(G113+H113+I113+J113)*E113) -> #N/A | L113: =IF(A113="","",IF(D113="Sin estampar",VLOOKUP(A113,Cotizador!$A$5:$J$43,8,FALSE),IF(D113="Pecho",VLOOKUP(A113,Cotizador!$A$5:$J$43,10,FALSE),VLOOKUP(A113,Cotizador!$A$5:$J$43,9,FALSE)))) -> #N/A | M113: =IF(OR(A113="",E113=""),"",L113*E113) -> #N/A | N113: =+G113+H113+I113+J113 -> #N/A | P113: =IF(L113>0,(L113-N113)/L113,0) -> #N/A | Q113: =CONCATENATE(A113," ",B113," ",C113) -> Camisa Boxy fit L Plomo Plata | R113: #NAME? | T113: =SUMIF($Q$48:$Q$181,R113,$E$48:$E$181) -> 0 | V113: =E113*G113 -> #N/A | Y113: =N113 -> #N/A | Z113: =L113 -> #N/A | AB113: =P113 -> #N/A | AC113: =ROUNDUP(L113*0.85,-3) -> #N/A | AD113: =AC113*3 -> #N/A | AE113: =IF(AC113>0,(AC113-N113)/AC113,0) -> #N/A | AF113: =ROUNDUP(L113*0.825,-3) -> #N/A | AG113: =AF113*6 -> #N/A | AH113: =IF(AF113>0,(AF113-N113)/AF113,0) -> #N/A | AI113: =ROUNDUP(L113*0.75,-3) -> #N/A | AJ113: =AI113*12 -> #N/A | AK113: =IF(AI113>0,(AI113-N113)/AI113,0) -> #N/A
A114: Hoodie | B114: L | C114: Acid Wash Gris | D114: Sin estampar | E114: 6 | F114: YOUR BRAND | G114: =IF(A114="","",VLOOKUP(A114,Cotizador!$A$5:$J$43,3,FALSE)) -> #N/A | H114: =IF(OR(A114="",D114=""),"",IF(D114="Sin estampar",0,IF(D114="Pecho",VLOOKUP(A114,Cotizador!$A$5:$J$43,4,FALSE),IF(D114="Espalda",VLOOKUP(A114,Cotizador!$A$5:$J$43,5,FALSE),VLOOKUP(A114,Cotizador!$A$5:$J$43,4,FALSE)+VLOOKUP(A114,Cotizador!$A$5:$J$43,5,FALSE))))) -> 0 | I114: =IF(A114="","",VLOOKUP(A114,Cotizador!$A$5:$J$43,6,FALSE)) -> #N/A | J114: =IF(A114="","",VLOOKUP(A114,Cotizador!$A$5:$J$43,7,FALSE)) -> #N/A | K114: =IF(OR(A114="",E114=""),"",(G114+H114+I114+J114)*E114) -> #N/A | L114: =IF(A114="","",IF(D114="Sin estampar",VLOOKUP(A114,Cotizador!$A$5:$J$43,8,FALSE),IF(D114="Pecho",VLOOKUP(A114,Cotizador!$A$5:$J$43,10,FALSE),VLOOKUP(A114,Cotizador!$A$5:$J$43,9,FALSE)))) -> #N/A | M114: =IF(OR(A114="",E114=""),"",L114*E114) -> #N/A | N114: =+G114+H114+I114+J114 -> #N/A | P114: =IF(L114>0,(L114-N114)/L114,0) -> #N/A | Q114: =CONCATENATE(A114," ",B114," ",C114) -> Hoodie L Acid Wash Gris | R114: #NAME? | T114: =SUMIF($Q$48:$Q$181,R114,$E$48:$E$181) -> 0 | V114: =E114*G114 -> #N/A | Y114: =N114 -> #N/A | Z114: =L114 -> #N/A | AB114: =P114 -> #N/A | AC114: =ROUNDUP(L114*0.85,-3) -> #N/A | AD114: =AC114*3 -> #N/A | AE114: =IF(AC114>0,(AC114-N114)/AC114,0) -> #N/A | AF114: =ROUNDUP(L114*0.825,-3) -> #N/A | AG114: =AF114*6 -> #N/A | AH114: =IF(AF114>0,(AF114-N114)/AF114,0) -> #N/A | AI114: =ROUNDUP(L114*0.85,-3) -> #N/A | AJ114: =AI114*12 -> #N/A | AK114: =IF(AI114>0,(AI114-N114)/AI114,0) -> #N/A
A115: Hoodie | B115: L | C115: Acid Wash Gris | D115: Pecho | E115: 6 | F115: YOUR BRAND | G115: =IF(A115="","",VLOOKUP(A115,Cotizador!$A$5:$J$43,3,FALSE)) -> #N/A | H115: =IF(OR(A115="",D115=""),"",IF(D115="Sin estampar",0,IF(D115="Pecho",VLOOKUP(A115,Cotizador!$A$5:$J$43,4,FALSE),IF(D115="Espalda",VLOOKUP(A115,Cotizador!$A$5:$J$43,5,FALSE),VLOOKUP(A115,Cotizador!$A$5:$J$43,4,FALSE)+VLOOKUP(A115,Cotizador!$A$5:$J$43,5,FALSE))))) -> #N/A | I115: =IF(A115="","",VLOOKUP(A115,Cotizador!$A$5:$J$43,6,FALSE)) -> #N/A | J115: =IF(A115="","",VLOOKUP(A115,Cotizador!$A$5:$J$43,7,FALSE)) -> #N/A | K115: =IF(OR(A115="",E115=""),"",(G115+H115+I115+J115)*E115) -> #N/A | L115: =IF(A115="","",IF(D115="Sin estampar",VLOOKUP(A115,Cotizador!$A$5:$J$43,8,FALSE),IF(D115="Pecho",VLOOKUP(A115,Cotizador!$A$5:$J$43,10,FALSE),VLOOKUP(A115,Cotizador!$A$5:$J$43,9,FALSE)))) -> #N/A | M115: =IF(OR(A115="",E115=""),"",L115*E115) -> #N/A | N115: =+G115+H115+I115+J115 -> #N/A | P115: =IF(L115>0,(L115-N115)/L115,0) -> #N/A | Q115: =CONCATENATE(A115," ",B115," ",C115) -> Hoodie L Acid Wash Gris | R115: #NAME? | T115: =SUMIF($Q$48:$Q$181,R115,$E$48:$E$181) -> 0 | V115: =E115*G115 -> #N/A | Y115: =N115 -> #N/A | Z115: =L115 -> #N/A | AB115: =P115 -> #N/A | AC115: =ROUNDUP(L115*0.85,-3) -> #N/A | AD115: =AC115*3 -> #N/A | AE115: =IF(AC115>0,(AC115-N115)/AC115,0) -> #N/A | AF115: =ROUNDUP(L115*0.825,-3) -> #N/A | AG115: =AF115*6 -> #N/A | AH115: =IF(AF115>0,(AF115-N115)/AF115,0) -> #N/A | AI115: =ROUNDUP(L115*0.85,-3) -> #N/A | AJ115: =AI115*12 -> #N/A | AK115: =IF(AI115>0,(AI115-N115)/AI115,0) -> #N/A
A116: Chompa Capucha | B116: S | C116: Negro | D116: Sin estampar | E116: 1 | F116: =IF(A116="","",VLOOKUP(A116,Cotizador!$A$5:$J$43,2,FALSE)) -> #N/A | G116: =IF(A116="","",VLOOKUP(A116,Cotizador!$A$5:$J$43,3,FALSE)) -> #N/A | H116: =IF(OR(A116="",D116=""),"",IF(D116="Sin estampar",0,IF(D116="Pecho",VLOOKUP(A116,Cotizador!$A$5:$J$43,4,FALSE),IF(D116="Espalda",VLOOKUP(A116,Cotizador!$A$5:$J$43,5,FALSE),VLOOKUP(A116,Cotizador!$A$5:$J$43,4,FALSE)+VLOOKUP(A116,Cotizador!$A$5:$J$43,5,FALSE))))) -> 0 | I116: =IF(A116="","",VLOOKUP(A116,Cotizador!$A$5:$J$43,6,FALSE)) -> #N/A | J116: =IF(A116="","",VLOOKUP(A116,Cotizador!$A$5:$J$43,7,FALSE)) -> #N/A | K116: =IF(OR(A116="",E116=""),"",(G116+H116+I116+J116)*E116) -> #N/A | L116: =IF(A116="","",IF(D116="Sin estampar",VLOOKUP(A116,Cotizador!$A$5:$J$43,8,FALSE),IF(D116="Pecho",VLOOKUP(A116,Cotizador!$A$5:$J$43,10,FALSE),VLOOKUP(A116,Cotizador!$A$5:$J$43,9,FALSE)))) -> #N/A | M116: =IF(OR(A116="",E116=""),"",L116*E116) -> #N/A | N116: =+G116+H116+I116+J116 -> #N/A | P116: =IF(L116>0,(L116-N116)/L116,0) -> #N/A | Q116: =CONCATENATE(A116," ",B116," ",C116) -> Chompa Capucha S Negro | R116: #NAME? | T116: =SUMIF($Q$48:$Q$181,R116,$E$48:$E$181) -> 0 | V116: =E116*G116 -> #N/A | Y116: =N116 -> #N/A | Z116: =L116 -> #N/A | AB116: =P116 -> #N/A | AC116: =ROUNDUP(L116*0.85,-3) -> #N/A | AD116: =AC116*3 -> #N/A | AE116: =IF(AC116>0,(AC116-N116)/AC116,0) -> #N/A | AF116: =ROUNDUP(L116*0.825,-3) -> #N/A | AG116: =AF116*6 -> #N/A | AH116: =IF(AF116>0,(AF116-N116)/AF116,0) -> #N/A | AI116: =ROUNDUP(L116*0.75,-3) -> #N/A | AJ116: =AI116*12 -> #N/A | AK116: =IF(AI116>0,(AI116-N116)/AI116,0) -> #N/A
A117: Chompa Capucha | B117: M | C117: Negro | D117: Sin estampar | E117: 6 | F117: =IF(A117="","",VLOOKUP(A117,Cotizador!$A$5:$J$43,2,FALSE)) -> #N/A | G117: =IF(A117="","",VLOOKUP(A117,Cotizador!$A$5:$J$43,3,FALSE)) -> #N/A | H117: =IF(OR(A117="",D117=""),"",IF(D117="Sin estampar",0,IF(D117="Pecho",VLOOKUP(A117,Cotizador!$A$5:$J$43,4,FALSE),IF(D117="Espalda",VLOOKUP(A117,Cotizador!$A$5:$J$43,5,FALSE),VLOOKUP(A117,Cotizador!$A$5:$J$43,4,FALSE)+VLOOKUP(A117,Cotizador!$A$5:$J$43,5,FALSE))))) -> 0 | I117: =IF(A117="","",VLOOKUP(A117,Cotizador!$A$5:$J$43,6,FALSE)) -> #N/A | J117: =IF(A117="","",VLOOKUP(A117,Cotizador!$A$5:$J$43,7,FALSE)) -> #N/A | K117: =IF(OR(A117="",E117=""),"",(G117+H117+I117+J117)*E117) -> #N/A | L117: =IF(A117="","",IF(D117="Sin estampar",VLOOKUP(A117,Cotizador!$A$5:$J$43,8,FALSE),IF(D117="Pecho",VLOOKUP(A117,Cotizador!$A$5:$J$43,10,FALSE),VLOOKUP(A117,Cotizador!$A$5:$J$43,9,FALSE)))) -> #N/A | M117: =IF(OR(A117="",E117=""),"",L117*E117) -> #N/A | N117: =+G117+H117+I117+J117 -> #N/A | P117: =IF(L117>0,(L117-N117)/L117,0) -> #N/A | Q117: =CONCATENATE(A117," ",B117," ",C117) -> Chompa Capucha M Negro | R117: #NAME? | T117: =SUMIF($Q$48:$Q$181,R117,$E$48:$E$181) -> 0 | V117: =E117*G117 -> #N/A | Y117: =N117 -> #N/A | Z117: =L117 -> #N/A | AB117: =P117 -> #N/A | AC117: =ROUNDUP(L117*0.85,-3) -> #N/A | AD117: =AC117*3 -> #N/A | AE117: =IF(AC117>0,(AC117-N117)/AC117,0) -> #N/A | AF117: =ROUNDUP(L117*0.825,-3) -> #N/A | AG117: =AF117*6 -> #N/A | AH117: =IF(AF117>0,(AF117-N117)/AF117,0) -> #N/A | AI117: =ROUNDUP(L117*0.75,-3) -> #N/A | AJ117: =AI117*12 -> #N/A | AK117: =IF(AI117>0,(AI117-N117)/AI117,0) -> #N/A
A118: Chompa Capucha | B118: L | C118: Negro | D118: Sin estampar | E118: 6 | F118: =IF(A118="","",VLOOKUP(A118,Cotizador!$A$5:$J$43,2,FALSE)) -> #N/A | G118: =IF(A118="","",VLOOKUP(A118,Cotizador!$A$5:$J$43,3,FALSE)) -> #N/A | H118: =IF(OR(A118="",D118=""),"",IF(D118="Sin estampar",0,IF(D118="Pecho",VLOOKUP(A118,Cotizador!$A$5:$J$43,4,FALSE),IF(D118="Espalda",VLOOKUP(A118,Cotizador!$A$5:$J$43,5,FALSE),VLOOKUP(A118,Cotizador!$A$5:$J$43,4,FALSE)+VLOOKUP(A118,Cotizador!$A$5:$J$43,5,FALSE))))) -> 0 | I118: =IF(A118="","",VLOOKUP(A118,Cotizador!$A$5:$J$43,6,FALSE)) -> #N/A | J118: =IF(A118="","",VLOOKUP(A118,Cotizador!$A$5:$J$43,7,FALSE)) -> #N/A | K118: =IF(OR(A118="",E118=""),"",(G118+H118+I118+J118)*E118) -> #N/A | L118: =IF(A118="","",IF(D118="Sin estampar",VLOOKUP(A118,Cotizador!$A$5:$J$43,8,FALSE),IF(D118="Pecho",VLOOKUP(A118,Cotizador!$A$5:$J$43,10,FALSE),VLOOKUP(A118,Cotizador!$A$5:$J$43,9,FALSE)))) -> #N/A | M118: =IF(OR(A118="",E118=""),"",L118*E118) -> #N/A | N118: =+G118+H118+I118+J118 -> #N/A | P118: =IF(L118>0,(L118-N118)/L118,0) -> #N/A | Q118: =CONCATENATE(A118," ",B118," ",C118) -> Chompa Capucha L Negro | R118: #NAME? | T118: =SUMIF($Q$48:$Q$181,R118,$E$48:$E$181) -> 0 | V118: =E118*G118 -> #N/A | Y118: =N118 -> #N/A | Z118: =L118 -> #N/A | AB118: =P118 -> #N/A | AC118: =ROUNDUP(L118*0.85,-3) -> #N/A | AD118: =AC118*3 -> #N/A | AE118: =IF(AC118>0,(AC118-N118)/AC118,0) -> #N/A | AF118: =ROUNDUP(L118*0.825,-3) -> #N/A | AG118: =AF118*6 -> #N/A | AH118: =IF(AF118>0,(AF118-N118)/AF118,0) -> #N/A | AI118: =ROUNDUP(L118*0.75,-3) -> #N/A | AJ118: =AI118*12 -> #N/A | AK118: =IF(AI118>0,(AI118-N118)/AI118,0) -> #N/A
A119: Chompa Capucha | B119: S | C119: Perla | D119: Sin estampar | E119: 1 | F119: =IF(A119="","",VLOOKUP(A119,Cotizador!$A$5:$J$43,2,FALSE)) -> #N/A | G119: =IF(A119="","",VLOOKUP(A119,Cotizador!$A$5:$J$43,3,FALSE)) -> #N/A | H119: =IF(OR(A119="",D119=""),"",IF(D119="Sin estampar",0,IF(D119="Pecho",VLOOKUP(A119,Cotizador!$A$5:$J$43,4,FALSE),IF(D119="Espalda",VLOOKUP(A119,Cotizador!$A$5:$J$43,5,FALSE),VLOOKUP(A119,Cotizador!$A$5:$J$43,4,FALSE)+VLOOKUP(A119,Cotizador!$A$5:$J$43,5,FALSE))))) -> 0 | I119: =IF(A119="","",VLOOKUP(A119,Cotizador!$A$5:$J$43,6,FALSE)) -> #N/A | J119: =IF(A119="","",VLOOKUP(A119,Cotizador!$A$5:$J$43,7,FALSE)) -> #N/A | K119: =IF(OR(A119="",E119=""),"",(G119+H119+I119+J119)*E119) -> #N/A | L119: =IF(A119="","",IF(D119="Sin estampar",VLOOKUP(A119,Cotizador!$A$5:$J$43,8,FALSE),IF(D119="Pecho",VLOOKUP(A119,Cotizador!$A$5:$J$43,10,FALSE),VLOOKUP(A119,Cotizador!$A$5:$J$43,9,FALSE)))) -> #N/A | M119: =IF(OR(A119="",E119=""),"",L119*E119) -> #N/A | N119: =+G119+H119+I119+J119 -> #N/A | P119: =IF(L119>0,(L119-N119)/L119,0) -> #N/A | Q119: =CONCATENATE(A119," ",B119," ",C119) -> Chompa Capucha S Perla | R119: #NAME? | T119: =SUMIF($Q$48:$Q$181,R119,$E$48:$E$181) -> 0 | V119: =E119*G119 -> #N/A | Y119: =N119 -> #N/A | Z119: =L119 -> #N/A | AB119: =P119 -> #N/A | AC119: =ROUNDUP(L119*0.85,-3) -> #N/A | AD119: =AC119*3 -> #N/A | AE119: =IF(AC119>0,(AC119-N119)/AC119,0) -> #N/A | AF119: =ROUNDUP(L119*0.825,-3) -> #N/A | AG119: =AF119*6 -> #N/A | AH119: =IF(AF119>0,(AF119-N119)/AF119,0) -> #N/A | AI119: =ROUNDUP(L119*0.75,-3) -> #N/A | AJ119: =AI119*12 -> #N/A | AK119: =IF(AI119>0,(AI119-N119)/AI119,0) -> #N/A
A120: Chompa Capucha | B120: M | C120: Perla | D120: Sin estampar | E120: 2 | F120: =IF(A120="","",VLOOKUP(A120,Cotizador!$A$5:$J$43,2,FALSE)) -> #N/A | G120: =IF(A120="","",VLOOKUP(A120,Cotizador!$A$5:$J$43,3,FALSE)) -> #N/A | H120: =IF(OR(A120="",D120=""),"",IF(D120="Sin estampar",0,IF(D120="Pecho",VLOOKUP(A120,Cotizador!$A$5:$J$43,4,FALSE),IF(D120="Espalda",VLOOKUP(A120,Cotizador!$A$5:$J$43,5,FALSE),VLOOKUP(A120,Cotizador!$A$5:$J$43,4,FALSE)+VLOOKUP(A120,Cotizador!$A$5:$J$43,5,FALSE))))) -> 0 | I120: =IF(A120="","",VLOOKUP(A120,Cotizador!$A$5:$J$43,6,FALSE)) -> #N/A | J120: =IF(A120="","",VLOOKUP(A120,Cotizador!$A$5:$J$43,7,FALSE)) -> #N/A | K120: =IF(OR(A120="",E120=""),"",(G120+H120+I120+J120)*E120) -> #N/A | L120: =IF(A120="","",IF(D120="Sin estampar",VLOOKUP(A120,Cotizador!$A$5:$J$43,8,FALSE),IF(D120="Pecho",VLOOKUP(A120,Cotizador!$A$5:$J$43,10,FALSE),VLOOKUP(A120,Cotizador!$A$5:$J$43,9,FALSE)))) -> #N/A | M120: =IF(OR(A120="",E120=""),"",L120*E120) -> #N/A | N120: =+G120+H120+I120+J120 -> #N/A | P120: =IF(L120>0,(L120-N120)/L120,0) -> #N/A | Q120: =CONCATENATE(A120," ",B120," ",C120) -> Chompa Capucha M Perla | R120: #NAME? | T120: =SUMIF($Q$48:$Q$181,R120,$E$48:$E$181) -> 0 | V120: =E120*G120 -> #N/A | Y120: =N120 -> #N/A | Z120: =L120 -> #N/A | AB120: =P120 -> #N/A | AC120: =ROUNDUP(L120*0.85,-3) -> #N/A | AD120: =AC120*3 -> #N/A | AE120: =IF(AC120>0,(AC120-N120)/AC120,0) -> #N/A | AF120: =ROUNDUP(L120*0.825,-3) -> #N/A | AG120: =AF120*6 -> #N/A | AH120: =IF(AF120>0,(AF120-N120)/AF120,0) -> #N/A | AI120: =ROUNDUP(L120*0.75,-3) -> #N/A | AJ120: =AI120*12 -> #N/A | AK120: =IF(AI120>0,(AI120-N120)/AI120,0) -> #N/A
A121: Chompa Capucha | B121: L | C121: Perla | D121: Sin estampar | E121: 2 | F121: =IF(A121="","",VLOOKUP(A121,Cotizador!$A$5:$J$43,2,FALSE)) -> #N/A | G121: =IF(A121="","",VLOOKUP(A121,Cotizador!$A$5:$J$43,3,FALSE)) -> #N/A | H121: =IF(OR(A121="",D121=""),"",IF(D121="Sin estampar",0,IF(D121="Pecho",VLOOKUP(A121,Cotizador!$A$5:$J$43,4,FALSE),IF(D121="Espalda",VLOOKUP(A121,Cotizador!$A$5:$J$43,5,FALSE),VLOOKUP(A121,Cotizador!$A$5:$J$43,4,FALSE)+VLOOKUP(A121,Cotizador!$A$5:$J$43,5,FALSE))))) -> 0 | I121: =IF(A121="","",VLOOKUP(A121,Cotizador!$A$5:$J$43,6,FALSE)) -> #N/A | J121: =IF(A121="","",VLOOKUP(A121,Cotizador!$A$5:$J$43,7,FALSE)) -> #N/A | K121: =IF(OR(A121="",E121=""),"",(G121+H121+I121+J121)*E121) -> #N/A | L121: =IF(A121="","",IF(D121="Sin estampar",VLOOKUP(A121,Cotizador!$A$5:$J$43,8,FALSE),IF(D121="Pecho",VLOOKUP(A121,Cotizador!$A$5:$J$43,10,FALSE),VLOOKUP(A121,Cotizador!$A$5:$J$43,9,FALSE)))) -> #N/A | M121: =IF(OR(A121="",E121=""),"",L121*E121) -> #N/A | N121: =+G121+H121+I121+J121 -> #N/A | P121: =IF(L121>0,(L121-N121)/L121,0) -> #N/A | Q121: =CONCATENATE(A121," ",B121," ",C121) -> Chompa Capucha L Perla | R121: #NAME? | T121: =SUMIF($Q$48:$Q$181,R121,$E$48:$E$181) -> 0 | V121: =E121*G121 -> #N/A | Y121: =N121 -> #N/A | Z121: =L121 -> #N/A | AB121: =P121 -> #N/A | AC121: =ROUNDUP(L121*0.85,-3) -> #N/A | AD121: =AC121*3 -> #N/A | AE121: =IF(AC121>0,(AC121-N121)/AC121,0) -> #N/A | AF121: =ROUNDUP(L121*0.825,-3) -> #N/A | AG121: =AF121*6 -> #N/A | AH121: =IF(AF121>0,(AF121-N121)/AF121,0) -> #N/A | AI121: =ROUNDUP(L121*0.75,-3) -> #N/A | AJ121: =AI121*12 -> #N/A | AK121: =IF(AI121>0,(AI121-N121)/AI121,0) -> #N/A
A122: Chompa Capucha | B122: S | C122: Verde Botella | D122: Sin estampar | E122: 1 | F122: =IF(A122="","",VLOOKUP(A122,Cotizador!$A$5:$J$43,2,FALSE)) -> #N/A | G122: =IF(A122="","",VLOOKUP(A122,Cotizador!$A$5:$J$43,3,FALSE)) -> #N/A | H122: =IF(OR(A122="",D122=""),"",IF(D122="Sin estampar",0,IF(D122="Pecho",VLOOKUP(A122,Cotizador!$A$5:$J$43,4,FALSE),IF(D122="Espalda",VLOOKUP(A122,Cotizador!$A$5:$J$43,5,FALSE),VLOOKUP(A122,Cotizador!$A$5:$J$43,4,FALSE)+VLOOKUP(A122,Cotizador!$A$5:$J$43,5,FALSE))))) -> 0 | I122: =IF(A122="","",VLOOKUP(A122,Cotizador!$A$5:$J$43,6,FALSE)) -> #N/A | J122: =IF(A122="","",VLOOKUP(A122,Cotizador!$A$5:$J$43,7,FALSE)) -> #N/A | K122: =IF(OR(A122="",E122=""),"",(G122+H122+I122+J122)*E122) -> #N/A | L122: =IF(A122="","",IF(D122="Sin estampar",VLOOKUP(A122,Cotizador!$A$5:$J$43,8,FALSE),IF(D122="Pecho",VLOOKUP(A122,Cotizador!$A$5:$J$43,10,FALSE),VLOOKUP(A122,Cotizador!$A$5:$J$43,9,FALSE)))) -> #N/A | M122: =IF(OR(A122="",E122=""),"",L122*E122) -> #N/A | N122: =+G122+H122+I122+J122 -> #N/A | P122: =IF(L122>0,(L122-N122)/L122,0) -> #N/A | Q122: =CONCATENATE(A122," ",B122," ",C122) -> Chompa Capucha S Verde Botella | R122: #NAME? | T122: =SUMIF($Q$48:$Q$181,R122,$E$48:$E$181) -> 0 | V122: =E122*G122 -> #N/A | Y122: =N122 -> #N/A | Z122: =L122 -> #N/A | AB122: =P122 -> #N/A | AC122: =ROUNDUP(L122*0.85,-3) -> #N/A | AD122: =AC122*3 -> #N/A | AE122: =IF(AC122>0,(AC122-N122)/AC122,0) -> #N/A | AF122: =ROUNDUP(L122*0.825,-3) -> #N/A | AG122: =AF122*6 -> #N/A | AH122: =IF(AF122>0,(AF122-N122)/AF122,0) -> #N/A | AI122: =ROUNDUP(L122*0.75,-3) -> #N/A | AJ122: =AI122*12 -> #N/A | AK122: =IF(AI122>0,(AI122-N122)/AI122,0) -> #N/A
A123: Chompa Capucha | B123: M | C123: Verde Botella | D123: Sin estampar | E123: 2 | F123: =IF(A123="","",VLOOKUP(A123,Cotizador!$A$5:$J$43,2,FALSE)) -> #N/A | G123: =IF(A123="","",VLOOKUP(A123,Cotizador!$A$5:$J$43,3,FALSE)) -> #N/A | H123: =IF(OR(A123="",D123=""),"",IF(D123="Sin estampar",0,IF(D123="Pecho",VLOOKUP(A123,Cotizador!$A$5:$J$43,4,FALSE),IF(D123="Espalda",VLOOKUP(A123,Cotizador!$A$5:$J$43,5,FALSE),VLOOKUP(A123,Cotizador!$A$5:$J$43,4,FALSE)+VLOOKUP(A123,Cotizador!$A$5:$J$43,5,FALSE))))) -> 0 | I123: =IF(A123="","",VLOOKUP(A123,Cotizador!$A$5:$J$43,6,FALSE)) -> #N/A | J123: =IF(A123="","",VLOOKUP(A123,Cotizador!$A$5:$J$43,7,FALSE)) -> #N/A | K123: =IF(OR(A123="",E123=""),"",(G123+H123+I123+J123)*E123) -> #N/A | L123: =IF(A123="","",IF(D123="Sin estampar",VLOOKUP(A123,Cotizador!$A$5:$J$43,8,FALSE),IF(D123="Pecho",VLOOKUP(A123,Cotizador!$A$5:$J$43,10,FALSE),VLOOKUP(A123,Cotizador!$A$5:$J$43,9,FALSE)))) -> #N/A | M123: =IF(OR(A123="",E123=""),"",L123*E123) -> #N/A | N123: =+G123+H123+I123+J123 -> #N/A | P123: =IF(L123>0,(L123-N123)/L123,0) -> #N/A | Q123: =CONCATENATE(A123," ",B123," ",C123) -> Chompa Capucha M Verde Botella | R123: #NAME? | T123: =SUMIF($Q$48:$Q$181,R123,$E$48:$E$181) -> 0 | V123: =E123*G123 -> #N/A | Y123: =N123 -> #N/A | Z123: =L123 -> #N/A | AB123: =P123 -> #N/A | AC123: =ROUNDUP(L123*0.85,-3) -> #N/A | AD123: =AC123*3 -> #N/A | AE123: =IF(AC123>0,(AC123-N123)/AC123,0) -> #N/A | AF123: =ROUNDUP(L123*0.825,-3) -> #N/A | AG123: =AF123*6 -> #N/A | AH123: =IF(AF123>0,(AF123-N123)/AF123,0) -> #N/A | AI123: =ROUNDUP(L123*0.75,-3) -> #N/A | AJ123: =AI123*12 -> #N/A | AK123: =IF(AI123>0,(AI123-N123)/AI123,0) -> #N/A
A124: Chompa Capucha | B124: L | C124: Verde Botella | D124: Sin estampar | E124: 2 | F124: =IF(A124="","",VLOOKUP(A124,Cotizador!$A$5:$J$43,2,FALSE)) -> #N/A | G124: =IF(A124="","",VLOOKUP(A124,Cotizador!$A$5:$J$43,3,FALSE)) -> #N/A | H124: =IF(OR(A124="",D124=""),"",IF(D124="Sin estampar",0,IF(D124="Pecho",VLOOKUP(A124,Cotizador!$A$5:$J$43,4,FALSE),IF(D124="Espalda",VLOOKUP(A124,Cotizador!$A$5:$J$43,5,FALSE),VLOOKUP(A124,Cotizador!$A$5:$J$43,4,FALSE)+VLOOKUP(A124,Cotizador!$A$5:$J$43,5,FALSE))))) -> 0 | I124: =IF(A124="","",VLOOKUP(A124,Cotizador!$A$5:$J$43,6,FALSE)) -> #N/A | J124: =IF(A124="","",VLOOKUP(A124,Cotizador!$A$5:$J$43,7,FALSE)) -> #N/A | K124: =IF(OR(A124="",E124=""),"",(G124+H124+I124+J124)*E124) -> #N/A | L124: =IF(A124="","",IF(D124="Sin estampar",VLOOKUP(A124,Cotizador!$A$5:$J$43,8,FALSE),IF(D124="Pecho",VLOOKUP(A124,Cotizador!$A$5:$J$43,10,FALSE),VLOOKUP(A124,Cotizador!$A$5:$J$43,9,FALSE)))) -> #N/A | M124: =IF(OR(A124="",E124=""),"",L124*E124) -> #N/A | N124: =+G124+H124+I124+J124 -> #N/A | P124: =IF(L124>0,(L124-N124)/L124,0) -> #N/A | Q124: =CONCATENATE(A124," ",B124," ",C124) -> Chompa Capucha L Verde Botella | R124: #NAME? | T124: =SUMIF($Q$48:$Q$181,R124,$E$48:$E$181) -> 0 | V124: =E124*G124 -> #N/A | Y124: =N124 -> #N/A | Z124: =L124 -> #N/A | AB124: =P124 -> #N/A | AC124: =ROUNDUP(L124*0.85,-3) -> #N/A | AD124: =AC124*3 -> #N/A | AE124: =IF(AC124>0,(AC124-N124)/AC124,0) -> #N/A | AF124: =ROUNDUP(L124*0.825,-3) -> #N/A | AG124: =AF124*6 -> #N/A | AH124: =IF(AF124>0,(AF124-N124)/AF124,0) -> #N/A | AI124: =ROUNDUP(L124*0.75,-3) -> #N/A | AJ124: =AI124*12 -> #N/A | AK124: =IF(AI124>0,(AI124-N124)/AI124,0) -> #N/A
A125: Chompa Capucha | B125: S | C125: Plomo Plata | D125: Sin estampar | E125: 1 | F125: =IF(A125="","",VLOOKUP(A125,Cotizador!$A$5:$J$43,2,FALSE)) -> #N/A | G125: =IF(A125="","",VLOOKUP(A125,Cotizador!$A$5:$J$43,3,FALSE)) -> #N/A | H125: =IF(OR(A125="",D125=""),"",IF(D125="Sin estampar",0,IF(D125="Pecho",VLOOKUP(A125,Cotizador!$A$5:$J$43,4,FALSE),IF(D125="Espalda",VLOOKUP(A125,Cotizador!$A$5:$J$43,5,FALSE),VLOOKUP(A125,Cotizador!$A$5:$J$43,4,FALSE)+VLOOKUP(A125,Cotizador!$A$5:$J$43,5,FALSE))))) -> 0 | I125: =IF(A125="","",VLOOKUP(A125,Cotizador!$A$5:$J$43,6,FALSE)) -> #N/A | J125: =IF(A125="","",VLOOKUP(A125,Cotizador!$A$5:$J$43,7,FALSE)) -> #N/A | K125: =IF(OR(A125="",E125=""),"",(G125+H125+I125+J125)*E125) -> #N/A | L125: =IF(A125="","",IF(D125="Sin estampar",VLOOKUP(A125,Cotizador!$A$5:$J$43,8,FALSE),IF(D125="Pecho",VLOOKUP(A125,Cotizador!$A$5:$J$43,10,FALSE),VLOOKUP(A125,Cotizador!$A$5:$J$43,9,FALSE)))) -> #N/A | M125: =IF(OR(A125="",E125=""),"",L125*E125) -> #N/A | N125: =+G125+H125+I125+J125 -> #N/A | P125: =IF(L125>0,(L125-N125)/L125,0) -> #N/A | Q125: =CONCATENATE(A125," ",B125," ",C125) -> Chompa Capucha S Plomo Plata | R125: #NAME? | T125: =SUMIF($Q$48:$Q$181,R125,$E$48:$E$181) -> 0 | V125: =E125*G125 -> #N/A | Y125: =N125 -> #N/A | Z125: =L125 -> #N/A | AB125: =P125 -> #N/A | AC125: =ROUNDUP(L125*0.85,-3) -> #N/A | AD125: =AC125*3 -> #N/A | AE125: =IF(AC125>0,(AC125-N125)/AC125,0) -> #N/A | AF125: =ROUNDUP(L125*0.825,-3) -> #N/A | AG125: =AF125*6 -> #N/A | AH125: =IF(AF125>0,(AF125-N125)/AF125,0) -> #N/A | AI125: =ROUNDUP(L125*0.75,-3) -> #N/A | AJ125: =AI125*12 -> #N/A | AK125: =IF(AI125>0,(AI125-N125)/AI125,0) -> #N/A
A126: Chompa Capucha | B126: M | C126: Plomo Plata | D126: Sin estampar | E126: 2 | F126: =IF(A126="","",VLOOKUP(A126,Cotizador!$A$5:$J$43,2,FALSE)) -> #N/A | G126: =IF(A126="","",VLOOKUP(A126,Cotizador!$A$5:$J$43,3,FALSE)) -> #N/A | H126: =IF(OR(A126="",D126=""),"",IF(D126="Sin estampar",0,IF(D126="Pecho",VLOOKUP(A126,Cotizador!$A$5:$J$43,4,FALSE),IF(D126="Espalda",VLOOKUP(A126,Cotizador!$A$5:$J$43,5,FALSE),VLOOKUP(A126,Cotizador!$A$5:$J$43,4,FALSE)+VLOOKUP(A126,Cotizador!$A$5:$J$43,5,FALSE))))) -> 0 | I126: =IF(A126="","",VLOOKUP(A126,Cotizador!$A$5:$J$43,6,FALSE)) -> #N/A | J126: =IF(A126="","",VLOOKUP(A126,Cotizador!$A$5:$J$43,7,FALSE)) -> #N/A | K126: =IF(OR(A126="",E126=""),"",(G126+H126+I126+J126)*E126) -> #N/A | L126: =IF(A126="","",IF(D126="Sin estampar",VLOOKUP(A126,Cotizador!$A$5:$J$43,8,FALSE),IF(D126="Pecho",VLOOKUP(A126,Cotizador!$A$5:$J$43,10,FALSE),VLOOKUP(A126,Cotizador!$A$5:$J$43,9,FALSE)))) -> #N/A | M126: =IF(OR(A126="",E126=""),"",L126*E126) -> #N/A | N126: =+G126+H126+I126+J126 -> #N/A | P126: =IF(L126>0,(L126-N126)/L126,0) -> #N/A | Q126: =CONCATENATE(A126," ",B126," ",C126) -> Chompa Capucha M Plomo Plata | R126: #NAME? | T126: =SUMIF($Q$48:$Q$181,R126,$E$48:$E$181) -> 0 | V126: =E126*G126 -> #N/A | Y126: =N126 -> #N/A | Z126: =L126 -> #N/A | AB126: =P126 -> #N/A | AC126: =ROUNDUP(L126*0.85,-3) -> #N/A | AD126: =AC126*3 -> #N/A | AE126: =IF(AC126>0,(AC126-N126)/AC126,0) -> #N/A | AF126: =ROUNDUP(L126*0.825,-3) -> #N/A | AG126: =AF126*6 -> #N/A | AH126: =IF(AF126>0,(AF126-N126)/AF126,0) -> #N/A | AI126: =ROUNDUP(L126*0.75,-3) -> #N/A | AJ126: =AI126*12 -> #N/A | AK126: =IF(AI126>0,(AI126-N126)/AI126,0) -> #N/A
A127: Chompa Capucha | B127: L | C127: Plomo Plata | D127: Sin estampar | E127: 2 | F127: =IF(A127="","",VLOOKUP(A127,Cotizador!$A$5:$J$43,2,FALSE)) -> #N/A | G127: =IF(A127="","",VLOOKUP(A127,Cotizador!$A$5:$J$43,3,FALSE)) -> #N/A | H127: =IF(OR(A127="",D127=""),"",IF(D127="Sin estampar",0,IF(D127="Pecho",VLOOKUP(A127,Cotizador!$A$5:$J$43,4,FALSE),IF(D127="Espalda",VLOOKUP(A127,Cotizador!$A$5:$J$43,5,FALSE),VLOOKUP(A127,Cotizador!$A$5:$J$43,4,FALSE)+VLOOKUP(A127,Cotizador!$A$5:$J$43,5,FALSE))))) -> 0 | I127: =IF(A127="","",VLOOKUP(A127,Cotizador!$A$5:$J$43,6,FALSE)) -> #N/A | J127: =IF(A127="","",VLOOKUP(A127,Cotizador!$A$5:$J$43,7,FALSE)) -> #N/A | K127: =IF(OR(A127="",E127=""),"",(G127+H127+I127+J127)*E127) -> #N/A | L127: =IF(A127="","",IF(D127="Sin estampar",VLOOKUP(A127,Cotizador!$A$5:$J$43,8,FALSE),IF(D127="Pecho",VLOOKUP(A127,Cotizador!$A$5:$J$43,10,FALSE),VLOOKUP(A127,Cotizador!$A$5:$J$43,9,FALSE)))) -> #N/A | M127: =IF(OR(A127="",E127=""),"",L127*E127) -> #N/A | N127: =+G127+H127+I127+J127 -> #N/A | P127: =IF(L127>0,(L127-N127)/L127,0) -> #N/A | Q127: =CONCATENATE(A127," ",B127," ",C127) -> Chompa Capucha L Plomo Plata | T127: =SUMIF($Q$48:$Q$181,R127,$E$48:$E$181) -> 0 | V127: =E127*G127 -> #N/A | Y127: =N127 -> #N/A | Z127: =L127 -> #N/A | AB127: =P127 -> #N/A | AC127: =ROUNDUP(L127*0.85,-3) -> #N/A | AD127: =AC127*3 -> #N/A | AE127: =IF(AC127>0,(AC127-N127)/AC127,0) -> #N/A | AF127: =ROUNDUP(L127*0.825,-3) -> #N/A | AG127: =AF127*6 -> #N/A | AH127: =IF(AF127>0,(AF127-N127)/AF127,0) -> #N/A | AI127: =ROUNDUP(L127*0.75,-3) -> #N/A | AJ127: =AI127*12 -> #N/A | AK127: =IF(AI127>0,(AI127-N127)/AI127,0) -> #N/A
A128: Chompa Capucha | B128: S | C128: Negro | D128: Pecho | E128: 1 | F128: =IF(A128="","",VLOOKUP(A128,Cotizador!$A$5:$J$43,2,FALSE)) -> #N/A | G128: =IF(A128="","",VLOOKUP(A128,Cotizador!$A$5:$J$43,3,FALSE)) -> #N/A | H128: =IF(OR(A128="",D128=""),"",IF(D128="Sin estampar",0,IF(D128="Pecho",VLOOKUP(A128,Cotizador!$A$5:$J$43,4,FALSE),IF(D128="Espalda",VLOOKUP(A128,Cotizador!$A$5:$J$43,5,FALSE),VLOOKUP(A128,Cotizador!$A$5:$J$43,4,FALSE)+VLOOKUP(A128,Cotizador!$A$5:$J$43,5,FALSE))))) -> #N/A | I128: =IF(A128="","",VLOOKUP(A128,Cotizador!$A$5:$J$43,6,FALSE)) -> #N/A | J128: =IF(A128="","",VLOOKUP(A128,Cotizador!$A$5:$J$43,7,FALSE)) -> #N/A | K128: =IF(OR(A128="",E128=""),"",(G128+H128+I128+J128)*E128) -> #N/A | L128: =IF(A128="","",IF(D128="Sin estampar",VLOOKUP(A128,Cotizador!$A$5:$J$43,8,FALSE),IF(D128="Pecho",VLOOKUP(A128,Cotizador!$A$5:$J$43,10,FALSE),VLOOKUP(A128,Cotizador!$A$5:$J$43,9,FALSE)))) -> #N/A | M128: =IF(OR(A128="",E128=""),"",L128*E128) -> #N/A | N128: =+G128+H128+I128+J128 -> #N/A | P128: =IF(L128>0,(L128-N128)/L128,0) -> #N/A | Q128: =CONCATENATE(A128," ",B128," ",C128) -> Chompa Capucha S Negro | T128: =SUMIF($Q$48:$Q$181,R128,$E$48:$E$181) -> 0 | V128: =E128*G128 -> #N/A | Y128: =N128 -> #N/A | Z128: =L128 -> #N/A | AB128: =P128 -> #N/A | AC128: =ROUNDUP(L128*0.85,-3) -> #N/A | AD128: =AC128*3 -> #N/A | AE128: =IF(AC128>0,(AC128-N128)/AC128,0) -> #N/A | AF128: =ROUNDUP(L128*0.825,-3) -> #N/A | AG128: =AF128*6 -> #N/A | AH128: =IF(AF128>0,(AF128-N128)/AF128,0) -> #N/A | AI128: =ROUNDUP(L128*0.75,-3) -> #N/A | AJ128: =AI128*12 -> #N/A | AK128: =IF(AI128>0,(AI128-N128)/AI128,0) -> #N/A
A129: Chompa Capucha | B129: M | C129: Negro | D129: Pecho | E129: 2 | F129: =IF(A129="","",VLOOKUP(A129,Cotizador!$A$5:$J$43,2,FALSE)) -> #N/A | G129: =IF(A129="","",VLOOKUP(A129,Cotizador!$A$5:$J$43,3,FALSE)) -> #N/A | H129: =IF(OR(A129="",D129=""),"",IF(D129="Sin estampar",0,IF(D129="Pecho",VLOOKUP(A129,Cotizador!$A$5:$J$43,4,FALSE),IF(D129="Espalda",VLOOKUP(A129,Cotizador!$A$5:$J$43,5,FALSE),VLOOKUP(A129,Cotizador!$A$5:$J$43,4,FALSE)+VLOOKUP(A129,Cotizador!$A$5:$J$43,5,FALSE))))) -> #N/A | I129: =IF(A129="","",VLOOKUP(A129,Cotizador!$A$5:$J$43,6,FALSE)) -> #N/A | J129: =IF(A129="","",VLOOKUP(A129,Cotizador!$A$5:$J$43,7,FALSE)) -> #N/A | K129: =IF(OR(A129="",E129=""),"",(G129+H129+I129+J129)*E129) -> #N/A | L129: =IF(A129="","",IF(D129="Sin estampar",VLOOKUP(A129,Cotizador!$A$5:$J$43,8,FALSE),IF(D129="Pecho",VLOOKUP(A129,Cotizador!$A$5:$J$43,10,FALSE),VLOOKUP(A129,Cotizador!$A$5:$J$43,9,FALSE)))) -> #N/A | M129: =IF(OR(A129="",E129=""),"",L129*E129) -> #N/A | N129: =+G129+H129+I129+J129 -> #N/A | P129: =IF(L129>0,(L129-N129)/L129,0) -> #N/A | Q129: =CONCATENATE(A129," ",B129," ",C129) -> Chompa Capucha M Negro | T129: =SUMIF($Q$48:$Q$181,R129,$E$48:$E$181) -> 0 | V129: =E129*G129 -> #N/A | Y129: =N129 -> #N/A | Z129: =L129 -> #N/A | AB129: =P129 -> #N/A | AC129: =ROUNDUP(L129*0.85,-3) -> #N/A | AD129: =AC129*3 -> #N/A | AE129: =IF(AC129>0,(AC129-N129)/AC129,0) -> #N/A | AF129: =ROUNDUP(L129*0.825,-3) -> #N/A | AG129: =AF129*6 -> #N/A | AH129: =IF(AF129>0,(AF129-N129)/AF129,0) -> #N/A | AI129: =ROUNDUP(L129*0.75,-3) -> #N/A | AJ129: =AI129*12 -> #N/A | AK129: =IF(AI129>0,(AI129-N129)/AI129,0) -> #N/A
A130: Chompa Capucha | B130: L | C130: Negro | D130: Pecho | E130: 2 | F130: =IF(A130="","",VLOOKUP(A130,Cotizador!$A$5:$J$43,2,FALSE)) -> #N/A | G130: =IF(A130="","",VLOOKUP(A130,Cotizador!$A$5:$J$43,3,FALSE)) -> #N/A | H130: =IF(OR(A130="",D130=""),"",IF(D130="Sin estampar",0,IF(D130="Pecho",VLOOKUP(A130,Cotizador!$A$5:$J$43,4,FALSE),IF(D130="Espalda",VLOOKUP(A130,Cotizador!$A$5:$J$43,5,FALSE),VLOOKUP(A130,Cotizador!$A$5:$J$43,4,FALSE)+VLOOKUP(A130,Cotizador!$A$5:$J$43,5,FALSE))))) -> #N/A | I130: =IF(A130="","",VLOOKUP(A130,Cotizador!$A$5:$J$43,6,FALSE)) -> #N/A | J130: =IF(A130="","",VLOOKUP(A130,Cotizador!$A$5:$J$43,7,FALSE)) -> #N/A | K130: =IF(OR(A130="",E130=""),"",(G130+H130+I130+J130)*E130) -> #N/A | L130: =IF(A130="","",IF(D130="Sin estampar",VLOOKUP(A130,Cotizador!$A$5:$J$43,8,FALSE),IF(D130="Pecho",VLOOKUP(A130,Cotizador!$A$5:$J$43,10,FALSE),VLOOKUP(A130,Cotizador!$A$5:$J$43,9,FALSE)))) -> #N/A | M130: =IF(OR(A130="",E130=""),"",L130*E130) -> #N/A | N130: =+G130+H130+I130+J130 -> #N/A | P130: =IF(L130>0,(L130-N130)/L130,0) -> #N/A | Q130: =CONCATENATE(A130," ",B130," ",C130) -> Chompa Capucha L Negro | T130: =SUMIF($Q$48:$Q$181,R130,$E$48:$E$181) -> 0 | V130: =E130*G130 -> #N/A | Y130: =N130 -> #N/A | Z130: =L130 -> #N/A | AB130: =P130 -> #N/A | AC130: =ROUNDUP(L130*0.85,-3) -> #N/A | AD130: =AC130*3 -> #N/A | AE130: =IF(AC130>0,(AC130-N130)/AC130,0) -> #N/A | AF130: =ROUNDUP(L130*0.825,-3) -> #N/A | AG130: =AF130*6 -> #N/A | AH130: =IF(AF130>0,(AF130-N130)/AF130,0) -> #N/A | AI130: =ROUNDUP(L130*0.75,-3) -> #N/A | AJ130: =AI130*12 -> #N/A | AK130: =IF(AI130>0,(AI130-N130)/AI130,0) -> #N/A
A131: Chompa Capucha | B131: S | C131: Perla | D131: Pecho | E131: 1 | F131: =IF(A131="","",VLOOKUP(A131,Cotizador!$A$5:$J$43,2,FALSE)) -> #N/A | G131: =IF(A131="","",VLOOKUP(A131,Cotizador!$A$5:$J$43,3,FALSE)) -> #N/A | H131: =IF(OR(A131="",D131=""),"",IF(D131="Sin estampar",0,IF(D131="Pecho",VLOOKUP(A131,Cotizador!$A$5:$J$43,4,FALSE),IF(D131="Espalda",VLOOKUP(A131,Cotizador!$A$5:$J$43,5,FALSE),VLOOKUP(A131,Cotizador!$A$5:$J$43,4,FALSE)+VLOOKUP(A131,Cotizador!$A$5:$J$43,5,FALSE))))) -> #N/A | I131: =IF(A131="","",VLOOKUP(A131,Cotizador!$A$5:$J$43,6,FALSE)) -> #N/A | J131: =IF(A131="","",VLOOKUP(A131,Cotizador!$A$5:$J$43,7,FALSE)) -> #N/A | K131: =IF(OR(A131="",E131=""),"",(G131+H131+I131+J131)*E131) -> #N/A | L131: =IF(A131="","",IF(D131="Sin estampar",VLOOKUP(A131,Cotizador!$A$5:$J$43,8,FALSE),IF(D131="Pecho",VLOOKUP(A131,Cotizador!$A$5:$J$43,10,FALSE),VLOOKUP(A131,Cotizador!$A$5:$J$43,9,FALSE)))) -> #N/A | M131: =IF(OR(A131="",E131=""),"",L131*E131) -> #N/A | N131: =+G131+H131+I131+J131 -> #N/A | P131: =IF(L131>0,(L131-N131)/L131,0) -> #N/A | Q131: =CONCATENATE(A131," ",B131," ",C131) -> Chompa Capucha S Perla | T131: =SUMIF($Q$48:$Q$181,R131,$E$48:$E$181) -> 0 | V131: =E131*G131 -> #N/A | Y131: =N131 -> #N/A | Z131: =L131 -> #N/A | AB131: =P131 -> #N/A | AC131: =ROUNDUP(L131*0.85,-3) -> #N/A | AD131: =AC131*3 -> #N/A | AE131: =IF(AC131>0,(AC131-N131)/AC131,0) -> #N/A | AF131: =ROUNDUP(L131*0.825,-3) -> #N/A | AG131: =AF131*6 -> #N/A | AH131: =IF(AF131>0,(AF131-N131)/AF131,0) -> #N/A | AI131: =ROUNDUP(L131*0.75,-3) -> #N/A | AJ131: =AI131*12 -> #N/A | AK131: =IF(AI131>0,(AI131-N131)/AI131,0) -> #N/A
A132: Chompa Capucha | B132: M | C132: Perla | D132: Pecho | E132: 2 | F132: =IF(A132="","",VLOOKUP(A132,Cotizador!$A$5:$J$43,2,FALSE)) -> #N/A | G132: =IF(A132="","",VLOOKUP(A132,Cotizador!$A$5:$J$43,3,FALSE)) -> #N/A | H132: =IF(OR(A132="",D132=""),"",IF(D132="Sin estampar",0,IF(D132="Pecho",VLOOKUP(A132,Cotizador!$A$5:$J$43,4,FALSE),IF(D132="Espalda",VLOOKUP(A132,Cotizador!$A$5:$J$43,5,FALSE),VLOOKUP(A132,Cotizador!$A$5:$J$43,4,FALSE)+VLOOKUP(A132,Cotizador!$A$5:$J$43,5,FALSE))))) -> #N/A | I132: =IF(A132="","",VLOOKUP(A132,Cotizador!$A$5:$J$43,6,FALSE)) -> #N/A | J132: =IF(A132="","",VLOOKUP(A132,Cotizador!$A$5:$J$43,7,FALSE)) -> #N/A | K132: =IF(OR(A132="",E132=""),"",(G132+H132+I132+J132)*E132) -> #N/A | L132: =IF(A132="","",IF(D132="Sin estampar",VLOOKUP(A132,Cotizador!$A$5:$J$43,8,FALSE),IF(D132="Pecho",VLOOKUP(A132,Cotizador!$A$5:$J$43,10,FALSE),VLOOKUP(A132,Cotizador!$A$5:$J$43,9,FALSE)))) -> #N/A | M132: =IF(OR(A132="",E132=""),"",L132*E132) -> #N/A | N132: =+G132+H132+I132+J132 -> #N/A | P132: =IF(L132>0,(L132-N132)/L132,0) -> #N/A | Q132: =CONCATENATE(A132," ",B132," ",C132) -> Chompa Capucha M Perla | T132: =SUMIF($Q$48:$Q$181,R132,$E$48:$E$181) -> 0 | V132: =E132*G132 -> #N/A | Y132: =N132 -> #N/A | Z132: =L132 -> #N/A | AB132: =P132 -> #N/A | AC132: =ROUNDUP(L132*0.85,-3) -> #N/A | AD132: =AC132*3 -> #N/A | AE132: =IF(AC132>0,(AC132-N132)/AC132,0) -> #N/A | AF132: =ROUNDUP(L132*0.825,-3) -> #N/A | AG132: =AF132*6 -> #N/A | AH132: =IF(AF132>0,(AF132-N132)/AF132,0) -> #N/A | AI132: =ROUNDUP(L132*0.75,-3) -> #N/A | AJ132: =AI132*12 -> #N/A | AK132: =IF(AI132>0,(AI132-N132)/AI132,0) -> #N/A
A133: Chompa Capucha | B133: L | C133: Perla | D133: Pecho | E133: 2 | F133: =IF(A133="","",VLOOKUP(A133,Cotizador!$A$5:$J$43,2,FALSE)) -> #N/A | G133: =IF(A133="","",VLOOKUP(A133,Cotizador!$A$5:$J$43,3,FALSE)) -> #N/A | H133: =IF(OR(A133="",D133=""),"",IF(D133="Sin estampar",0,IF(D133="Pecho",VLOOKUP(A133,Cotizador!$A$5:$J$43,4,FALSE),IF(D133="Espalda",VLOOKUP(A133,Cotizador!$A$5:$J$43,5,FALSE),VLOOKUP(A133,Cotizador!$A$5:$J$43,4,FALSE)+VLOOKUP(A133,Cotizador!$A$5:$J$43,5,FALSE))))) -> #N/A | I133: =IF(A133="","",VLOOKUP(A133,Cotizador!$A$5:$J$43,6,FALSE)) -> #N/A | J133: =IF(A133="","",VLOOKUP(A133,Cotizador!$A$5:$J$43,7,FALSE)) -> #N/A | K133: =IF(OR(A133="",E133=""),"",(G133+H133+I133+J133)*E133) -> #N/A | L133: =IF(A133="","",IF(D133="Sin estampar",VLOOKUP(A133,Cotizador!$A$5:$J$43,8,FALSE),IF(D133="Pecho",VLOOKUP(A133,Cotizador!$A$5:$J$43,10,FALSE),VLOOKUP(A133,Cotizador!$A$5:$J$43,9,FALSE)))) -> #N/A | M133: =IF(OR(A133="",E133=""),"",L133*E133) -> #N/A | N133: =+G133+H133+I133+J133 -> #N/A | P133: =IF(L133>0,(L133-N133)/L133,0) -> #N/A | Q133: =CONCATENATE(A133," ",B133," ",C133) -> Chompa Capucha L Perla | T133: =SUMIF($Q$48:$Q$181,R133,$E$48:$E$181) -> 0 | V133: =E133*G133 -> #N/A | Y133: =N133 -> #N/A | Z133: =L133 -> #N/A | AB133: =P133 -> #N/A | AC133: =ROUNDUP(L133*0.85,-3) -> #N/A | AD133: =AC133*3 -> #N/A | AE133: =IF(AC133>0,(AC133-N133)/AC133,0) -> #N/A | AF133: =ROUNDUP(L133*0.825,-3) -> #N/A | AG133: =AF133*6 -> #N/A | AH133: =IF(AF133>0,(AF133-N133)/AF133,0) -> #N/A | AI133: =ROUNDUP(L133*0.75,-3) -> #N/A | AJ133: =AI133*12 -> #N/A | AK133: =IF(AI133>0,(AI133-N133)/AI133,0) -> #N/A
A134: Chompa Capucha | B134: S | C134: Verde Botella | D134: Pecho | E134: 1 | F134: =IF(A134="","",VLOOKUP(A134,Cotizador!$A$5:$J$43,2,FALSE)) -> #N/A | G134: =IF(A134="","",VLOOKUP(A134,Cotizador!$A$5:$J$43,3,FALSE)) -> #N/A | H134: =IF(OR(A134="",D134=""),"",IF(D134="Sin estampar",0,IF(D134="Pecho",VLOOKUP(A134,Cotizador!$A$5:$J$43,4,FALSE),IF(D134="Espalda",VLOOKUP(A134,Cotizador!$A$5:$J$43,5,FALSE),VLOOKUP(A134,Cotizador!$A$5:$J$43,4,FALSE)+VLOOKUP(A134,Cotizador!$A$5:$J$43,5,FALSE))))) -> #N/A | I134: =IF(A134="","",VLOOKUP(A134,Cotizador!$A$5:$J$43,6,FALSE)) -> #N/A | J134: =IF(A134="","",VLOOKUP(A134,Cotizador!$A$5:$J$43,7,FALSE)) -> #N/A | K134: =IF(OR(A134="",E134=""),"",(G134+H134+I134+J134)*E134) -> #N/A | L134: =IF(A134="","",IF(D134="Sin estampar",VLOOKUP(A134,Cotizador!$A$5:$J$43,8,FALSE),IF(D134="Pecho",VLOOKUP(A134,Cotizador!$A$5:$J$43,10,FALSE),VLOOKUP(A134,Cotizador!$A$5:$J$43,9,FALSE)))) -> #N/A | M134: =IF(OR(A134="",E134=""),"",L134*E134) -> #N/A | N134: =+G134+H134+I134+J134 -> #N/A | P134: =IF(L134>0,(L134-N134)/L134,0) -> #N/A | Q134: =CONCATENATE(A134," ",B134," ",C134) -> Chompa Capucha S Verde Botella | T134: =SUMIF($Q$48:$Q$181,R134,$E$48:$E$181) -> 0 | V134: =E134*G134 -> #N/A | Y134: =N134 -> #N/A | Z134: =L134 -> #N/A | AB134: =P134 -> #N/A | AC134: =ROUNDUP(L134*0.85,-3) -> #N/A | AD134: =AC134*3 -> #N/A | AE134: =IF(AC134>0,(AC134-N134)/AC134,0) -> #N/A | AF134: =ROUNDUP(L134*0.825,-3) -> #N/A | AG134: =AF134*6 -> #N/A | AH134: =IF(AF134>0,(AF134-N134)/AF134,0) -> #N/A | AI134: =ROUNDUP(L134*0.75,-3) -> #N/A | AJ134: =AI134*12 -> #N/A | AK134: =IF(AI134>0,(AI134-N134)/AI134,0) -> #N/A
A135: Chompa Capucha | B135: M | C135: Verde Botella | D135: Pecho | E135: 2 | F135: =IF(A135="","",VLOOKUP(A135,Cotizador!$A$5:$J$43,2,FALSE)) -> #N/A | G135: =IF(A135="","",VLOOKUP(A135,Cotizador!$A$5:$J$43,3,FALSE)) -> #N/A | H135: =IF(OR(A135="",D135=""),"",IF(D135="Sin estampar",0,IF(D135="Pecho",VLOOKUP(A135,Cotizador!$A$5:$J$43,4,FALSE),IF(D135="Espalda",VLOOKUP(A135,Cotizador!$A$5:$J$43,5,FALSE),VLOOKUP(A135,Cotizador!$A$5:$J$43,4,FALSE)+VLOOKUP(A135,Cotizador!$A$5:$J$43,5,FALSE))))) -> #N/A | I135: =IF(A135="","",VLOOKUP(A135,Cotizador!$A$5:$J$43,6,FALSE)) -> #N/A | J135: =IF(A135="","",VLOOKUP(A135,Cotizador!$A$5:$J$43,7,FALSE)) -> #N/A | K135: =IF(OR(A135="",E135=""),"",(G135+H135+I135+J135)*E135) -> #N/A | L135: =IF(A135="","",IF(D135="Sin estampar",VLOOKUP(A135,Cotizador!$A$5:$J$43,8,FALSE),IF(D135="Pecho",VLOOKUP(A135,Cotizador!$A$5:$J$43,10,FALSE),VLOOKUP(A135,Cotizador!$A$5:$J$43,9,FALSE)))) -> #N/A | M135: =IF(OR(A135="",E135=""),"",L135*E135) -> #N/A | N135: =+G135+H135+I135+J135 -> #N/A | P135: =IF(L135>0,(L135-N135)/L135,0) -> #N/A | Q135: =CONCATENATE(A135," ",B135," ",C135) -> Chompa Capucha M Verde Botella | T135: =SUMIF($Q$48:$Q$181,R135,$E$48:$E$181) -> 0 | V135: =E135*G135 -> #N/A | Y135: =N135 -> #N/A | Z135: =L135 -> #N/A | AB135: =P135 -> #N/A | AC135: =ROUNDUP(L135*0.85,-3) -> #N/A | AD135: =AC135*3 -> #N/A | AE135: =IF(AC135>0,(AC135-N135)/AC135,0) -> #N/A | AF135: =ROUNDUP(L135*0.825,-3) -> #N/A | AG135: =AF135*6 -> #N/A | AH135: =IF(AF135>0,(AF135-N135)/AF135,0) -> #N/A | AI135: =ROUNDUP(L135*0.75,-3) -> #N/A | AJ135: =AI135*12 -> #N/A | AK135: =IF(AI135>0,(AI135-N135)/AI135,0) -> #N/A
A136: Chompa Capucha | B136: L | C136: Verde Botella | D136: Pecho | E136: 2 | F136: =IF(A136="","",VLOOKUP(A136,Cotizador!$A$5:$J$43,2,FALSE)) -> #N/A | G136: =IF(A136="","",VLOOKUP(A136,Cotizador!$A$5:$J$43,3,FALSE)) -> #N/A | H136: =IF(OR(A136="",D136=""),"",IF(D136="Sin estampar",0,IF(D136="Pecho",VLOOKUP(A136,Cotizador!$A$5:$J$43,4,FALSE),IF(D136="Espalda",VLOOKUP(A136,Cotizador!$A$5:$J$43,5,FALSE),VLOOKUP(A136,Cotizador!$A$5:$J$43,4,FALSE)+VLOOKUP(A136,Cotizador!$A$5:$J$43,5,FALSE))))) -> #N/A | I136: =IF(A136="","",VLOOKUP(A136,Cotizador!$A$5:$J$43,6,FALSE)) -> #N/A | J136: =IF(A136="","",VLOOKUP(A136,Cotizador!$A$5:$J$43,7,FALSE)) -> #N/A | K136: =IF(OR(A136="",E136=""),"",(G136+H136+I136+J136)*E136) -> #N/A | L136: =IF(A136="","",IF(D136="Sin estampar",VLOOKUP(A136,Cotizador!$A$5:$J$43,8,FALSE),IF(D136="Pecho",VLOOKUP(A136,Cotizador!$A$5:$J$43,10,FALSE),VLOOKUP(A136,Cotizador!$A$5:$J$43,9,FALSE)))) -> #N/A | M136: =IF(OR(A136="",E136=""),"",L136*E136) -> #N/A | N136: =+G136+H136+I136+J136 -> #N/A | P136: =IF(L136>0,(L136-N136)/L136,0) -> #N/A | Q136: =CONCATENATE(A136," ",B136," ",C136) -> Chompa Capucha L Verde Botella | T136: =SUMIF($Q$48:$Q$181,R136,$E$48:$E$181) -> 0 | V136: =E136*G136 -> #N/A | Y136: =N136 -> #N/A | Z136: =L136 -> #N/A | AB136: =P136 -> #N/A | AC136: =ROUNDUP(L136*0.85,-3) -> #N/A | AD136: =AC136*3 -> #N/A | AE136: =IF(AC136>0,(AC136-N136)/AC136,0) -> #N/A | AF136: =ROUNDUP(L136*0.825,-3) -> #N/A | AG136: =AF136*6 -> #N/A | AH136: =IF(AF136>0,(AF136-N136)/AF136,0) -> #N/A | AI136: =ROUNDUP(L136*0.75,-3) -> #N/A | AJ136: =AI136*12 -> #N/A | AK136: =IF(AI136>0,(AI136-N136)/AI136,0) -> #N/A
A137: Chompa Capucha | B137: S | C137: Plomo Plata | D137: Pecho | E137: 1 | F137: =IF(A137="","",VLOOKUP(A137,Cotizador!$A$5:$J$43,2,FALSE)) -> #N/A | G137: =IF(A137="","",VLOOKUP(A137,Cotizador!$A$5:$J$43,3,FALSE)) -> #N/A | H137: =IF(OR(A137="",D137=""),"",IF(D137="Sin estampar",0,IF(D137="Pecho",VLOOKUP(A137,Cotizador!$A$5:$J$43,4,FALSE),IF(D137="Espalda",VLOOKUP(A137,Cotizador!$A$5:$J$43,5,FALSE),VLOOKUP(A137,Cotizador!$A$5:$J$43,4,FALSE)+VLOOKUP(A137,Cotizador!$A$5:$J$43,5,FALSE))))) -> #N/A | I137: =IF(A137="","",VLOOKUP(A137,Cotizador!$A$5:$J$43,6,FALSE)) -> #N/A | J137: =IF(A137="","",VLOOKUP(A137,Cotizador!$A$5:$J$43,7,FALSE)) -> #N/A | K137: =IF(OR(A137="",E137=""),"",(G137+H137+I137+J137)*E137) -> #N/A | L137: =IF(A137="","",IF(D137="Sin estampar",VLOOKUP(A137,Cotizador!$A$5:$J$43,8,FALSE),IF(D137="Pecho",VLOOKUP(A137,Cotizador!$A$5:$J$43,10,FALSE),VLOOKUP(A137,Cotizador!$A$5:$J$43,9,FALSE)))) -> #N/A | M137: =IF(OR(A137="",E137=""),"",L137*E137) -> #N/A | N137: =+G137+H137+I137+J137 -> #N/A | P137: =IF(L137>0,(L137-N137)/L137,0) -> #N/A | Q137: =CONCATENATE(A137," ",B137," ",C137) -> Chompa Capucha S Plomo Plata | T137: =SUMIF($Q$48:$Q$181,R137,$E$48:$E$181) -> 0 | V137: =E137*G137 -> #N/A | Y137: =N137 -> #N/A | Z137: =L137 -> #N/A | AB137: =P137 -> #N/A | AC137: =ROUNDUP(L137*0.85,-3) -> #N/A | AD137: =AC137*3 -> #N/A | AE137: =IF(AC137>0,(AC137-N137)/AC137,0) -> #N/A | AF137: =ROUNDUP(L137*0.825,-3) -> #N/A | AG137: =AF137*6 -> #N/A | AH137: =IF(AF137>0,(AF137-N137)/AF137,0) -> #N/A | AI137: =ROUNDUP(L137*0.75,-3) -> #N/A | AJ137: =AI137*12 -> #N/A | AK137: =IF(AI137>0,(AI137-N137)/AI137,0) -> #N/A
A138: Chompa Capucha | B138: M | C138: Plomo Plata | D138: Pecho | E138: 2 | F138: =IF(A138="","",VLOOKUP(A138,Cotizador!$A$5:$J$43,2,FALSE)) -> #N/A | G138: =IF(A138="","",VLOOKUP(A138,Cotizador!$A$5:$J$43,3,FALSE)) -> #N/A | H138: =IF(OR(A138="",D138=""),"",IF(D138="Sin estampar",0,IF(D138="Pecho",VLOOKUP(A138,Cotizador!$A$5:$J$43,4,FALSE),IF(D138="Espalda",VLOOKUP(A138,Cotizador!$A$5:$J$43,5,FALSE),VLOOKUP(A138,Cotizador!$A$5:$J$43,4,FALSE)+VLOOKUP(A138,Cotizador!$A$5:$J$43,5,FALSE))))) -> #N/A | I138: =IF(A138="","",VLOOKUP(A138,Cotizador!$A$5:$J$43,6,FALSE)) -> #N/A | J138: =IF(A138="","",VLOOKUP(A138,Cotizador!$A$5:$J$43,7,FALSE)) -> #N/A | K138: =IF(OR(A138="",E138=""),"",(G138+H138+I138+J138)*E138) -> #N/A | L138: =IF(A138="","",IF(D138="Sin estampar",VLOOKUP(A138,Cotizador!$A$5:$J$43,8,FALSE),IF(D138="Pecho",VLOOKUP(A138,Cotizador!$A$5:$J$43,10,FALSE),VLOOKUP(A138,Cotizador!$A$5:$J$43,9,FALSE)))) -> #N/A | M138: =IF(OR(A138="",E138=""),"",L138*E138) -> #N/A | N138: =+G138+H138+I138+J138 -> #N/A | P138: =IF(L138>0,(L138-N138)/L138,0) -> #N/A | Q138: =CONCATENATE(A138," ",B138," ",C138) -> Chompa Capucha M Plomo Plata | T138: =SUMIF($Q$48:$Q$181,R138,$E$48:$E$181) -> 0 | V138: =E138*G138 -> #N/A | Y138: =N138 -> #N/A | Z138: =L138 -> #N/A | AB138: =P138 -> #N/A | AC138: =ROUNDUP(L138*0.85,-3) -> #N/A | AD138: =AC138*3 -> #N/A | AE138: =IF(AC138>0,(AC138-N138)/AC138,0) -> #N/A | AF138: =ROUNDUP(L138*0.825,-3) -> #N/A | AG138: =AF138*6 -> #N/A | AH138: =IF(AF138>0,(AF138-N138)/AF138,0) -> #N/A | AI138: =ROUNDUP(L138*0.75,-3) -> #N/A | AJ138: =AI138*12 -> #N/A | AK138: =IF(AI138>0,(AI138-N138)/AI138,0) -> #N/A
